Workbook

Sheet Executive Summary
B1: DAWN RE ENTERPRISES CORP.
B2: E SUNRISE BLVD ASSEMBLAGE · COVERED LAND PLAY — EXECUTIVE SUMMARY
B3: Fort Lauderdale, FL 33304 · Galleria hard corner · five contiguous assets, plat block 49-42-36-12 · prepared 2026-07-21 · CONFIDENTIAL
B5: INCOME-BASED PRICE | E5: COVERED-LAND PRICE | H5: BLENDED IN-PLACE CAP | K5: LAND CONTROLLED
B6: ='Income Valuation'!C120 | E6: ='Assemblage'!C29 | H6: ='Assemblage'!C23 | K6: ='Assemblage'!C21
B7: what the combined cash flows support | E7: HBU: land value + assemblage premium | H7: income covers carry | K7: acres of E Sunrise frontage
B9: THE DEAL
B10: Assemble the entire E Sunrise Blvd frontage at the Galleria hard corner (~60,000 vehicles/day, across from the 31.5-ac Galleria
B11: redevelopment and the Live Local corridor). Five contiguous assets on one plat block. Strategy: buy/value each asset off the rent it
B12: produces, let the in-place income cover the carry, and control ~7+ acres for eventual Live Local high-density redevelopment. The
B13: redevelopment residual is negative today (AE flood zone, coastal hard costs), so the disciplined play is to HOLD income-covered land.
B14: Publix already validated the thesis — it paid land value ($679/SF building), not income value, to control its parcel.
B16: ASSET SCORECARD — 🟢 live links to each asset tab
B17: Asset | D17: Address / size | G17: Control cost | H17: In-place NOI | J17: Unlev IRR | K17: Lev IRR
B18: Shahidi Retail (Galleria Plaza) | D18: 2541–2595 E Sunrise · 26,272 SF retail | G18: ='Shahidi Retail'!C57 | H18: ='Shahidi Retail'!C122 | J18: ='Shahidi Retail'!C117 | K18: ='Shahidi Retail'!C120
B19: Publix + Starbucks | D19: 2501–2519 E Sunrise · 36,822 SF grocery + pad | G19: ='Publix & Starbucks'!C44 | H19: ='Publix & Starbucks'!C109 | J19: ='Publix & Starbucks'!C104 | K19: ='Publix & Starbucks'!C107
B20: Sunrise Plaza (Kar Luen) | D20: 2465–2485 E Sunrise · 25,105 SF retail | G20: ='Sunrise Plaza'!C47 | H20: ='Sunrise Plaza'!C112 | J20: ='Sunrise Plaza'!C107 | K20: ='Sunrise Plaza'!C110
B21: Galleria Corporate Centre | D21: 2455 E Sunrise · 168,807 SF office condo | G21: ='Office Condo'!I97 | H21: ='Office Condo'!C78 | J21: ='Office Condo'!C73 | K21: ='Office Condo'!C76
B22: 1040 Bayview (land) | D22: 1040 Bayview Dr · 2.39 ac · 259 units entitled | G22: ='Land'!E40 | H22: ='Land'!C47 | J22: ='Land'!C65 | K22: ='Land'!C68
B23: ASSEMBLAGE (pre-premium) | D23: 5 assets · ~7+ ac · 341,501 SF bldg | G23: ='Assemblage'!C17 | H23: ='Assemblage'!D17 | J23: ='Income Valuation'!C90 | K23: ='Income Valuation'!C92
B24: Portfolio IRR (unlev / lev) = consolidated cash-flow IRR at the income price (Income Valuation tab)
B26: CAPITAL, VALUATION & COVERED-LAND MATH
B27: ① Income-based price (assemblage cash flows) | C27: ='Income Valuation'!C120 | D27: direct cap on consolidated in-place NOI
B28: ② Sum of the parts (priced independently) | C28: ='Highest & Best Use'!C11 | D28: each component on its own
B29: ③ Covered-land / HBU price (assembled) | C29: ='Assemblage'!C29 | D29: sum of parts + assemblage premium
B30: Premium over income value (dirt + optionality) | C30: ='Income Valuation'!C122 | D30: ③ − ① = the land / Live Local option cost
B31: Office condo FULL BUY-OUT (both owners) | C31: ='Office Condo'!I97 | D31: Main St 57.4% + Intl Sunrise 42.6% + premium
B32: Land — fragmented vs. assembled (plottage) | C32: ='Highest & Best Use'!C39 | D32: assembled land worth this much more than the parts
B33: Summed control cost (pre-premium) | C33: ='Assemblage'!C17
B34: Total equity required (all assets, HBU) | C34: ='Assemblage'!C36
B35: Total in-place NOI | C35: ='Assemblage'!D17 | D35: covers debt service + taxes during hold
B36: Blended in-place cap | C36: ='Assemblage'!C23 | D36: covered-land ~3–5% range
B37: Total land assembled (SF) | C37: ='Assemblage'!F17
B38: Blended land basis ($/SF) | C38: ='Assemblage'!C22 | D38: vs. subject comps $228–255/SF
B39: Total land value | C39: ='Assemblage'!G17
B40: Redevelopment residual (Live Local) | C40: ='Land'!C78 | D40: NEGATIVE → hold, do not redevelop yet
B42: RETURNS AT THE INCOME PRICE & SCENARIO RANGE
B43: Portfolio unlevered / levered IRR (base) | C43: ='Income Valuation'!C92 | D43: levered; unlevered on Income Valuation tab
B44: Levered IRR — downside / base / upside | C44: ='Scenarios'!G22 | D44: ='Income Valuation'!C92 | E44: ='Scenarios'!G24 | F44: recession → plan → tailwind (see Scenarios tab)
B45: Avg cash-on-cash (base, levered) | C45: ='Income Valuation'!C96 | D45: current yield on equity
B46: Break-even exit cap (return of capital) | C46: ='Income Valuation'!C116 | D46: downside guardrail; underwritten exit 6.75%
B47: Total equity (income price) / LTC | C47: ='Income Valuation'!C84 | D47: see Sources & Uses on Income Valuation tab
B49: RECOMMENDATION
B50: ACQUIRE & HOLD as a covered land play. Pursue the acquirable parcels (Shahidi, Sunrise Plaza, the two office-condo owners, and
B51: the Bayview land); structure Publix as a SALE-LEASEBACK — acquire the fee and lease it back during entitlement. The blended in-place income covers the
B52: carry, individual assets deliver value-add / income returns in their own right, and the assemblage banks ~7+ acres of the Galleria
B53: hard corner for Live Local density once coastal hard costs and achievable rents make redevelopment pencil. Do not underwrite the
B54: redevelopment as accretive today — the residual is negative. The return is optionality on the dirt, paid for by the rent.
B56: Confidence flags | D56: ✅ Shahidi & Publix = BCPA-verified · ⚠️ Sunrise Plaza, Office, Land = reported (BCPA blocked in build env — verify at bcpa.net) · 🔶 all rents/caps modeled

Sheet Assumptions
B1: ASSUMPTIONS — CONTROL PANEL
B2: The single input surface. GLOBAL drivers first, then a block per asset (price · rents · occupancy · OPERATING EXPENSES · caps · debt). Every blue cell drives the model by live link — change one and price, IRR, DSCR, and value all recalculate.
B4: GLOBAL — VALUATION & HOLD (→ Income Valuation)
B5: Driver | C5: Input | D5: Flag | E5: Drives / note
B6: Blended going-in cap (as-is) | C6: 0.065 | D6: 🔶 | E6: income price = as-is NOI ÷ this
B7: Blended stabilized / exit cap | C7: 0.0675 | D7: 🔶 | E7: reversion & stabilized value
B8: Target unlevered yield (DCF discount) | C8: 0.085 | D8: 🔶 | E8: DCF value; NPV hurdle
B9: Blended NOI growth | C9: 0.025 | D9: 🔶 | E9: reversion & sensitivities
B10: Hold period (yrs) | C10: 5 | D10: 🔶 | E10: exit year for all assets
B11: Cost of sale at exit | C11: 0.02 | D11: 🔶 | E11: net reversion
B12: GLOBAL — SENIOR FINANCING (→ Income Valuation)
B13: Driver | C13: Input | D13: Flag | E13: Drives / note
B14: Max senior LTV | C14: 0.6 | D14: 🔶 | E14: debt sizing constraint 1
B15: Min DSCR | C15: 1.3 | D15: 🔶 | E15: debt sizing constraint 2
B16: Min debt yield | C16: 0.085 | D16: 🔶 | E16: debt sizing constraint 3
B17: Senior rate | C17: 0.065 | D17: 🔶 | E17: debt service
B18: Amortization (yrs) | C18: 30 | D18: 🔶 | E18: mortgage constant
B19: GLOBAL — ACQUISITION COSTS (→ Income Valuation Sources & Uses)
B20: Driver | C20: Input | D20: Flag | E20: Drives / note
B21: Doc-stamp / transfer tax (% price) | C21: 0.007 | D21: 🔶 | E21: FL Broward $0.70/$100
B22: Title insurance (% price) | C22: 0.005 | D22: 🔶 | E22: closing cost
B23: Legal & due diligence (% price) | C23: 0.004 | D23: 🔶 | E23: closing cost
B24: Loan origination (% loan) | C24: 0.01 | D24: 🔶 | E24: financing cost → equity
B25: GLOBAL — ASSEMBLAGE PREMIUM (→ Assemblage / covered-land price)
B26: Driver | C26: Input | D26: Flag | E26: Drives / note
B27: Assemblage premium — low | C27: 0.15 | D27: 🔶 | E27: control-cost premium
B28: Assemblage premium — base | C28: 0.2 | D28: 🔶 | E28: headline covered-land price
B29: Assemblage premium — high | C29: 0.25 | D29: 🔶 | E29: aggressive case
B30: GLOBAL — LAND & REDEVELOPMENT (1040 Bayview) (→ Land tab)
B31: Driver | C31: Input | D31: Flag | E31: Drives / note
B32: Entitlement lift (% uplift post-Live Local approval) | C32: 0.3 | D32: 🔶 | E32: assembled land value bump once entitled
B33: Land value — low ($/SF) | C33: 64 | D33: 🔶 | E33: BCPA-implied floor
B34: Land value — base ($/SF) | C34: 125 | D34: 🔶 | E34: mid-block corridor
B35: Land value — high ($/SF) | C35: 200 | D35: 🔶 | E35: toward hard-corner comps
B36: Per entitled unit — low ($) | C36: 40000 | D36: 🔶 | E36: 259 units
B37: Per entitled unit — base ($) | C37: 55000 | D37: 🔶 | E37: entitled-land value
B38: Per entitled unit — high ($) | C38: 70000 | D38: 🔶 | E38: strong entitlement
B39: Achievable value per unit ($) | C39: 600000 | D39: 🔶 | E39: sellout / cap'd rental
B40: Hard cost ($/GBA SF) | C40: 500 | D40: 🔶 | E40: AE-zone coastal
B41: GBA per unit (SF) | C41: 950 | D41: 🔶 | E41: gross buildable/unit
B42: Soft cost (% hard) | C42: 0.2 | D42: 🔶 | E42: A&E, financing, fees
B43: Developer profit (% GDV) | C43: 0.15 | D43: 🔶 | E43: required margin
B45: PER-ASSET INPUTS — value drivers & OPERATING EXPENSES (each asset tab reads these)
B46: Shahidi Retail (Galleria Plaza) — NNN retail ✅ verified parcel
B47: Purchase price / basis | C47: 17100000
B48: Land (SF) | C48: 67080
B49: Land value ($/SF) | C49: 254.92
B50: Market rent ($/SF NNN) | C50: 55
B51: In-place occupancy | C51: 0.8317
B52: Stabilized occupancy | C52: 0.95
B53: Insurance ($/yr) | C53: 65000
B54: CAM ($/yr, recoverable) | C54: 55000
B55: Repairs & maintenance ($/yr) | C55: 40000
B56: Management fee (% EGR) | C56: 0.04
B57: Going-in cap | C57: 0.06
B58: Exit cap | C58: 0.06
... B60: Senior rate | C60: 0.0675
B62: Publix + Starbucks — SALE-LEASEBACK (acquire fee, lease back during entitlement) ✅ verified parcel
B63: SLB acquisition price (fee) | C63: 25000000
B64: Land (SF) | C64: 109791
B65: Land value ($/SF) | C65: 227.75
B66: Publix leaseback rent ($/SF NNN) | C66: 22
B67: Publix leaseback SF | C67: 34622
B68: Starbucks pad rent ($/SF NNN) | C68: 60
B69: Starbucks pad SF | C69: 2200
B70: Leaseback term / entitlement (yrs) | C70: 4
B71: In-place occupancy | C71: 1
B72: Stabilized occupancy | C72: 1
B73: Insurance ($/yr) | C73: 45000
B74: CAM ($/yr, recoverable) | C74: 35000
... B80: Senior rate | C80: 0.0625
B82: Sunrise Plaza (Kar Luen) — value-add retail ⚠️ reported parcel
B83: Purchase price / basis | C83: 8500000
B84: Land (SF) | C84: 30928
B85: Land value ($/SF) | C85: 248
B86: Market rent ($/SF NNN) | C86: 34
B87: In-place occupancy | C87: 0.801
B88: Stabilized occupancy | C88: 0.95
B89: Insurance ($/yr) | C89: 40000
B90: CAM ($/yr, recoverable) | C90: 40000
B91: Repairs & maintenance ($/yr) | C91: 30000
B92: Management fee (% EGR) | C92: 0.04
B93: Going-in cap | C93: 0.075
B94: Exit cap | C94: 0.0775
... B96: Senior rate | C96: 0.075
B98: Galleria Corporate Centre — office, Modified Gross ⚠️ reported parcel
B99: Acquisition basis | C99: 21700000
B100: Market rent ($/SF MG) | C100: 26
B101: In-place occupancy | C101: 0.85
B102: Stabilized occupancy | C102: 0.88
B103: Office opex ex-taxes ($/SF, landlord) | C103: 8
B104: Management fee (% EGR) | C104: 0.03
B105: Going-in cap | C105: 0.08
B106: Exit cap | C106: 0.0825
B107: Senior LTV | C107: 0.55
B108: Senior rate | C108: 0.075
B110: 1040 Bayview — covered land (interim office) ⚠️ reported parcel
B111: Acquisition basis (entitled land) | C111: 13000000
B112: Interim office occupancy | C112: 0.72
B113: Interim office rent ($/SF MG) | C113: 23
...

Sheet Income Valuation
B1: ASSEMBLAGE — INCOME VALUATION (CONSOLIDATED CASH FLOWS)
B2: Combine every asset's cash flow → value the block on the income it produces (as-is + stabilized + DCF) → contrast with the covered-land / highest-and-best-use price. Portfolio returns run off consolidated cash flows.
B4: HOW THIS DIFFERS FROM THE HBU ASSEMBLAGE
B5: The Assemblage tab prices the block on a highest-and-best-use / covered-land basis (land value + assemblage premium to control every
B6: parcel). This tab prices the SAME block on the income it produces. Income-producing real estate is worth the rent it throws off — which
B7: is less than the land-control price. Returns are computed by consolidating the actual cash flows and running one IRR (not by averaging
B8: asset IRRs, which is mathematically invalid). Debt is sized to the lesser of LTV / DSCR / debt-yield, the way a lender underwrites.
B10: CONSOLIDATED CASH FLOW — 10-year annual (🟢 links to each asset tab)
B11: Year | D11: 1 | E11: 2 | F11: 3 | G11: 4 | H11: 5 | I11: 6 | J11: 7 | K11: 8 | L11: 9 | M11: 10
B12: Year ending | D12: Dec-2027 | E12: Dec-2028 | F12: Dec-2029 | G12: Dec-2030 | H12: Dec-2031 | I12: Dec-2032 | J12: Dec-2033 | K12: Dec-2034 | L12: Dec-2035 | M12: Dec-2036
B13: NET OPERATING INCOME by asset
B14: Shahidi Retail (Galleria Plaza) | D14: ='Shahidi Retail'!D100 | E14: ='Shahidi Retail'!E100 | F14: ='Shahidi Retail'!F100 | G14: ='Shahidi Retail'!G100 | H14: ='Shahidi Retail'!H100 | I14: ='Shahidi Retail'!I100 | J14: ='Shahidi Retail'!J100 | K14: ='Shahidi Retail'!K100 | ... M14: ='Shahidi Retail'!M100
B15: Publix + Starbucks | D15: ='Publix & Starbucks'!D87 | E15: ='Publix & Starbucks'!E87 | F15: ='Publix & Starbucks'!F87 | G15: ='Publix & Starbucks'!G87 | H15: ='Publix & Starbucks'!H87 | I15: ='Publix & Starbucks'!I87 | J15: ='Publix & Starbucks'!J87 | K15: ='Publix & Starbucks'!K87 | ... M15: ='Publix & Starbucks'!M87
B16: Sunrise Plaza (Kar Luen) | D16: ='Sunrise Plaza'!D90 | E16: ='Sunrise Plaza'!E90 | F16: ='Sunrise Plaza'!F90 | G16: ='Sunrise Plaza'!G90 | H16: ='Sunrise Plaza'!H90 | I16: ='Sunrise Plaza'!I90 | J16: ='Sunrise Plaza'!J90 | K16: ='Sunrise Plaza'!K90 | ... M16: ='Sunrise Plaza'!M90
B17: Galleria Corporate Centre (office) | D17: ='Office Condo'!D61 | E17: ='Office Condo'!E61 | F17: ='Office Condo'!F61 | G17: ='Office Condo'!G61 | H17: ='Office Condo'!H61 | I17: ='Office Condo'!I61 | J17: ='Office Condo'!J61 | K17: ='Office Condo'!K61 | ... M17: ='Office Condo'!M61
B18: 1040 Bayview (interim office) | D18: ='Land'!D58 | E18: ='Land'!E58 | F18: ='Land'!F58 | G18: ='Land'!G58 | H18: ='Land'!H58 | I18: ='Land'!I58 | J18: ='Land'!J58 | K18: ='Land'!K58 | ... M18: ='Land'!M58
B19: Consolidated NOI | D19: =SUM(D14:D18) | E19: =SUM(E14:E18) | F19: =SUM(F14:F18) | G19: =SUM(G14:G18) | H19: =SUM(H14:H18) | I19: =SUM(I14:I18) | J19: =SUM(J14:J18) | K19: =SUM(K14:K18) | ... M19: =SUM(M14:M18)
B20: Less: consolidated capital (reserves + leasing) | D20: =-('Shahidi Retail'!D104+'Publix & Starbucks'!D91+'Sunrise Plaza'!D94+'Office Condo'!D62) | E20: =-('Shahidi Retail'!E104+'Publix & Starbucks'!E91+'Sunrise Plaza'!E94+'Office Condo'!E62) | F20: =-('Shahidi Retail'!F104+'Publix & Starbucks'!F91+'Sunrise Plaza'!F94+'Office Condo'!F62) | G20: =-('Shahidi Retail'!G104+'Publix & Starbucks'!G91+'Sunrise Plaza'!G94+'Office Condo'!G62) | H20: =-('Shahidi Retail'!H104+'Publix & Starbucks'!H91+'Sunrise Plaza'!H94+'Office Condo'!H62) | I20: =-('Shahidi Retail'!I104+'Publix & Starbucks'!I91+'Sunrise Plaza'!I94+'Office Condo'!I62) | J20: =-('Shahidi Retail'!J104+'Publix & Starbucks'!J91+'Sunrise Plaza'!J94+'Office Condo'!J62) | K20: =-('Shahidi Retail'!K104+'Publix & Starbucks'!K91+'Sunrise Plaza'!K94+'Office Condo'!K62) | ... M20: =-('Shahidi Retail'!M104+'Publix & Starbucks'!M91+'Sunrise Plaza'!M94+'Office Condo'!M62)
B21: Consolidated unlevered operating CF | D21: =D19+D20 | E21: =E19+E20 | F21: =F19+F20 | G21: =G19+G20 | H21: =H19+H20 | I21: =I19+I20 | J21: =J19+J20 | K21: =K19+K20 | ... M21: =M19+M20
B22: Consolidated reversion (net sale, exit yr) | D22: ='Shahidi Retail'!D108+'Publix & Starbucks'!D95+'Sunrise Plaza'!D98+'Office Condo'!D66+'Land'!D59 | E22: ='Shahidi Retail'!E108+'Publix & Starbucks'!E95+'Sunrise Plaza'!E98+'Office Condo'!E66+'Land'!E59 | F22: ='Shahidi Retail'!F108+'Publix & Starbucks'!F95+'Sunrise Plaza'!F98+'Office Condo'!F66+'Land'!F59 | G22: ='Shahidi Retail'!G108+'Publix & Starbucks'!G95+'Sunrise Plaza'!G98+'Office Condo'!G66+'Land'!G59 | H22: ='Shahidi Retail'!H108+'Publix & Starbucks'!H95+'Sunrise Plaza'!H98+'Office Condo'!H66+'Land'!H59 | I22: ='Shahidi Retail'!I108+'Publix & Starbucks'!I95+'Sunrise Plaza'!I98+'Office Condo'!I66+'Land'!I59 | J22: ='Shahidi Retail'!J108+'Publix & Starbucks'!J95+'Sunrise Plaza'!J98+'Office Condo'!J66+'Land'!J59 | K22: ='Shahidi Retail'!K108+'Publix & Starbucks'!K95+'Sunrise Plaza'!K98+'Office Condo'!K66+'Land'!K59 | ... M22: ='Shahidi Retail'!M108+'Publix & Starbucks'!M95+'Sunrise Plaza'!M98+'Office Condo'!M66+'Land'!M59
B24: AS-IS vs. STABILIZED NOI (going-in vs. lease-up complete)
B25: Consolidated AS-IS in-place NOI | C25: ='Shahidi Retail'!C122+'Publix & Starbucks'!C110+'Sunrise Plaza'!C113+'Office Condo'!C79+'Land'!C47 | D25: current occupancy, no lease-up (going-in)
B26: Consolidated STABILIZED NOI (lease-up complete) | C26: ='Shahidi Retail'!C124+'Publix & Starbucks'!C112+'Sunrise Plaza'!C115+'Office Condo'!C81+'Land'!C47 | D26: post lease-up (Shahidi to 95%, Sunrise to 95%, office to 88%)
B27: Value creation (lease-up NOI gain) | C27: =C26-C25
B29: INCOME-VALUATION ASSUMPTIONS — 🟢 linked from the Assumptions control tab (adjust there)
B30: Blended going-in cap (as-is) | C30: ='Assumptions'!C6 | D30: 🟢 Assumptions tab
B31: Blended stabilized / exit cap | C31: ='Assumptions'!C7 | D31: 🟢 Assumptions tab
B32: Target unlevered yield (DCF discount) | C32: ='Assumptions'!C8 | D32: 🟢 Assumptions tab
B33: Blended NOI growth | C33: ='Assumptions'!C9 | D33: 🟢 Assumptions tab
B34: Hold period (yrs) | C34: ='Assumptions'!C10 | D34: 🟢 Assumptions tab
B35: Cost of sale at exit | C35: ='Assumptions'!C11 | D35: 🟢 Assumptions tab
B36: Doc-stamp / transfer tax (% price) | C36: ='Assumptions'!C21 | D36: 🟢 Assumptions tab
B37: Title insurance (% price) | C37: ='Assumptions'!C22 | D37: 🟢 Assumptions tab
B38: Legal & due diligence (% price) | C38: ='Assumptions'!C23 | D38: 🟢 Assumptions tab
B39: Loan origination fee (% loan) | C39: ='Assumptions'!C24 | D39: 🟢 Assumptions tab
B40: Max senior LTV | C40: ='Assumptions'!C14 | D40: 🟢 Assumptions tab
B41: Min DSCR (sizing constraint) | C41: ='Assumptions'!C15 | D41: 🟢 Assumptions tab
B42: Min debt yield (sizing constraint) | C42: ='Assumptions'!C16 | D42: 🟢 Assumptions tab
B43: Senior rate | C43: ='Assumptions'!C17 | D43: 🟢 Assumptions tab
B44: Amortization (yrs) | C44: ='Assumptions'!C18 | D44: 🟢 Assumptions tab
B46: SIZING HELPERS
B47: Monthly rate | C47: =C43/12
B48: Mortgage constant (annual) | C48: =(C47/(1-(1+C47)^(-C44*12)))*12 | D48: DS ÷ loan
B49: Total transaction cost (% price) | C49: =C36+C37+C38 | D49: doc stamps + title + legal/DD
B50: Σ unlevered operating CF, Yr 1–hold | C50: =SUM(D21:INDEX(D21:M21,C34))
B51: Exit-year consolidated NOI | C51: =INDEX(D19:M19,C34)
B52: Base-case consolidated reversion | C52: =INDEX(D22:M22,C34) | D52: sum of asset reversions
B54: PURCHASE PRICE ON THE BASIS OF ASSEMBLAGE CASH FLOWS
B55: ① As-is value (as-is NOI ÷ going-in cap) | C55: =C25/C30 | D55: going-in income value
B56: ② Stabilized value (stab NOI ÷ exit cap) | C56: =C26/C31 | D56: post lease-up
B57: Valuation CF (op CF ≤ hold + reversion) | D57: =IF(1<=C34,D21,0)+IF(1=C34,D22,0) | E57: =IF(2<=C34,E21,0)+IF(2=C34,E22,0) | F57: =IF(3<=C34,F21,0)+IF(3=C34,F22,0) | G57: =IF(4<=C34,G21,0)+IF(4=C34,G22,0) | H57: =IF(5<=C34,H21,0)+IF(5=C34,H22,0) | I57: =IF(6<=C34,I21,0)+IF(6=C34,I22,0) | J57: =IF(7<=C34,J21,0)+IF(7=C34,J22,0) | K57: =IF(8<=C34,K21,0)+IF(8=C34,K22,0) | L57: =IF(9<=C34,L21,0)+IF(9=C34,L22,0) | M57: =IF(10<=C34,M21,0)+IF(10=C34,M22,0)
B58: ③ DCF value (PV @ target unlevered yield) | C58: =NPV(C32,D57:M57) | D58: price where unlevered IRR = target
B59: CONCLUDED INCOME-BASED PURCHASE PRICE | C59: =C55 | D59: 🔶 as-is direct cap; ②/③ cross-check
B61: SENIOR DEBT SIZING — lesser of LTV / DSCR / debt-yield (sized on as-is NOI)
B62: Loan by max LTV | C62: =C59*C40
B63: Loan by min DSCR | C63: =C25/(C41*C48)
B64: Loan by min debt yield | C64: =C25/C42
B65: SIZED SENIOR LOAN (binding constraint) | C65: =MIN(C62,C63,C64) | D65: =IF(C65=C62,"LTV-constrained",IF(C65=C63,"DSCR-constrained","Debt-yield-constrained"))
B66: Annual debt service | C66: =C65*C48
B67: Loan balance at exit | C67: =C65*(1+C47)^(12*C34)-(C66/12)*((1+C47)^(12*C34)-1)/C47
B68: Equity required (at income price) | C68: =C59*(1+C49)+C39*C65-C65
B70: SOURCES & USES (at the income-based price)
B71: USES | E71: SOURCES
B72: Purchase price | C72: =C59 | E72: Senior loan (sized) | F72: =C65
B73: Doc-stamp / transfer tax | C73: =C59*C36 | E73: Sponsor equity (plug) | F73: =C68
B74: Title insurance | C74: =C59*C37
B75: Legal & due diligence | C75: =C59*C38
B76: Loan origination fee | C76: =C39*C65
B77: TOTAL USES | C77: =SUM(C72:C76) | E77: TOTAL SOURCES | F77: =F72+F73
B78: Check (sources − uses) | C78: =F77-C77 | E78: Loan-to-cost (LTC) | F78: =F72/C77
B80: PORTFOLIO RETURNS — consolidated cash-flow IRR at income price vs. covered-land price
B81: Scenario | C81: ① Income price | E81: ② Covered-land (HBU)
B82: Purchase price | C82: =C59 | E82: ='Assemblage'!C29
B83: Sized senior loan | C83: =C65 | E83: =MIN('Assemblage'!C29*C40,C63,C64)
B84: Equity required | C84: =C59*(1+C49)+C39*C83-C83 | E84: ='Assemblage'!C29*(1+C49)+C39*E83-E83
B85: Going-in cap (as-is NOI ÷ price) | C85: =C25/C59 | E85: =C25/'Assemblage'!C29
B86: Unlevered CF ① (acq + valuation CF) | C86: =-C59*(1+C49) | D86: =D57 | E86: =E57 | F86: =F57 | G86: =G57 | H86: =H57 | I86: =I57 | J86: =J57 | K86: =K57 | ... M86: =M57
B87: Unlevered CF ② (acq + valuation CF) | C87: =-'Assemblage'!C29*(1+C49) | D87: =D57 | E87: =E57 | F87: =F57 | G87: =G57 | H87: =H57 | I87: =I57 | J87: =J57 | K87: =K57 | ... M87: =M57
B88: Levered CF ① (equity) | C88: =-C84 | D88: =IF(1<=C34,D21-C83*C48,0)+IF(1=C34,D22-(C83*(1+C47)^(12*C34)-(C83*C48/12)*((1+C47)^(12*C34)-1)/C47),0) | E88: =IF(2<=C34,E21-C83*C48,0)+IF(2=C34,E22-(C83*(1+C47)^(12*C34)-(C83*C48/12)*((1+C47)^(12*C34)-1)/C47),0) | F88: =IF(3<=C34,F21-C83*C48,0)+IF(3=C34,F22-(C83*(1+C47)^(12*C34)-(C83*C48/12)*((1+C47)^(12*C34)-1)/C47),0) | G88: =IF(4<=C34,G21-C83*C48,0)+IF(4=C34,G22-(C83*(1+C47)^(12*C34)-(C83*C48/12)*((1+C47)^(12*C34)-1)/C47),0) | H88: =IF(5<=C34,H21-C83*C48,0)+IF(5=C34,H22-(C83*(1+C47)^(12*C34)-(C83*C48/12)*((1+C47)^(12*C34)-1)/C47),0) | I88: =IF(6<=C34,I21-C83*C48,0)+IF(6=C34,I22-(C83*(1+C47)^(12*C34)-(C83*C48/12)*((1+C47)^(12*C34)-1)/C47),0) | J88: =IF(7<=C34,J21-C83*C48,0)+IF(7=C34,J22-(C83*(1+C47)^(12*C34)-(C83*C48/12)*((1+C47)^(12*C34)-1)/C47),0) | K88: =IF(8<=C34,K21-C83*C48,0)+IF(8=C34,K22-(C83*(1+C47)^(12*C34)-(C83*C48/12)*((1+C47)^(12*C34)-1)/C47),0) | L88: =IF(9<=C34,L21-C83*C48,0)+IF(9=C34,L22-(C83*(1+C47)^(12*C34)-(C83*C48/12)*((1+C47)^(12*C34)-1)/C47),0) | M88: =IF(10<=C34,M21-C83*C48,0)+IF(10=C34,M22-(C83*(1+C47)^(12*C34)-(C83*C48/12)*((1+C47)^(12*C34)-1)/C47),0)
B89: Levered CF ② (equity) | C89: =-E84 | D89: =IF(1<=C34,D21-E83*C48,0)+IF(1=C34,D22-(E83*(1+C47)^(12*C34)-(E83*C48/12)*((1+C47)^(12*C34)-1)/C47),0) | E89: =IF(2<=C34,E21-E83*C48,0)+IF(2=C34,E22-(E83*(1+C47)^(12*C34)-(E83*C48/12)*((1+C47)^(12*C34)-1)/C47),0) | F89: =IF(3<=C34,F21-E83*C48,0)+IF(3=C34,F22-(E83*(1+C47)^(12*C34)-(E83*C48/12)*((1+C47)^(12*C34)-1)/C47),0) | G89: =IF(4<=C34,G21-E83*C48,0)+IF(4=C34,G22-(E83*(1+C47)^(12*C34)-(E83*C48/12)*((1+C47)^(12*C34)-1)/C47),0) | H89: =IF(5<=C34,H21-E83*C48,0)+IF(5=C34,H22-(E83*(1+C47)^(12*C34)-(E83*C48/12)*((1+C47)^(12*C34)-1)/C47),0) | I89: =IF(6<=C34,I21-E83*C48,0)+IF(6=C34,I22-(E83*(1+C47)^(12*C34)-(E83*C48/12)*((1+C47)^(12*C34)-1)/C47),0) | J89: =IF(7<=C34,J21-E83*C48,0)+IF(7=C34,J22-(E83*(1+C47)^(12*C34)-(E83*C48/12)*((1+C47)^(12*C34)-1)/C47),0) | K89: =IF(8<=C34,K21-E83*C48,0)+IF(8=C34,K22-(E83*(1+C47)^(12*C34)-(E83*C48/12)*((1+C47)^(12*C34)-1)/C47),0) | L89: =IF(9<=C34,L21-E83*C48,0)+IF(9=C34,L22-(E83*(1+C47)^(12*C34)-(E83*C48/12)*((1+C47)^(12*C34)-1)/C47),0) | M89: =IF(10<=C34,M21-E83*C48,0)+IF(10=C34,M22-(E83*(1+C47)^(12*C34)-(E83*C48/12)*((1+C47)^(12*C34)-1)/C47),0)
B90: Unlevered IRR | C90: =IRR(C86:M86) | E90: =IRR(C87:M87)
B91: Unlevered equity multiple | C91: =SUM(D86:M86)/-C86 | E91: =SUM(D87:M87)/-C87
B92: Levered IRR | C92: =IRR(C88:M88) | E92: =IRR(C89:M89)
B93: Levered equity multiple | C93: =SUM(D88:M88)/C84 | E93: =SUM(D89:M89)/E84
B94: Year-1 DSCR | C94: =C25/(C83*C48) | E94: =C25/(E83*C48)
B95: Cash-on-cash ① by year (levered) | D95: =IF(1<=C34,(D21-C83*C48)/C84,0) | E95: =IF(2<=C34,(E21-C83*C48)/C84,0) | F95: =IF(3<=C34,(F21-C83*C48)/C84,0) | G95: =IF(4<=C34,(G21-C83*C48)/C84,0) | H95: =IF(5<=C34,(H21-C83*C48)/C84,0) | I95: =IF(6<=C34,(I21-C83*C48)/C84,0) | J95: =IF(7<=C34,(J21-C83*C48)/C84,0) | K95: =IF(8<=C34,(K21-C83*C48)/C84,0) | L95: =IF(9<=C34,(L21-C83*C48)/C84,0) | M95: =IF(10<=C34,(M21-C83*C48)/C84,0)
B96: Avg cash-on-cash (Yr 1–hold) | C96: =SUM(D95:M95)/C34 | E96: =(( C50-C34*E83*C48)/C34)/E84
B98: COVERED-LAND JUSTIFICATION — land appreciation required to make the HBU price work
B99: Premium paid over income value | C99: ='Assemblage'!C29-C59 | D99: the dirt / optionality cost
B100: Land CAGR over hold to recover the premium | C100: =((C59+C99)/C59)^(1/C34)-1 | D100: annual land-value growth needed just to break even on the premium at exit
B101: Read | D101: At the covered-land price the income IRR is thin — the return thesis is land appreciation / redevelopment, not current yield. The premium only pencils if land compounds at ≥ the rate above over the hold.
B103: RETURN ATTRIBUTION — where the unlevered profit comes from (at income price)
B104: Exit-year forward NOI (grown into sale) | C104: =C51*(1+C33)
B105: Gross exit value (from consolidated reversion) | C105: =C52/(1-C35)
B106: ＋ Operating cash flow (Yr 1–hold) | C106: =C50
B107: ＋ Value from NOI growth / lease-up | C107: =(C104-C25)/C30
B108: ＋/− Value from cap-rate movement | C108: =C105-C104/C30
B109: − Cost of sale at exit | C109: =-C105*C35
B110: − Acquisition transaction costs | C110: =-C59*C49
B111: UNLEVERED PROFIT (sum of the above) | C111: =C106+C107+C108+C109+C110
...

Sheet Scenarios
B1: SCENARIO ANALYSIS — DOWNSIDE / BASE / UPSIDE
B2: Acquisition held at the base income price; the business plan is stressed on NOI achievement, exit cap, and financing rate. Each case is a full consolidated cash flow with its own levered/unlevered return.
B4: SCENARIO DRIVERS — 🔵 blue inputs
B5: Scenario | C5: NOI achieved | D5: Exit cap | E5: Senior rate
B6: Downside | C6: 0.92 | D6: 0.0725 | E6: 0.0725
B7: Base | C7: 1 | D7: 0.0675 | E7: 0.065
B8: Upside | C8: 1.06 | D8: 0.0625 | E8: 0.06
B9: Base income price (fixed basis) | C9: ='Income Valuation'!C59 | E9: loan & equity held fixed; only the senior rate varies debt service across cases
B11: CONSOLIDATED CASH FLOW BY SCENARIO (unlevered & levered)
B12: Year | C12: 0/Acq | D12: 1 | E12: 2 | F12: 3 | G12: 4 | H12: 5 | I12: 6 | J12: 7 | K12: 8 | L12: 9 | M12: 10
B13: Downside — unlevered CF | C13: =-'Income Valuation'!C59*(1+'Income Valuation'!C49) | D13: =IF(1<='Income Valuation'!C34,'Income Valuation'!D21*C6,0)+IF(1='Income Valuation'!C34,('Income Valuation'!C52*C6*D7/D6),0) | E13: =IF(2<='Income Valuation'!C34,'Income Valuation'!E21*C6,0)+IF(2='Income Valuation'!C34,('Income Valuation'!C52*C6*D7/D6),0) | F13: =IF(3<='Income Valuation'!C34,'Income Valuation'!F21*C6,0)+IF(3='Income Valuation'!C34,('Income Valuation'!C52*C6*D7/D6),0) | G13: =IF(4<='Income Valuation'!C34,'Income Valuation'!G21*C6,0)+IF(4='Income Valuation'!C34,('Income Valuation'!C52*C6*D7/D6),0) | H13: =IF(5<='Income Valuation'!C34,'Income Valuation'!H21*C6,0)+IF(5='Income Valuation'!C34,('Income Valuation'!C52*C6*D7/D6),0) | I13: =IF(6<='Income Valuation'!C34,'Income Valuation'!I21*C6,0)+IF(6='Income Valuation'!C34,('Income Valuation'!C52*C6*D7/D6),0) | J13: =IF(7<='Income Valuation'!C34,'Income Valuation'!J21*C6,0)+IF(7='Income Valuation'!C34,('Income Valuation'!C52*C6*D7/D6),0) | K13: =IF(8<='Income Valuation'!C34,'Income Valuation'!K21*C6,0)+IF(8='Income Valuation'!C34,('Income Valuation'!C52*C6*D7/D6),0) | L13: =IF(9<='Income Valuation'!C34,'Income Valuation'!L21*C6,0)+IF(9='Income Valuation'!C34,('Income Valuation'!C52*C6*D7/D6),0) | M13: =IF(10<='Income Valuation'!C34,'Income Valuation'!M21*C6,0)+IF(10='Income Valuation'!C34,('Income Valuation'!C52*C6*D7/D6),0)
B14: Downside — levered CF | C14: =-('Income Valuation'!C59*(1+'Income Valuation'!C49)+'Income Valuation'!C39*'Income Valuation'!C65-'Income Valuation'!C65) | D14: =IF(1<='Income Valuation'!C34,'Income Valuation'!D21*C6-('Income Valuation'!C65*((E6/12)/(1-(1+(E6/12))^(-'Income Valuation'!C44*12))*12)),0)+IF(1='Income Valuation'!C34,('Income Valuation'!C52*C6*D7/D6)-('Income Valuation'!C65*(1+(E6/12))^(12*'Income Valuation'!C34)-(('Income Valuation'!C65*((E6/12)/(1-(1+(E6/12))^(-'Income Valuation'!C44*12))*12))/12)*((1+(E6/12))^(12*'Income Valuation'!C34)-1)/(E6/12)),0) | E14: =IF(2<='Income Valuation'!C34,'Income Valuation'!E21*C6-('Income Valuation'!C65*((E6/12)/(1-(1+(E6/12))^(-'Income Valuation'!C44*12))*12)),0)+IF(2='Income Valuation'!C34,('Income Valuation'!C52*C6*D7/D6)-('Income Valuation'!C65*(1+(E6/12))^(12*'Income Valuation'!C34)-(('Income Valuation'!C65*((E6/12)/(1-(1+(E6/12))^(-'Income Valuation'!C44*12))*12))/12)*((1+(E6/12))^(12*'Income Valuation'!C34)-1)/(E6/12)),0) | F14: =IF(3<='Income Valuation'!C34,'Income Valuation'!F21*C6-('Income Valuation'!C65*((E6/12)/(1-(1+(E6/12))^(-'Income Valuation'!C44*12))*12)),0)+IF(3='Income Valuation'!C34,('Income Valuation'!C52*C6*D7/D6)-('Income Valuation'!C65*(1+(E6/12))^(12*'Income Valuation'!C34)-(('Income Valuation'!C65*((E6/12)/(1-(1+(E6/12))^(-'Income Valuation'!C44*12))*12))/12)*((1+(E6/12))^(12*'Income Valuation'!C34)-1)/(E6/12)),0) | G14: =IF(4<='Income Valuation'!C34,'Income Valuation'!G21*C6-('Income Valuation'!C65*((E6/12)/(1-(1+(E6/12))^(-'Income Valuation'!C44*12))*12)),0)+IF(4='Income Valuation'!C34,('Income Valuation'!C52*C6*D7/D6)-('Income Valuation'!C65*(1+(E6/12))^(12*'Income Valuation'!C34)-(('Income Valuation'!C65*((E6/12)/(1-(1+(E6/12))^(-'Income Valuation'!C44*12))*12))/12)*((1+(E6/12))^(12*'Income Valuation'!C34)-1)/(E6/12)),0) | H14: =IF(5<='Income Valuation'!C34,'Income Valuation'!H21*C6-('Income Valuation'!C65*((E6/12)/(1-(1+(E6/12))^(-'Income Valuation'!C44*12))*12)),0)+IF(5='Income Valuation'!C34,('Income Valuation'!C52*C6*D7/D6)-('Income Valuation'!C65*(1+(E6/12))^(12*'Income Valuation'!C34)-(('Income Valuation'!C65*((E6/12)/(1-(1+(E6/12))^(-'Income Valuation'!C44*12))*12))/12)*((1+(E6/12))^(12*'Income Valuation'!C34)-1)/(E6/12)),0) | I14: =IF(6<='Income Valuation'!C34,'Income Valuation'!I21*C6-('Income Valuation'!C65*((E6/12)/(1-(1+(E6/12))^(-'Income Valuation'!C44*12))*12)),0)+IF(6='Income Valuation'!C34,('Income Valuation'!C52*C6*D7/D6)-('Income Valuation'!C65*(1+(E6/12))^(12*'Income Valuation'!C34)-(('Income Valuation'!C65*((E6/12)/(1-(1+(E6/12))^(-'Income Valuation'!C44*12))*12))/12)*((1+(E6/12))^(12*'Income Valuation'!C34)-1)/(E6/12)),0) | J14: =IF(7<='Income Valuation'!C34,'Income Valuation'!J21*C6-('Income Valuation'!C65*((E6/12)/(1-(1+(E6/12))^(-'Income Valuation'!C44*12))*12)),0)+IF(7='Income Valuation'!C34,('Income Valuation'!C52*C6*D7/D6)-('Income Valuation'!C65*(1+(E6/12))^(12*'Income Valuation'!C34)-(('Income Valuation'!C65*((E6/12)/(1-(1+(E6/12))^(-'Income Valuation'!C44*12))*12))/12)*((1+(E6/12))^(12*'Income Valuation'!C34)-1)/(E6/12)),0) | K14: =IF(8<='Income Valuation'!C34,'Income Valuation'!K21*C6-('Income Valuation'!C65*((E6/12)/(1-(1+(E6/12))^(-'Income Valuation'!C44*12))*12)),0)+IF(8='Income Valuation'!C34,('Income Valuation'!C52*C6*D7/D6)-('Income Valuation'!C65*(1+(E6/12))^(12*'Income Valuation'!C34)-(('Income Valuation'!C65*((E6/12)/(1-(1+(E6/12))^(-'Income Valuation'!C44*12))*12))/12)*((1+(E6/12))^(12*'Income Valuation'!C34)-1)/(E6/12)),0) | L14: =IF(9<='Income Valuation'!C34,'Income Valuation'!L21*C6-('Income Valuation'!C65*((E6/12)/(1-(1+(E6/12))^(-'Income Valuation'!C44*12))*12)),0)+IF(9='Income Valuation'!C34,('Income Valuation'!C52*C6*D7/D6)-('Income Valuation'!C65*(1+(E6/12))^(12*'Income Valuation'!C34)-(('Income Valuation'!C65*((E6/12)/(1-(1+(E6/12))^(-'Income Valuation'!C44*12))*12))/12)*((1+(E6/12))^(12*'Income Valuation'!C34)-1)/(E6/12)),0) | M14: =IF(10<='Income Valuation'!C34,'Income Valuation'!M21*C6-('Income Valuation'!C65*((E6/12)/(1-(1+(E6/12))^(-'Income Valuation'!C44*12))*12)),0)+IF(10='Income Valuation'!C34,('Income Valuation'!C52*C6*D7/D6)-('Income Valuation'!C65*(1+(E6/12))^(12*'Income Valuation'!C34)-(('Income Valuation'!C65*((E6/12)/(1-(1+(E6/12))^(-'Income Valuation'!C44*12))*12))/12)*((1+(E6/12))^(12*'Income Valuation'!C34)-1)/(E6/12)),0)
B15: Base — unlevered CF | C15: =-'Income Valuation'!C59*(1+'Income Valuation'!C49) | D15: =IF(1<='Income Valuation'!C34,'Income Valuation'!D21*C7,0)+IF(1='Income Valuation'!C34,('Income Valuation'!C52*C7*D7/D7),0) | E15: =IF(2<='Income Valuation'!C34,'Income Valuation'!E21*C7,0)+IF(2='Income Valuation'!C34,('Income Valuation'!C52*C7*D7/D7),0) | F15: =IF(3<='Income Valuation'!C34,'Income Valuation'!F21*C7,0)+IF(3='Income Valuation'!C34,('Income Valuation'!C52*C7*D7/D7),0) | G15: =IF(4<='Income Valuation'!C34,'Income Valuation'!G21*C7,0)+IF(4='Income Valuation'!C34,('Income Valuation'!C52*C7*D7/D7),0) | H15: =IF(5<='Income Valuation'!C34,'Income Valuation'!H21*C7,0)+IF(5='Income Valuation'!C34,('Income Valuation'!C52*C7*D7/D7),0) | I15: =IF(6<='Income Valuation'!C34,'Income Valuation'!I21*C7,0)+IF(6='Income Valuation'!C34,('Income Valuation'!C52*C7*D7/D7),0) | J15: =IF(7<='Income Valuation'!C34,'Income Valuation'!J21*C7,0)+IF(7='Income Valuation'!C34,('Income Valuation'!C52*C7*D7/D7),0) | K15: =IF(8<='Income Valuation'!C34,'Income Valuation'!K21*C7,0)+IF(8='Income Valuation'!C34,('Income Valuation'!C52*C7*D7/D7),0) | L15: =IF(9<='Income Valuation'!C34,'Income Valuation'!L21*C7,0)+IF(9='Income Valuation'!C34,('Income Valuation'!C52*C7*D7/D7),0) | M15: =IF(10<='Income Valuation'!C34,'Income Valuation'!M21*C7,0)+IF(10='Income Valuation'!C34,('Income Valuation'!C52*C7*D7/D7),0)
B16: Base — levered CF | C16: =-('Income Valuation'!C59*(1+'Income Valuation'!C49)+'Income Valuation'!C39*'Income Valuation'!C65-'Income Valuation'!C65) | D16: =IF(1<='Income Valuation'!C34,'Income Valuation'!D21*C7-('Income Valuation'!C65*((E7/12)/(1-(1+(E7/12))^(-'Income Valuation'!C44*12))*12)),0)+IF(1='Income Valuation'!C34,('Income Valuation'!C52*C7*D7/D7)-('Income Valuation'!C65*(1+(E7/12))^(12*'Income Valuation'!C34)-(('Income Valuation'!C65*((E7/12)/(1-(1+(E7/12))^(-'Income Valuation'!C44*12))*12))/12)*((1+(E7/12))^(12*'Income Valuation'!C34)-1)/(E7/12)),0) | E16: =IF(2<='Income Valuation'!C34,'Income Valuation'!E21*C7-('Income Valuation'!C65*((E7/12)/(1-(1+(E7/12))^(-'Income Valuation'!C44*12))*12)),0)+IF(2='Income Valuation'!C34,('Income Valuation'!C52*C7*D7/D7)-('Income Valuation'!C65*(1+(E7/12))^(12*'Income Valuation'!C34)-(('Income Valuation'!C65*((E7/12)/(1-(1+(E7/12))^(-'Income Valuation'!C44*12))*12))/12)*((1+(E7/12))^(12*'Income Valuation'!C34)-1)/(E7/12)),0) | F16: =IF(3<='Income Valuation'!C34,'Income Valuation'!F21*C7-('Income Valuation'!C65*((E7/12)/(1-(1+(E7/12))^(-'Income Valuation'!C44*12))*12)),0)+IF(3='Income Valuation'!C34,('Income Valuation'!C52*C7*D7/D7)-('Income Valuation'!C65*(1+(E7/12))^(12*'Income Valuation'!C34)-(('Income Valuation'!C65*((E7/12)/(1-(1+(E7/12))^(-'Income Valuation'!C44*12))*12))/12)*((1+(E7/12))^(12*'Income Valuation'!C34)-1)/(E7/12)),0) | G16: =IF(4<='Income Valuation'!C34,'Income Valuation'!G21*C7-('Income Valuation'!C65*((E7/12)/(1-(1+(E7/12))^(-'Income Valuation'!C44*12))*12)),0)+IF(4='Income Valuation'!C34,('Income Valuation'!C52*C7*D7/D7)-('Income Valuation'!C65*(1+(E7/12))^(12*'Income Valuation'!C34)-(('Income Valuation'!C65*((E7/12)/(1-(1+(E7/12))^(-'Income Valuation'!C44*12))*12))/12)*((1+(E7/12))^(12*'Income Valuation'!C34)-1)/(E7/12)),0) | H16: =IF(5<='Income Valuation'!C34,'Income Valuation'!H21*C7-('Income Valuation'!C65*((E7/12)/(1-(1+(E7/12))^(-'Income Valuation'!C44*12))*12)),0)+IF(5='Income Valuation'!C34,('Income Valuation'!C52*C7*D7/D7)-('Income Valuation'!C65*(1+(E7/12))^(12*'Income Valuation'!C34)-(('Income Valuation'!C65*((E7/12)/(1-(1+(E7/12))^(-'Income Valuation'!C44*12))*12))/12)*((1+(E7/12))^(12*'Income Valuation'!C34)-1)/(E7/12)),0) | I16: =IF(6<='Income Valuation'!C34,'Income Valuation'!I21*C7-('Income Valuation'!C65*((E7/12)/(1-(1+(E7/12))^(-'Income Valuation'!C44*12))*12)),0)+IF(6='Income Valuation'!C34,('Income Valuation'!C52*C7*D7/D7)-('Income Valuation'!C65*(1+(E7/12))^(12*'Income Valuation'!C34)-(('Income Valuation'!C65*((E7/12)/(1-(1+(E7/12))^(-'Income Valuation'!C44*12))*12))/12)*((1+(E7/12))^(12*'Income Valuation'!C34)-1)/(E7/12)),0) | J16: =IF(7<='Income Valuation'!C34,'Income Valuation'!J21*C7-('Income Valuation'!C65*((E7/12)/(1-(1+(E7/12))^(-'Income Valuation'!C44*12))*12)),0)+IF(7='Income Valuation'!C34,('Income Valuation'!C52*C7*D7/D7)-('Income Valuation'!C65*(1+(E7/12))^(12*'Income Valuation'!C34)-(('Income Valuation'!C65*((E7/12)/(1-(1+(E7/12))^(-'Income Valuation'!C44*12))*12))/12)*((1+(E7/12))^(12*'Income Valuation'!C34)-1)/(E7/12)),0) | K16: =IF(8<='Income Valuation'!C34,'Income Valuation'!K21*C7-('Income Valuation'!C65*((E7/12)/(1-(1+(E7/12))^(-'Income Valuation'!C44*12))*12)),0)+IF(8='Income Valuation'!C34,('Income Valuation'!C52*C7*D7/D7)-('Income Valuation'!C65*(1+(E7/12))^(12*'Income Valuation'!C34)-(('Income Valuation'!C65*((E7/12)/(1-(1+(E7/12))^(-'Income Valuation'!C44*12))*12))/12)*((1+(E7/12))^(12*'Income Valuation'!C34)-1)/(E7/12)),0) | L16: =IF(9<='Income Valuation'!C34,'Income Valuation'!L21*C7-('Income Valuation'!C65*((E7/12)/(1-(1+(E7/12))^(-'Income Valuation'!C44*12))*12)),0)+IF(9='Income Valuation'!C34,('Income Valuation'!C52*C7*D7/D7)-('Income Valuation'!C65*(1+(E7/12))^(12*'Income Valuation'!C34)-(('Income Valuation'!C65*((E7/12)/(1-(1+(E7/12))^(-'Income Valuation'!C44*12))*12))/12)*((1+(E7/12))^(12*'Income Valuation'!C34)-1)/(E7/12)),0) | M16: =IF(10<='Income Valuation'!C34,'Income Valuation'!M21*C7-('Income Valuation'!C65*((E7/12)/(1-(1+(E7/12))^(-'Income Valuation'!C44*12))*12)),0)+IF(10='Income Valuation'!C34,('Income Valuation'!C52*C7*D7/D7)-('Income Valuation'!C65*(1+(E7/12))^(12*'Income Valuation'!C34)-(('Income Valuation'!C65*((E7/12)/(1-(1+(E7/12))^(-'Income Valuation'!C44*12))*12))/12)*((1+(E7/12))^(12*'Income Valuation'!C34)-1)/(E7/12)),0)
B17: Upside — unlevered CF | C17: =-'Income Valuation'!C59*(1+'Income Valuation'!C49) | D17: =IF(1<='Income Valuation'!C34,'Income Valuation'!D21*C8,0)+IF(1='Income Valuation'!C34,('Income Valuation'!C52*C8*D7/D8),0) | E17: =IF(2<='Income Valuation'!C34,'Income Valuation'!E21*C8,0)+IF(2='Income Valuation'!C34,('Income Valuation'!C52*C8*D7/D8),0) | F17: =IF(3<='Income Valuation'!C34,'Income Valuation'!F21*C8,0)+IF(3='Income Valuation'!C34,('Income Valuation'!C52*C8*D7/D8),0) | G17: =IF(4<='Income Valuation'!C34,'Income Valuation'!G21*C8,0)+IF(4='Income Valuation'!C34,('Income Valuation'!C52*C8*D7/D8),0) | H17: =IF(5<='Income Valuation'!C34,'Income Valuation'!H21*C8,0)+IF(5='Income Valuation'!C34,('Income Valuation'!C52*C8*D7/D8),0) | I17: =IF(6<='Income Valuation'!C34,'Income Valuation'!I21*C8,0)+IF(6='Income Valuation'!C34,('Income Valuation'!C52*C8*D7/D8),0) | J17: =IF(7<='Income Valuation'!C34,'Income Valuation'!J21*C8,0)+IF(7='Income Valuation'!C34,('Income Valuation'!C52*C8*D7/D8),0) | K17: =IF(8<='Income Valuation'!C34,'Income Valuation'!K21*C8,0)+IF(8='Income Valuation'!C34,('Income Valuation'!C52*C8*D7/D8),0) | L17: =IF(9<='Income Valuation'!C34,'Income Valuation'!L21*C8,0)+IF(9='Income Valuation'!C34,('Income Valuation'!C52*C8*D7/D8),0) | M17: =IF(10<='Income Valuation'!C34,'Income Valuation'!M21*C8,0)+IF(10='Income Valuation'!C34,('Income Valuation'!C52*C8*D7/D8),0)
B18: Upside — levered CF | C18: =-('Income Valuation'!C59*(1+'Income Valuation'!C49)+'Income Valuation'!C39*'Income Valuation'!C65-'Income Valuation'!C65) | D18: =IF(1<='Income Valuation'!C34,'Income Valuation'!D21*C8-('Income Valuation'!C65*((E8/12)/(1-(1+(E8/12))^(-'Income Valuation'!C44*12))*12)),0)+IF(1='Income Valuation'!C34,('Income Valuation'!C52*C8*D7/D8)-('Income Valuation'!C65*(1+(E8/12))^(12*'Income Valuation'!C34)-(('Income Valuation'!C65*((E8/12)/(1-(1+(E8/12))^(-'Income Valuation'!C44*12))*12))/12)*((1+(E8/12))^(12*'Income Valuation'!C34)-1)/(E8/12)),0) | E18: =IF(2<='Income Valuation'!C34,'Income Valuation'!E21*C8-('Income Valuation'!C65*((E8/12)/(1-(1+(E8/12))^(-'Income Valuation'!C44*12))*12)),0)+IF(2='Income Valuation'!C34,('Income Valuation'!C52*C8*D7/D8)-('Income Valuation'!C65*(1+(E8/12))^(12*'Income Valuation'!C34)-(('Income Valuation'!C65*((E8/12)/(1-(1+(E8/12))^(-'Income Valuation'!C44*12))*12))/12)*((1+(E8/12))^(12*'Income Valuation'!C34)-1)/(E8/12)),0) | F18: =IF(3<='Income Valuation'!C34,'Income Valuation'!F21*C8-('Income Valuation'!C65*((E8/12)/(1-(1+(E8/12))^(-'Income Valuation'!C44*12))*12)),0)+IF(3='Income Valuation'!C34,('Income Valuation'!C52*C8*D7/D8)-('Income Valuation'!C65*(1+(E8/12))^(12*'Income Valuation'!C34)-(('Income Valuation'!C65*((E8/12)/(1-(1+(E8/12))^(-'Income Valuation'!C44*12))*12))/12)*((1+(E8/12))^(12*'Income Valuation'!C34)-1)/(E8/12)),0) | G18: =IF(4<='Income Valuation'!C34,'Income Valuation'!G21*C8-('Income Valuation'!C65*((E8/12)/(1-(1+(E8/12))^(-'Income Valuation'!C44*12))*12)),0)+IF(4='Income Valuation'!C34,('Income Valuation'!C52*C8*D7/D8)-('Income Valuation'!C65*(1+(E8/12))^(12*'Income Valuation'!C34)-(('Income Valuation'!C65*((E8/12)/(1-(1+(E8/12))^(-'Income Valuation'!C44*12))*12))/12)*((1+(E8/12))^(12*'Income Valuation'!C34)-1)/(E8/12)),0) | H18: =IF(5<='Income Valuation'!C34,'Income Valuation'!H21*C8-('Income Valuation'!C65*((E8/12)/(1-(1+(E8/12))^(-'Income Valuation'!C44*12))*12)),0)+IF(5='Income Valuation'!C34,('Income Valuation'!C52*C8*D7/D8)-('Income Valuation'!C65*(1+(E8/12))^(12*'Income Valuation'!C34)-(('Income Valuation'!C65*((E8/12)/(1-(1+(E8/12))^(-'Income Valuation'!C44*12))*12))/12)*((1+(E8/12))^(12*'Income Valuation'!C34)-1)/(E8/12)),0) | I18: =IF(6<='Income Valuation'!C34,'Income Valuation'!I21*C8-('Income Valuation'!C65*((E8/12)/(1-(1+(E8/12))^(-'Income Valuation'!C44*12))*12)),0)+IF(6='Income Valuation'!C34,('Income Valuation'!C52*C8*D7/D8)-('Income Valuation'!C65*(1+(E8/12))^(12*'Income Valuation'!C34)-(('Income Valuation'!C65*((E8/12)/(1-(1+(E8/12))^(-'Income Valuation'!C44*12))*12))/12)*((1+(E8/12))^(12*'Income Valuation'!C34)-1)/(E8/12)),0) | J18: =IF(7<='Income Valuation'!C34,'Income Valuation'!J21*C8-('Income Valuation'!C65*((E8/12)/(1-(1+(E8/12))^(-'Income Valuation'!C44*12))*12)),0)+IF(7='Income Valuation'!C34,('Income Valuation'!C52*C8*D7/D8)-('Income Valuation'!C65*(1+(E8/12))^(12*'Income Valuation'!C34)-(('Income Valuation'!C65*((E8/12)/(1-(1+(E8/12))^(-'Income Valuation'!C44*12))*12))/12)*((1+(E8/12))^(12*'Income Valuation'!C34)-1)/(E8/12)),0) | K18: =IF(8<='Income Valuation'!C34,'Income Valuation'!K21*C8-('Income Valuation'!C65*((E8/12)/(1-(1+(E8/12))^(-'Income Valuation'!C44*12))*12)),0)+IF(8='Income Valuation'!C34,('Income Valuation'!C52*C8*D7/D8)-('Income Valuation'!C65*(1+(E8/12))^(12*'Income Valuation'!C34)-(('Income Valuation'!C65*((E8/12)/(1-(1+(E8/12))^(-'Income Valuation'!C44*12))*12))/12)*((1+(E8/12))^(12*'Income Valuation'!C34)-1)/(E8/12)),0) | L18: =IF(9<='Income Valuation'!C34,'Income Valuation'!L21*C8-('Income Valuation'!C65*((E8/12)/(1-(1+(E8/12))^(-'Income Valuation'!C44*12))*12)),0)+IF(9='Income Valuation'!C34,('Income Valuation'!C52*C8*D7/D8)-('Income Valuation'!C65*(1+(E8/12))^(12*'Income Valuation'!C34)-(('Income Valuation'!C65*((E8/12)/(1-(1+(E8/12))^(-'Income Valuation'!C44*12))*12))/12)*((1+(E8/12))^(12*'Income Valuation'!C34)-1)/(E8/12)),0) | M18: =IF(10<='Income Valuation'!C34,'Income Valuation'!M21*C8-('Income Valuation'!C65*((E8/12)/(1-(1+(E8/12))^(-'Income Valuation'!C44*12))*12)),0)+IF(10='Income Valuation'!C34,('Income Valuation'!C52*C8*D7/D8)-('Income Valuation'!C65*(1+(E8/12))^(12*'Income Valuation'!C34)-(('Income Valuation'!C65*((E8/12)/(1-(1+(E8/12))^(-'Income Valuation'!C44*12))*12))/12)*((1+(E8/12))^(12*'Income Valuation'!C34)-1)/(E8/12)),0)
B20: SCENARIO SUMMARY — returns at the base income price
B21: Scenario | D21: Income value | F21: Unlev IRR | G21: Lev IRR | H21: Lev EM | I21: Yr-1 DSCR | J21: Avg CoC
B22: Downside | D22: ='Income Valuation'!C25*C6/'Income Valuation'!C30 | F22: =IRR(C13:M13) | G22: =IRR(C14:M14) | H22: =SUM(D14:M14)/('Income Valuation'!C59*(1+'Income Valuation'!C49)+'Income Valuation'!C39*'Income Valuation'!C65-'Income Valuation'!C65) | I22: ='Income Valuation'!C25*C6/('Income Valuation'!C65*((E6/12)/(1-(1+(E6/12))^(-'Income Valuation'!C44*12))*12)) | J22: =('Income Valuation'!C50*C6-'Income Valuation'!C34*('Income Valuation'!C65*((E6/12)/(1-(1+(E6/12))^(-'Income Valuation'!C44*12))*12)))/'Income Valuation'!C34/('Income Valuation'!C59*(1+'Income Valuation'!C49)+'Income Valuation'!C39*'Income Valuation'!C65-'Income Valuation'!C65)
B23: Base | D23: ='Income Valuation'!C25*C7/'Income Valuation'!C30 | F23: =IRR(C15:M15) | G23: =IRR(C16:M16) | H23: =SUM(D16:M16)/('Income Valuation'!C59*(1+'Income Valuation'!C49)+'Income Valuation'!C39*'Income Valuation'!C65-'Income Valuation'!C65) | I23: ='Income Valuation'!C25*C7/('Income Valuation'!C65*((E7/12)/(1-(1+(E7/12))^(-'Income Valuation'!C44*12))*12)) | J23: =('Income Valuation'!C50*C7-'Income Valuation'!C34*('Income Valuation'!C65*((E7/12)/(1-(1+(E7/12))^(-'Income Valuation'!C44*12))*12)))/'Income Valuation'!C34/('Income Valuation'!C59*(1+'Income Valuation'!C49)+'Income Valuation'!C39*'Income Valuation'!C65-'Income Valuation'!C65)
B24: Upside | D24: ='Income Valuation'!C25*C8/'Income Valuation'!C30 | F24: =IRR(C17:M17) | G24: =IRR(C18:M18) | H24: =SUM(D18:M18)/('Income Valuation'!C59*(1+'Income Valuation'!C49)+'Income Valuation'!C39*'Income Valuation'!C65-'Income Valuation'!C65) | I24: ='Income Valuation'!C25*C8/('Income Valuation'!C65*((E8/12)/(1-(1+(E8/12))^(-'Income Valuation'!C44*12))*12)) | J24: =('Income Valuation'!C50*C8-'Income Valuation'!C34*('Income Valuation'!C65*((E8/12)/(1-(1+(E8/12))^(-'Income Valuation'!C44*12))*12)))/'Income Valuation'!C34/('Income Valuation'!C59*(1+'Income Valuation'!C49)+'Income Valuation'!C39*'Income Valuation'!C65-'Income Valuation'!C65)
B26: Read | D26: Downside stresses NOI −8%, exit cap +50 bps, and rate +75 bps simultaneously (a compound recession case). The base case is highlighted; the levered IRR range brackets the deal for the investment committee.

Sheet Assemblage
B1: THE ASSEMBLAGE · COVERED LAND PLAY
B2: E Sunrise Blvd @ the Galleria — five contiguous assets, plat block 49-42-36-12 · buy the income, control the dirt · highest & best use = hold for Live Local density
B4: THE COVERED-LAND THESIS
B5: Assemble the whole E Sunrise Blvd frontage at the Galleria hard corner. Each asset is bought/valued off the rent it produces;
B6: the in-place income covers the carry (debt service, taxes, insurance) while DAWN RE controls ~7+ acres for eventual redevelopment.
B7: Redevelopment does NOT pencil today (AE flood zone, coastal hard costs → negative residual), so the play is to HOLD the income-
B8: covered land and hold the Live Local density option. Publix already proved the model — it paid land value ($679/SF bldg), not income value.
B10: ASSET ROLL-UP — 🟢 green = live links to each asset tab
B11: Asset | C11: Control cost | D11: In-place NOI | E11: Going-in cap | F11: Land SF | G11: Land value | H11: Unlev IRR | I11: Lev IRR | J11: Note
B12: Shahidi Retail (Galleria Plaza) | C12: ='Shahidi Retail'!C57 | D12: ='Shahidi Retail'!C122 | E12: =D12/C12 | F12: ='Shahidi Retail'!C36 | G12: ='Shahidi Retail'!C80 | H12: ='Shahidi Retail'!C117 | I12: ='Shahidi Retail'!C120 | J12: acquirable · value-add lease-up
B13: Publix + Starbucks | C13: ='Publix & Starbucks'!C44 | D13: ='Publix & Starbucks'!C109 | E13: =D13/C13 | F13: ='Publix & Starbucks'!C25 | G13: ='Publix & Starbucks'!C67 | H13: ='Publix & Starbucks'!C104 | I13: ='Publix & Starbucks'!C107 | J13: sale-leaseback · acquire fee, lease back
B14: Sunrise Plaza (Kar Luen) | C14: ='Sunrise Plaza'!C47 | D14: ='Sunrise Plaza'!C112 | E14: =D14/C14 | F14: ='Sunrise Plaza'!C28 | G14: ='Sunrise Plaza'!C70 | H14: ='Sunrise Plaza'!C107 | I14: ='Sunrise Plaza'!C110 | J14: acquirable · restaurant value-add
B15: Galleria Corporate Centre (office) | C15: ='Office Condo'!I97 | D15: ='Office Condo'!C78 | E15: =D15/C15 | F15: 0 | G15: =0 | H15: ='Office Condo'!C73 | I15: ='Office Condo'!C76 | J15: buy out both condo owners
B16: 1040 Bayview (covered land) | C16: ='Land'!E40 | D16: ='Land'!C47 | E16: =D16/C16 | F16: ='Land'!C15 | G16: ='Land'!E40 | H16: ='Land'!C65 | I16: ='Land'!C68 | J16: entitled 259 units · hold for redevelopment
B17: ASSEMBLAGE TOTAL (pre-premium) | C17: =SUM(C12:C16) | D17: =SUM(D12:D16) | E17: =D17/C17 | F17: =SUM(F12:F16) | G17: =SUM(G12:G16) | H17: — | I17: — | J17: blended going-in cap covers carry
B19: COVERED-LAND METRICS & ACQUISITION COST
B20: Total existing building (GLA, SF) | C20: =341501 | D20: existing improvements across all five
B21: Total land assembled (acres) | C21: =F17/43560 | D21: ≈ 7+ acres of E Sunrise frontage
B22: Blended land basis ($/SF) | C22: =G17/F17 | D22: vs. subject comps $228–255/SF; Galleria bulk $53/SF
B23: Blended in-place cap (income ÷ cost) | C23: =D17/C17 | D23: covered-land range ~3–5% — income covers carry, not a yield play
B25: Assemblage premium (to control holdouts)
B26: Low | C26: =C17*(1+'Assumptions'!C27) | D26: ='Assumptions'!C27
B27: Base | C27: =C17*(1+'Assumptions'!C28) | D27: ='Assumptions'!C28
B28: High | C28: =C17*(1+'Assumptions'!C29) | D28: ='Assumptions'!C29
B29: TOTAL ASSEMBLAGE ACQUISITION COST (base) | C29: =C27 | D29: 🔶 base premium (Assumptions tab) on the summed control cost
B31: HIGHEST & BEST USE — redevelopment residual (Live Local) vs. hold
B32: Redevelopment residual — 1040 Bayview (per Land tab) | C32: ='Land'!C78
B33: Redevelopment verdict | C33: HOLD | D33: Residual runs NEGATIVE in the AE flood zone at current coastal hard costs — do not force it positive. Best use today = hold the income-covered land + Live Local density option until costs/rents support redevelopment.
B35: PORTFOLIO CAPITAL — consolidated returns computed on the Income Valuation tab
B36: Total equity required (all assets, at asset prices) | C36: ='Shahidi Retail'!C78+'Publix & Starbucks'!C65+'Sunrise Plaza'!C68+'Office Condo'!C46+'Land'!C52
B37: Total in-place NOI (covers carry) | C37: =D17
B38: Portfolio IRR (unlevered / levered) | D38: Computed from the CONSOLIDATED cash flows on the Income Valuation tab — never by averaging asset IRRs (mathematically invalid). See that tab for portfolio returns at both the income and covered-land prices.

Sheet Highest & Best Use
B1: HIGHEST & BEST USE — INDIVIDUAL vs. ASSEMBLED
B2: Every component priced on its own, then combined; the land valued as regular fragmented parcels and as an assembled superblock (worth more, but hard to put together); the office FULL BUY-OUT; and the Live Local redevelopment test.
B4: ① COMPONENT PRICING — each priced independently, then combined (🟢 live links)
B5: Component | C5: Independent price | E5: Basis / note
B6: Shahidi Retail (Galleria Plaza) | C6: ='Shahidi Retail'!C57 | E6: acquire fee · value-add retail
B7: Publix + Starbucks | C7: ='Publix & Starbucks'!C44 | E7: sale-leaseback (acquire fee)
B8: Sunrise Plaza (Kar Luen) | C8: ='Sunrise Plaza'!C47 | E8: acquire fee · restaurant value-add
B9: Galleria Corp Centre (full buy-out) | C9: ='Office Condo'!I97 | E9: buy out BOTH condo owners
B10: 1040 Bayview (entitled land) | C10: ='Land'!E40 | E10: covered land · hold for redevelopment
B11: SUM OF THE PARTS (priced independently) | C11: =SUM(C6:C10) | E11: what you'd pay buying each one at a time
B12: ＋ Assemblage premium (hard to put together) | C12: =C11*'Assumptions'!C28 | D12: ='Assumptions'!C28 | E12: 5 owners · a sale-leaseback · a fractured condo · holdout risk
B13: PRICED AS AN ASSEMBLAGE (base) | C13: =C11+C12 | E13: total to control the whole block
B15: ACQUISITION HISTORY — what each owner paid, and when (seller basis = negotiation leverage)
B16: Component / owner | C16: Bought | D16: For | E16: Our modeled price | F16: note
B17: Shahidi Retail — Shawnick Galleria LLC (Shahidi) | C17: 11/09/2021 | D17: 17100000 | E17: ='Shahidi Retail'!C57 | F17: Special Warranty Deed (flagged disqualified sale)
B18: Publix + Starbucks — REAL SUB LLC (Publix) | C18: 03/14/2025 | D18: 25000000 | E18: ='Publix & Starbucks'!C44 | F18: Trustee's Deed · $679/SF bldg
B19: Sunrise Plaza — Kar Luen Inc | C19: Oct 2000 | D19: 128000 | E19: ='Sunrise Plaza'!C47 | F19: stale/nominal — held since; no recent arm's-length
B20: Office — Main St Fund LLC (57.4%) | C20: 09/23/2019 | D20: 10000000 | E20: ='Office Condo'!I90 | F20: 96,930 SF + 2 parking lots (Daily Business Review)
B21: Office — Intl Sunrise Partners (42.6%) | C21: 2011 | D21: — | E21: ='Office Condo'!I91 | F21: condo-conversion sponsor (Bush Development)
B22: 1040 Bayview — Sunrise & Bayview Partners | C22: 2014 (JV) | D22: — | E22: ='Land'!E40 | F22: Procacci; BBX exited 2022; stale 1961 deed $801,933
B24: ② LAND VALUE — as REGULAR (fragmented) parcels
B25: Parcel | C25: Land SF | D25: $/SF | E25: Land value | F25: note
B26: Shahidi Retail | C26: ='Shahidi Retail'!C36 | D26: ='Shahidi Retail'!C79 | E26: ='Shahidi Retail'!C80 | F26: standalone parcel
B27: Publix + Starbucks | C27: ='Publix & Starbucks'!C25 | D27: ='Publix & Starbucks'!C55 | E27: ='Publix & Starbucks'!C67 | F27: standalone parcel
B28: Sunrise Plaza (Kar Luen) | C28: ='Sunrise Plaza'!C28 | D28: ='Sunrise Plaza'!C58 | E28: ='Sunrise Plaza'!C70 | F28: standalone parcel
B29: 1040 Bayview | C29: ='Land'!C15 | D29: ='Land'!E40/'Land'!C15 | E29: ='Land'!E40 | F29: standalone parcel
B30: SUM OF THE PARTS (fragmented land) | C30: =SUM(C26:C29) | D30: =SUM(E26:E29)/SUM(C26:C29) | E30: =SUM(E26:E29) | F30: office excluded — building, not land (buy-out below)
B31: ② LAND VALUE — as an ASSEMBLED SUPERBLOCK (plottage: worth more, hard to assemble)
B32: Assembled land (SF) | C32: =C30 | E32: 4 contiguous land parcels, one plat block
B33: Assembled land (acres) | C33: =C30/43560
B34: Plottage / assemblage premium (base) | C34: ='Assumptions'!C28 | E34: uplift for a large contiguous development site
B35: Assembled land value — low | C35: =E30*(1+'Assumptions'!C27)
B36: Assembled land value — BASE | C36: =E30*(1+'Assumptions'!C28)
B37: Assembled land value — high | C37: =E30*(1+'Assumptions'!C29)
B38: Implied assembled $/SF (base) | C38: =C36/C30 | E38: vs. fragmented blend above
B39: PLOTTAGE PREMIUM (assembled − fragmented) | C39: =C36-E30 | E39: the value created / cost incurred by assembling the hard-to-put-together block
B40: Entitlement lift (post-Live Local approval) | C40: ='Assumptions'!C32 | E40: value bump once entitled for Live Local density
B41: POST-APPROVAL assembled land value | C41: =C36*(1+'Assumptions'!C32) | E41: what the ENTITLED dirt is worth — the redevelopment upside the premium buys you the option on
B43: ③ OFFICE CONDO — FULL BUY-OUT (the building on the corner, two dominant owners)
B44: Main Street Fund LLC (Grove Gate, 57.4%) | C44: ='Office Condo'!I90 | E44: bought 96,930 SF + 2 parking lots for $10M (2019)
B45: International Sunrise Partners LLC (42.6%) | C45: ='Office Condo'!I91 | E45: prior bulk owner (2011 condo-conversion sponsor)
B46: FULL BUY-OUT VALUE (both owners) | C46: ='Office Condo'!I97 | E46: income value + buy-out premium; adjust the premium on the Office Condo tab
B48: ④ REDEVELOPMENT — LIVE LOCAL RESIDUAL (assemblage scale · ⚠️ negative → HOLD)
B49: Buildable density (units/acre) | C49: 100 | D49: 🔵 Live Local target
B50: Assemblage buildable units | C50: =C30/43560*C49 | E50: acres × density
B51: Gross development value (GDV) | C51: =C50*'Assumptions'!C39 | E51: units × achievable value/unit (Assumptions)
B52: Buildable GBA (SF) | C52: =C50*'Assumptions'!C41
B53: − Hard cost | C53: =-C52*'Assumptions'!C40
B54: − Soft cost | C54: =-C52*'Assumptions'!C40*'Assumptions'!C42
B55: − Developer profit | C55: =-C51*'Assumptions'!C43
B56: RESIDUAL LAND VALUE (supports acquisition?) | C56: =C51+C53-C52*'Assumptions'!C40*'Assumptions'!C42-C51*'Assumptions'!C43
B57: HBU verdict | C57: HOLD | D57: Residual runs NEGATIVE at coastal AE-zone hard costs — redevelopment does not pencil today. Highest & best use = acquire and HOLD the income-covered assemblage; redevelop when achievable rents / hard costs support Live Local density.
B59: ⑤ CONCLUSION
B60: • Priced independently, the components sum to ~$86M; as an assemblage (base premium) ~$103M — the premium is the cost of controlling
B61: a contiguous block held by five owners (a sale-leaseback, a fractured condo, and holdout risk).
B62: • The land alone is worth more assembled (plottage) than as fragmented parcels — but redevelopment does not yet pencil, so the
B63: return today is income-covered land banking, with the Live Local density as the option you are paying the premium to hold.

Sheet Shahidi Retail
B1: SHAHIDI RETAIL CENTER · “GALLERIA PLAZA”
B2: 2541–2595 E Sunrise Blvd, Fort Lauderdale, FL 33304 | Folio 49-42-36-12-0070 | 26,272 SF NNN neighborhood retail · 83.17% leased · value-add lease-up
B4: PROPERTY FACTS — ✅ public record (BCPA / Sunbiz / recorded deed)
B5: Record owner | D5: SHAWNICK GALLERIA LLC
B6: Principal / manager | D6: Esmail Shahidi (mgr) — Sunbiz L21000389291
B7: Gross leasable area (GLA) | D7: 26,272 SF
B8: Land | D8: 67,080 SF (1.54 ac)
B9: Year built | D9: 1960 (eff. 1980)
B10: Zoning / flood | D10: B-1 (Boulevard Business) / FEMA AE
B11: Last sale | D11: 11/09/2021 — $17,100,000 (Special Warranty Deed)
B12: 2025 real-estate taxes | D12: $162,366 (2024: $152,766)
B13: 2026 just / market value (BCPA) | D13: $8,911,690
B14: Effective millage | D14: 1.91% (2025 tax ÷ just value)
B15: Derived basis on $17.1M | D15: $254.92/SF land · $650.88/SF building
B16: In-place occupancy | D16: 83.17% → ~4,422 SF vacant to lease
B18: TENANT RENT ROLL — 🔶 suites/rents estimated from corridor comps ($45–60/SF NNN); SF-weighted blend ties to model market rent
B19: Suite | C19: Tenant | D19: Category | F19: SF | G19: $/SF NNN | H19: Annual rent | K19: Tenant type
B20: 2541 | C20: Primo Liquors & Fine Wine | D20: Retail – liquor/wine | F20: 4000 | G20: 48 | H20: =F20*G20 | K20: Local
B21: 2577 | C21: Wells Fargo Bank | D21: Bank / financial | F21: 3500 | G21: 62 | H21: =F21*G21 | K21: NATIONAL credit
B22: 2543–75 | C22: In-line shops (mid-strip) | D22: Various local retail/service | F22: 3700 | G22: 52 | H22: =F22*G22 | K22: Local
B23: 2587 | C23: Verizon Wireless | D23: Wireless / electronics | F23: 2200 | G23: 58 | H23: =F23*G23 | K23: NATIONAL credit
B24: 2595 | C24: First Impressions Smile Center | D24: Medical – dentistry | F24: 2200 | G24: 54 | H24: =F24*G24 | K24: Local
B25: 2549 | C25: Freeman's Luggage & Gifts | D25: Retail – luggage/gifts | F25: 2000 | G25: 50 | H25: =F25*G25 | K25: Local
B26: 2583 | C26: Eyes on Sunrise | D26: Medical – optometry | F26: 1800 | G26: 56 | H26: =F26*G26 | K26: Local
B27: 2541 | C27: Lilac & Lilies Boutique | D27: Retail – apparel | F27: 1250 | G27: 58 | H27: =F27*G27 | K27: Local
B28: 2595 | C28: Roxanne Jackson – GEICO | D28: Insurance agency | F28: 1200 | G28: 56 | H28: =F28*G28 | K28: Regional
B29: — | C29: VACANT / available (mid-strip) | D29: Lease-up target to 95% | F29: 4422 | G29: — | H29: — | K29: value-add upside
B30: TOTAL / WEIGHTED AVG | C30: 9 tenants + vacancy | F30: =SUM(F20:F29) | G30: =IFERROR(SUM(H20:H28)/SUM(F20:F28),0) | H30: =SUM(H20:H28) | K30: Wells Fargo + Verizon = credit
B32: ASSUMPTIONS — 🔵 blue = hardcoded inputs (the only cells you change)
B33: Property
B34: GLA (SF) | C34: 26272 | D34: ✅ BCPA
B35: In-place occupancy | C35: ='Assumptions'!C51 | D35: 🟢 Assumptions
B36: Land (SF) | C36: ='Assumptions'!C48 | D36: 🟢 Assumptions
B37: Effective millage | C37: 0.0191 | D37: ✅ 2025 tax ÷ just value
B38: Revenue
B39: In-place base rent ($/SF NNN) | C39: 55 | D39: 🔶 owner says $60; corridor $45–60
B40: Market rent ($/SF NNN) | C40: ='Assumptions'!C50 | D40: 🟢 Assumptions
B41: Market rent growth | C41: 0.03 | D41: 🔶
B42: Stabilized occupancy | C42: ='Assumptions'!C52 | D42: 🟢 Assumptions
B43: Credit & collection loss | C43: 0.02 | D43: 🔶
B44: Operating expenses
B45: Reassessed value (= price, FL rule) | C45: 17100000 | D45: 🔶 FL reassess-to-price
B46: Insurance ($/yr) | C46: ='Assumptions'!C53 | D46: 🟢 Assumptions
B47: CAM ($/yr, recoverable) | C47: ='Assumptions'!C54 | D47: 🟢 Assumptions
B48: Repairs & maintenance ($/yr) | C48: ='Assumptions'!C55 | D48: 🟢 Assumptions
B49: Management fee (% EGR) | C49: ='Assumptions'!C56 | D49: 🟢 Assumptions
B50: Expense growth | C50: 0.03 | D50: 🔶
B51: Capital
B52: Tenant improvements ($/SF) | C52: 30 | D52: 🔶 on leased-up SF
B53: Leasing commissions ($/SF) | C53: 20 | D53: 🔶 on leased-up SF
B54: Replacement reserves ($/SF/yr) | C54: 0.15 | D54: 🔶
B55: Rollover leasing reserve ($/SF/yr) | C55: 0.75 | D55: 🔶
B56: Acquisition & financing
B57: Purchase price | C57: ='Assumptions'!C47 | D57: 🟢 Assumptions
B58: Closing & acq costs (% price) | C58: 0.025 | D58: 🔶
B59: Senior loan LTV | C59: ='Assumptions'!C59 | D59: 🟢 Assumptions
B60: Senior loan rate | C60: ='Assumptions'!C60 | D60: 🟢 Assumptions
B61: Senior loan amortization (yrs) | C61: 30 | D61: 🔶
B62: Valuation & hold
B63: Going-in cap (reference) | C63: ='Assumptions'!C57 | D63: 🟢 Assumptions
B64: Exit / reversion cap | C64: ='Assumptions'!C58 | D64: 🟢 Assumptions
B65: Cost of sale at exit | C65: 0.02 | D65: 🔶
B66: Hold period (yrs) | C66: 5 | D66: 🔶 reversion in this year
B67: Discount rate (unlevered, for NPV) | C67: 0.09 | D67: 🔶 target unlevered yield
B69: DERIVED VALUES & DEBT SIZING
B70: Senior loan amount | C70: =C57*C59 | D70: price × LTV
B71: Monthly rate | C71: =C60/12
B72: Amortization periods | C72: =C61*12
B73: Annual debt service (amortizing) | C73: =C70*(C71/(1-(1+C71)^(-C72)))*12
B74: Equity at acquisition | C74: =C57*(1+C58)-C70 | D74: price×(1+closing) − loan
B75: Absorption SF (lease-up) | C75: =C34*(C42-C35)
B76: Initial leasing capital (TI/LC on absorbed SF) | C76: =C75*(C52+C53)
B77: Total cost basis (incl. initial leasing) | C77: =C57*(1+C58)+C76
B78: Total equity required | C78: =C77-C70
B79: Land value ($/SF) | C79: ='Assumptions'!C49 | D79: 🟢 Assumptions
B80: Land value (land SF × $/SF) | C80: =C36*C79 | D80: both blue inputs above
B82: OPERATING CASH FLOW — 10-year annual (black = formulas; expenses positive, subtracted in subtotals)
B83: Year | C83: 0 / Acq | D83: 1 | E83: 2 | F83: 3 | G83: 4 | H83: 5 | I83: 6 | J83: 7 | K83: 8 | L83: 9 | M83: 10
B84: Year ending | C84: At close | D84: Dec-2027 | E84: Dec-2028 | F84: Dec-2029 | G84: Dec-2030 | H84: Dec-2031 | I84: Dec-2032 | J84: Dec-2033 | K84: Dec-2034 | L84: Dec-2035 | M84: Dec-2036
B85: Occupancy | D85: =(C35+C42)/2 | E85: =C42 | F85: =C42 | G85: =C42 | H85: =C42 | I85: =C42 | J85: =C42 | K85: =C42 | L85: =C42 | M85: =C42
B86: Leased SF | D86: =C34*D85 | E86: =C34*E85 | F86: =C34*F85 | G86: =C34*G85 | H86: =C34*H85 | I86: =C34*I85 | J86: =C34*J85 | K86: =C34*K85 | L86: =C34*L85 | M86: =C34*M85
B87: REVENUE
B88: Base rental income | D88: =D86*C40*(1+C41)^(1-1) | E88: =E86*C40*(1+C41)^(2-1) | F88: =F86*C40*(1+C41)^(3-1) | G88: =G86*C40*(1+C41)^(4-1) | H88: =H86*C40*(1+C41)^(5-1) | I88: =I86*C40*(1+C41)^(6-1) | J88: =J86*C40*(1+C41)^(7-1) | K88: =K86*C40*(1+C41)^(8-1) | L88: =L86*C40*(1+C41)^(9-1) | M88: =M86*C40*(1+C41)^(10-1)
B89: Recoverable opex (gross) | D89: =(C45*C37+C46+C47)*(1+C50)^(1-1) | E89: =(C45*C37+C46+C47)*(1+C50)^(2-1) | F89: =(C45*C37+C46+C47)*(1+C50)^(3-1) | G89: =(C45*C37+C46+C47)*(1+C50)^(4-1) | H89: =(C45*C37+C46+C47)*(1+C50)^(5-1) | I89: =(C45*C37+C46+C47)*(1+C50)^(6-1) | J89: =(C45*C37+C46+C47)*(1+C50)^(7-1) | K89: =(C45*C37+C46+C47)*(1+C50)^(8-1) | L89: =(C45*C37+C46+C47)*(1+C50)^(9-1) | M89: =(C45*C37+C46+C47)*(1+C50)^(10-1)
B90: Expense reimbursements (NNN) | D90: =D89*D85 | E90: =E89*E85 | F90: =F89*F85 | G90: =G89*G85 | H90: =H89*H85 | I90: =I89*I85 | J90: =J89*J85 | K90: =K89*K85 | ... M90: =M89*M85
B91: Less: credit & collection loss | D91: =-D88*C43 | E91: =-E88*C43 | F91: =-F88*C43 | G91: =-G88*C43 | H91: =-H88*C43 | I91: =-I88*C43 | J91: =-J88*C43 | K91: =-K88*C43 | L91: =-L88*C43 | M91: =-M88*C43
B92: Effective Gross Revenue | D92: =D88+D90+D91 | E92: =E88+E90+E91 | F92: =F88+F90+F91 | G92: =G88+G90+G91 | H92: =H88+H90+H91 | I92: =I88+I90+I91 | J92: =J88+J90+J91 | K92: =K88+K90+K91 | ... M92: =M88+M90+M91
B93: OPERATING EXPENSES
B94: Real-estate taxes (reassessed) | D94: =C45*C37*(1+C50)^(1-1) | E94: =C45*C37*(1+C50)^(2-1) | F94: =C45*C37*(1+C50)^(3-1) | G94: =C45*C37*(1+C50)^(4-1) | H94: =C45*C37*(1+C50)^(5-1) | I94: =C45*C37*(1+C50)^(6-1) | J94: =C45*C37*(1+C50)^(7-1) | K94: =C45*C37*(1+C50)^(8-1) | L94: =C45*C37*(1+C50)^(9-1) | M94: =C45*C37*(1+C50)^(10-1)
B95: Insurance | D95: =C46*(1+C50)^(1-1) | E95: =C46*(1+C50)^(2-1) | F95: =C46*(1+C50)^(3-1) | G95: =C46*(1+C50)^(4-1) | H95: =C46*(1+C50)^(5-1) | I95: =C46*(1+C50)^(6-1) | J95: =C46*(1+C50)^(7-1) | K95: =C46*(1+C50)^(8-1) | L95: =C46*(1+C50)^(9-1) | M95: =C46*(1+C50)^(10-1)
B96: CAM | D96: =C47*(1+C50)^(1-1) | E96: =C47*(1+C50)^(2-1) | F96: =C47*(1+C50)^(3-1) | G96: =C47*(1+C50)^(4-1) | H96: =C47*(1+C50)^(5-1) | I96: =C47*(1+C50)^(6-1) | J96: =C47*(1+C50)^(7-1) | K96: =C47*(1+C50)^(8-1) | L96: =C47*(1+C50)^(9-1) | M96: =C47*(1+C50)^(10-1)
B97: Repairs & maintenance | D97: =C48*(1+C50)^(1-1) | E97: =C48*(1+C50)^(2-1) | F97: =C48*(1+C50)^(3-1) | G97: =C48*(1+C50)^(4-1) | H97: =C48*(1+C50)^(5-1) | I97: =C48*(1+C50)^(6-1) | J97: =C48*(1+C50)^(7-1) | K97: =C48*(1+C50)^(8-1) | L97: =C48*(1+C50)^(9-1) | M97: =C48*(1+C50)^(10-1)
B98: Management fee | D98: =D92*C49 | E98: =E92*C49 | F98: =F92*C49 | G98: =G92*C49 | H98: =H92*C49 | I98: =I92*C49 | J98: =J92*C49 | K98: =K92*C49 | L98: =L92*C49 | M98: =M92*C49
B99: Total operating expenses | D99: =SUM(D94:D98) | E99: =SUM(E94:E98) | F99: =SUM(F94:F98) | G99: =SUM(G94:G98) | H99: =SUM(H94:H98) | I99: =SUM(I94:I98) | J99: =SUM(J94:J98) | K99: =SUM(K94:K98) | ... M99: =SUM(M94:M98)
B100: NET OPERATING INCOME | D100: =D92-D99 | E100: =E92-E99 | F100: =F92-F99 | G100: =G92-G99 | H100: =H92-H99 | I100: =I92-I99 | J100: =J92-J99 | K100: =K92-K99 | ... M100: =M92-M99
B101: CAPITAL
B102: Replacement reserves | D102: =C34*C54*(1+C50)^(1-1) | E102: =C34*C54*(1+C50)^(2-1) | F102: =C34*C54*(1+C50)^(3-1) | G102: =C34*C54*(1+C50)^(4-1) | H102: =C34*C54*(1+C50)^(5-1) | I102: =C34*C54*(1+C50)^(6-1) | J102: =C34*C54*(1+C50)^(7-1) | K102: =C34*C54*(1+C50)^(8-1) | L102: =C34*C54*(1+C50)^(9-1) | M102: =C34*C54*(1+C50)^(10-1)
B103: Leasing costs (TI/LC + rollover) | D103: =C75*(C52+C53)+C34*C55 | E103: =C34*C55*(1+C50)^(2-1) | F103: =C34*C55*(1+C50)^(3-1) | G103: =C34*C55*(1+C50)^(4-1) | H103: =C34*C55*(1+C50)^(5-1) | I103: =C34*C55*(1+C50)^(6-1) | J103: =C34*C55*(1+C50)^(7-1) | K103: =C34*C55*(1+C50)^(8-1) | L103: =C34*C55*(1+C50)^(9-1) | M103: =C34*C55*(1+C50)^(10-1)
B104: Total capital | D104: =D102+D103 | E104: =E102+E103 | F104: =F102+F103 | G104: =G102+G103 | H104: =H102+H103 | I104: =I102+I103 | J104: =J102+J103 | K104: =K102+K103 | ... M104: =M102+M103
B105: Unlevered cash flow (before reversion) | C105: =-C57*(1+C58) | D105: =D100-D104 | E105: =E100-E104 | F105: =F100-F104 | G105: =G100-G104 | H105: =H100-H104 | I105: =I100-I104 | J105: =J100-J104 | K105: =K100-K104 | ... M105: =M100-M104
...

Sheet Publix & Starbucks
B1: PUBLIX + STARBUCKS · SALE-LEASEBACK (acquire fee, lease back during entitlement)
B2: 2501–2519 E Sunrise Blvd | Folio 49-42-36-12-0060 | REAL SUB LLC (Publix) · 36,822 SF · built 2011 · acquire the fee → Publix leases back → rent covers carry while you entitle the land
B4: PROPERTY FACTS — ✅ BCPA / 🔶 SALE-LEASEBACK STRUCTURE (leaseback terms on the Assumptions tab)
B5: Record owner (today) | D5: REAL SUB LLC (Publix Super Markets real-estate entity, Lakeland FL) — fee owner
B6: Deal structure | D6: Sale-leaseback: DAWN RE acquires the fee; Publix leases back and pays rent during the entitlement period, then vacates for redevelopment
B7: Building | D7: 36,822 SF (Publix ~34,622 SF leaseback + Starbucks drive-thru pad ~2,200 SF)
B8: Land | D8: 109,791 SF (2.520 ac)
B9: Year built | D9: 2011 (eff. 2012)
B10: Last sale | D10: 03/14/2025 — $25,000,000 (Trustee's Deed) = $679/SF bldg · $228/SF land
B11: 2025 real-estate taxes | D11: $208,467 (2024: $217,404) — NNN, reimbursed by Publix during leaseback
B12: Leaseback economics | D12: Publix leaseback ~$22/SF NNN (bridge rate) + Starbucks pad ~$60/SF NNN; ~4-yr term (adjustable on Assumptions tab)
B13: Covered-land logic | D13: The leaseback rent covers the operating carry (Publix pays taxes/ins NNN) while the land is entitled; the play is the dirt, not the current yield
B14: Standalone return (below) | D14: NEGATIVE on a pure income basis by design — you pay land value ($25M) for income supporting only ~$13M. The return is the LAND, realized via the assemblage / redevelopment; the leaseback (DSCR ≈ 1.0x) simply covers the entitlement carry
B16: RENT ROLL — 🔶 sale-leaseback terms (set on the Assumptions tab · Publix block)
B17: Tenant / component | E17: Category | G17: SF | H17: $/SF NNN | I17: Annual rent | L17: Note
B18: Publix (sale-leaseback) | E18: Grocery anchor (credit) — leases back during entitlement | G18: 34622 | H18: 22 | I18: =G18*H18 | L18: leaseback NNN; terms on Assumptions tab
B19: Starbucks (drive-thru pad) | E19: QSR pad (credit) | G19: 2200 | H19: 60 | I19: =G19*H19 | L19: pad NNN; terms on Assumptions tab
B20: TOTAL / WTD AVG | G20: =SUM(G18:G19) | H20: =IFERROR(SUM(I18:I19)/SUM(G18:G19),0) | I20: =SUM(I18:I19) | L20: 100% occ · credit tenants · sale-leaseback
B22: ASSUMPTIONS — 🔵 blue = hardcoded inputs
B23: Property & revenue
B24: Rentable SF | C24: 36822 | D24: ✅ BCPA (36,822 SF)
B25: Land (SF) | C25: ='Assumptions'!C64 | D25: 🟢 Assumptions
B26: In-place occupancy | C26: ='Assumptions'!C71 | D26: 🟢 Assumptions
B27: Stabilized occupancy | C27: ='Assumptions'!C72 | D27: 🟢 Assumptions
B28: Blended NNN rent ($/SF) — leaseback + pad | C28: =('Assumptions'!C67*'Assumptions'!C66+'Assumptions'!C69*'Assumptions'!C68)/C24 | D28: 🟢 computed from Publix leaseback + Starbucks pad (Assumptions)
B29: Rent growth | C29: 0.02 | D29: 🔶
B30: Credit & collection loss | C30: 0.01 | D30: 🔶
B31: Effective millage | C31: 0.0191 | D31: ✅ 2025
B32: Operating expenses
B33: Insurance ($/yr) | C33: ='Assumptions'!C73 | D33: 🟢 Assumptions
B34: CAM ($/yr, recoverable) | C34: ='Assumptions'!C74 | D34: 🟢 Assumptions
B35: Repairs & maintenance ($/yr) | C35: ='Assumptions'!C75 | D35: 🟢 Assumptions
B36: Management fee (% EGR) | C36: ='Assumptions'!C76 | D36: 🟢 Assumptions
B37: Expense growth | C37: 0.03 | D37: 🔶
B38: Capital
B39: Tenant improvements ($/SF) | C39: 0 | D39: 🔶 on leased-up SF
B40: Leasing commissions ($/SF) | C40: 0 | D40: 🔶 on leased-up SF
B41: Replacement reserves ($/SF/yr) | C41: 0.15 | D41: 🔶
B42: Rollover leasing reserve ($/SF/yr) | C42: 0.15 | D42: 🔶
B43: Acquisition & financing
B44: Purchase price / basis | C44: ='Assumptions'!C63 | D44: 🟢 Assumptions
B45: Closing & acq costs (% price) | C45: 0.02 | D45: 🔶
B46: Senior loan LTV | C46: ='Assumptions'!C79 | D46: 🟢 Assumptions
B47: Senior loan rate | C47: ='Assumptions'!C80 | D47: 🟢 Assumptions
B48: Senior loan amortization (yrs) | C48: 30 | D48: 🔶
B49: Valuation & hold
B50: Going-in cap | C50: ='Assumptions'!C77 | D50: 🟢 Assumptions
B51: Exit / reversion cap | C51: ='Assumptions'!C78 | D51: 🟢 Assumptions
B52: Cost of sale at exit | C52: 0.02 | D52: 🔶
B53: Hold period (yrs) | C53: 5 | D53: 🔶
B54: Discount rate (NPV) | C54: 0.07 | D54: 🔶
B55: Land value ($/SF) | C55: ='Assumptions'!C65 | D55: 🟢 Assumptions
B57: DERIVED VALUES & DEBT SIZING
B58: Senior loan amount | C58: =C44*C46 | D58: price × LTV
B59: Monthly rate | C59: =C47/12
B60: Annual debt service | C60: =C58*(C59/(1-(1+C59)^(-C48*12)))*12
B61: Equity at acquisition | C61: =C44*(1+C45)-C58
B62: Absorption SF (lease-up) | C62: =C24*(C27-C26)
B63: Initial leasing capital | C63: =C62*(C39+C40)
B64: Total cost basis | C64: =C44*(1+C45)+C63
B65: Total equity required | C65: =C64-C58
B66: Income value (Yr-1 NOI ÷ going-in cap) | C66: =D87/C50 | D66: computed below
B67: Land value (land SF × $/SF) | C67: =C25*C55 | D67: land SF × land $/SF (both blue inputs above)
B69: OPERATING CASH FLOW — 10-year annual
B70: Year | C70: 0 / Acq | D70: 1 | E70: 2 | F70: 3 | G70: 4 | H70: 5 | I70: 6 | J70: 7 | K70: 8 | L70: 9 | M70: 10
B71: Year ending | C71: At close | D71: Dec-2027 | E71: Dec-2028 | F71: Dec-2029 | G71: Dec-2030 | H71: Dec-2031 | I71: Dec-2032 | J71: Dec-2033 | K71: Dec-2034 | L71: Dec-2035 | M71: Dec-2036
B72: Occupancy | D72: =(C26+C27)/2 | E72: =C27 | F72: =C27 | G72: =C27 | H72: =C27 | I72: =C27 | J72: =C27 | K72: =C27 | L72: =C27 | M72: =C27
B73: Leased SF | D73: =C24*D72 | E73: =C24*E72 | F73: =C24*F72 | G73: =C24*G72 | H73: =C24*H72 | I73: =C24*I72 | J73: =C24*J72 | K73: =C24*K72 | L73: =C24*L72 | M73: =C24*M72
B74: REVENUE
B75: Base rental income (leaseback cliffs at term) | D75: =IF(1<='Assumptions'!C70,D73*C28*(1+C29)^(1-1),0) | E75: =IF(2<='Assumptions'!C70,E73*C28*(1+C29)^(2-1),0) | F75: =IF(3<='Assumptions'!C70,F73*C28*(1+C29)^(3-1),0) | G75: =IF(4<='Assumptions'!C70,G73*C28*(1+C29)^(4-1),0) | H75: =IF(5<='Assumptions'!C70,H73*C28*(1+C29)^(5-1),0) | I75: =IF(6<='Assumptions'!C70,I73*C28*(1+C29)^(6-1),0) | J75: =IF(7<='Assumptions'!C70,J73*C28*(1+C29)^(7-1),0) | K75: =IF(8<='Assumptions'!C70,K73*C28*(1+C29)^(8-1),0) | L75: =IF(9<='Assumptions'!C70,L73*C28*(1+C29)^(9-1),0) | M75: =IF(10<='Assumptions'!C70,M73*C28*(1+C29)^(10-1),0)
B76: Recoverable opex (gross) | D76: =(C44*C31+C33+C34)*(1+C37)^(1-1) | E76: =(C44*C31+C33+C34)*(1+C37)^(2-1) | F76: =(C44*C31+C33+C34)*(1+C37)^(3-1) | G76: =(C44*C31+C33+C34)*(1+C37)^(4-1) | H76: =(C44*C31+C33+C34)*(1+C37)^(5-1) | I76: =(C44*C31+C33+C34)*(1+C37)^(6-1) | J76: =(C44*C31+C33+C34)*(1+C37)^(7-1) | K76: =(C44*C31+C33+C34)*(1+C37)^(8-1) | L76: =(C44*C31+C33+C34)*(1+C37)^(9-1) | M76: =(C44*C31+C33+C34)*(1+C37)^(10-1)
B77: Expense reimbursements (NNN) | D77: =D76*D72 | E77: =E76*E72 | F77: =F76*F72 | G77: =G76*G72 | H77: =H76*H72 | I77: =I76*I72 | J77: =J76*J72 | K77: =K76*K72 | ... M77: =M76*M72
B78: Less: credit & collection loss | D78: =-D75*C30 | E78: =-E75*C30 | F78: =-F75*C30 | G78: =-G75*C30 | H78: =-H75*C30 | I78: =-I75*C30 | J78: =-J75*C30 | K78: =-K75*C30 | L78: =-L75*C30 | M78: =-M75*C30
B79: Effective Gross Revenue | D79: =D75+D77+D78 | E79: =E75+E77+E78 | F79: =F75+F77+F78 | G79: =G75+G77+G78 | H79: =H75+H77+H78 | I79: =I75+I77+I78 | J79: =J75+J77+J78 | K79: =K75+K77+K78 | ... M79: =M75+M77+M78
B80: OPERATING EXPENSES
B81: Real-estate taxes (reassessed) | D81: =C44*C31*(1+C37)^(1-1) | E81: =C44*C31*(1+C37)^(2-1) | F81: =C44*C31*(1+C37)^(3-1) | G81: =C44*C31*(1+C37)^(4-1) | H81: =C44*C31*(1+C37)^(5-1) | I81: =C44*C31*(1+C37)^(6-1) | J81: =C44*C31*(1+C37)^(7-1) | K81: =C44*C31*(1+C37)^(8-1) | L81: =C44*C31*(1+C37)^(9-1) | M81: =C44*C31*(1+C37)^(10-1)
B82: Insurance | D82: =C33*(1+C37)^(1-1) | E82: =C33*(1+C37)^(2-1) | F82: =C33*(1+C37)^(3-1) | G82: =C33*(1+C37)^(4-1) | H82: =C33*(1+C37)^(5-1) | I82: =C33*(1+C37)^(6-1) | J82: =C33*(1+C37)^(7-1) | K82: =C33*(1+C37)^(8-1) | L82: =C33*(1+C37)^(9-1) | M82: =C33*(1+C37)^(10-1)
B83: CAM | D83: =C34*(1+C37)^(1-1) | E83: =C34*(1+C37)^(2-1) | F83: =C34*(1+C37)^(3-1) | G83: =C34*(1+C37)^(4-1) | H83: =C34*(1+C37)^(5-1) | I83: =C34*(1+C37)^(6-1) | J83: =C34*(1+C37)^(7-1) | K83: =C34*(1+C37)^(8-1) | L83: =C34*(1+C37)^(9-1) | M83: =C34*(1+C37)^(10-1)
B84: Repairs & maintenance | D84: =C35*(1+C37)^(1-1) | E84: =C35*(1+C37)^(2-1) | F84: =C35*(1+C37)^(3-1) | G84: =C35*(1+C37)^(4-1) | H84: =C35*(1+C37)^(5-1) | I84: =C35*(1+C37)^(6-1) | J84: =C35*(1+C37)^(7-1) | K84: =C35*(1+C37)^(8-1) | L84: =C35*(1+C37)^(9-1) | M84: =C35*(1+C37)^(10-1)
B85: Management fee | D85: =D79*C36 | E85: =E79*C36 | F85: =F79*C36 | G85: =G79*C36 | H85: =H79*C36 | I85: =I79*C36 | J85: =J79*C36 | K85: =K79*C36 | L85: =L79*C36 | M85: =M79*C36
B86: Total operating expenses | D86: =SUM(D81:D85) | E86: =SUM(E81:E85) | F86: =SUM(F81:F85) | G86: =SUM(G81:G85) | H86: =SUM(H81:H85) | I86: =SUM(I81:I85) | J86: =SUM(J81:J85) | K86: =SUM(K81:K85) | ... M86: =SUM(M81:M85)
B87: NET OPERATING INCOME | D87: =D79-D86 | E87: =E79-E86 | F87: =F79-F86 | G87: =G79-G86 | H87: =H79-H86 | I87: =I79-I86 | J87: =J79-J86 | K87: =K79-K86 | ... M87: =M79-M86
B88: CAPITAL
B89: Replacement reserves | D89: =C24*C41*(1+C37)^(1-1) | E89: =C24*C41*(1+C37)^(2-1) | F89: =C24*C41*(1+C37)^(3-1) | G89: =C24*C41*(1+C37)^(4-1) | H89: =C24*C41*(1+C37)^(5-1) | I89: =C24*C41*(1+C37)^(6-1) | J89: =C24*C41*(1+C37)^(7-1) | K89: =C24*C41*(1+C37)^(8-1) | L89: =C24*C41*(1+C37)^(9-1) | M89: =C24*C41*(1+C37)^(10-1)
B90: Leasing costs | D90: =C62*(C39+C40)+C24*C42 | E90: =C24*C42*(1+C37)^(2-1) | F90: =C24*C42*(1+C37)^(3-1) | G90: =C24*C42*(1+C37)^(4-1) | H90: =C24*C42*(1+C37)^(5-1) | I90: =C24*C42*(1+C37)^(6-1) | J90: =C24*C42*(1+C37)^(7-1) | K90: =C24*C42*(1+C37)^(8-1) | L90: =C24*C42*(1+C37)^(9-1) | M90: =C24*C42*(1+C37)^(10-1)
B91: Total capital | D91: =D89+D90 | E91: =E89+E90 | F91: =F89+F90 | G91: =G89+G90 | H91: =H89+H90 | I91: =I89+I90 | J91: =J89+J90 | K91: =K89+K90 | ... M91: =M89+M90
B92: Unlevered cash flow (before reversion) | C92: =-C44*(1+C45) | D92: =D87-D91 | E92: =E87-E91 | F92: =F87-F91 | G92: =G87-G91 | H92: =H87-H91 | I92: =I87-I91 | J92: =J87-J91 | K92: =K87-K91 | ... M92: =M87-M91
B94: REVERSION, DEBT SERVICE & LEVERED CASH FLOW
B95: Net sale — land value (covered-land exit) | D95: =IF(1=C53,C67*(1-C52),0) | E95: =IF(2=C53,C67*(1-C52),0) | F95: =IF(3=C53,C67*(1-C52),0) | G95: =IF(4=C53,C67*(1-C52),0) | H95: =IF(5=C53,C67*(1-C52),0) | I95: =IF(6=C53,C67*(1-C52),0) | J95: =IF(7=C53,C67*(1-C52),0) | K95: =IF(8=C53,C67*(1-C52),0) | L95: =IF(9=C53,C67*(1-C52),0) | M95: =IF(10=C53,C67*(1-C52),0)
B96: UNLEVERED PROJECT CASH FLOW | C96: =C92 | D96: =IF(1<=C53,D92,0)+D95 | E96: =IF(2<=C53,E92,0)+E95 | F96: =IF(3<=C53,F92,0)+F95 | G96: =IF(4<=C53,G92,0)+G95 | H96: =IF(5<=C53,H92,0)+H95 | I96: =IF(6<=C53,I92,0)+I95 | J96: =IF(7<=C53,J92,0)+J95 | K96: =IF(8<=C53,K92,0)+K95 | L96: =IF(9<=C53,L92,0)+L95 | M96: =IF(10<=C53,M92,0)+M95
B97: Debt service | D97: =IF(1<=C53,-C60,0) | E97: =IF(2<=C53,-C60,0) | F97: =IF(3<=C53,-C60,0) | G97: =IF(4<=C53,-C60,0) | H97: =IF(5<=C53,-C60,0) | I97: =IF(6<=C53,-C60,0) | J97: =IF(7<=C53,-C60,0) | K97: =IF(8<=C53,-C60,0) | L97: =IF(9<=C53,-C60,0) | M97: =IF(10<=C53,-C60,0)
B98: Loan balance (year-end) | D98: =C58*(1+C59)^(12*1)-(C60/12)*((1+C59)^(12*1)-1)/C59 | E98: =C58*(1+C59)^(12*2)-(C60/12)*((1+C59)^(12*2)-1)/C59 | F98: =C58*(1+C59)^(12*3)-(C60/12)*((1+C59)^(12*3)-1)/C59 | G98: =C58*(1+C59)^(12*4)-(C60/12)*((1+C59)^(12*4)-1)/C59 | H98: =C58*(1+C59)^(12*5)-(C60/12)*((1+C59)^(12*5)-1)/C59 | I98: =C58*(1+C59)^(12*6)-(C60/12)*((1+C59)^(12*6)-1)/C59 | J98: =C58*(1+C59)^(12*7)-(C60/12)*((1+C59)^(12*7)-1)/C59 | K98: =C58*(1+C59)^(12*8)-(C60/12)*((1+C59)^(12*8)-1)/C59 | L98: =C58*(1+C59)^(12*9)-(C60/12)*((1+C59)^(12*9)-1)/C59 | M98: =C58*(1+C59)^(12*10)-(C60/12)*((1+C59)^(12*10)-1)/C59
B99: DSCR (NOI ÷ DS) | D99: =D87/C60 | E99: =E87/C60 | F99: =F87/C60 | G99: =G87/C60 | H99: =H87/C60 | I99: =I87/C60 | J99: =J87/C60 | K99: =K87/C60 | L99: =L87/C60 | M99: =M87/C60
B100: Debt yield (NOI ÷ loan) | D100: =D87/C58 | E100: =E87/C58 | F100: =F87/C58 | G100: =G87/C58 | H100: =H87/C58 | I100: =I87/C58 | J100: =J87/C58 | K100: =K87/C58 | L100: =L87/C58 | M100: =M87/C58
B101: LEVERED CASH FLOW (equity) | C101: =-C61 | D101: =IF(1<=C53,D92-C60,0)+IF(1=C53,D95-D98,0) | E101: =IF(2<=C53,E92-C60,0)+IF(2=C53,E95-E98,0) | F101: =IF(3<=C53,F92-C60,0)+IF(3=C53,F95-F98,0) | G101: =IF(4<=C53,G92-C60,0)+IF(4=C53,G95-G98,0) | H101: =IF(5<=C53,H92-C60,0)+IF(5=C53,H95-H98,0) | I101: =IF(6<=C53,I92-C60,0)+IF(6=C53,I95-I98,0) | J101: =IF(7<=C53,J92-C60,0)+IF(7=C53,J95-J98,0) | K101: =IF(8<=C53,K92-C60,0)+IF(8=C53,K95-K98,0) | L101: =IF(9<=C53,L92-C60,0)+IF(9=C53,L95-L98,0) | M101: =IF(10<=C53,M92-C60,0)+IF(10=C53,M95-M98,0)
B103: RETURNS — unlevered & levered
B104: Unlevered IRR | C104: =IFERROR(IRR(C96:M96),"n/m")
B105: Unlevered equity multiple | C105: =SUM(D96:M96)/-C96
B106: Unlevered NPV @ discount rate | C106: =C96+NPV(C54,D96:M96)
B107: Levered IRR | C107: =IFERROR(IRR(C101:M101),"n/m")
...

Sheet Sunrise Plaza
B1: SUNRISE PLAZA · ADJACENT RETAIL CENTER (2465–2485, incl. 2473)
B2: 2465–2485 E Sunrise Blvd | Folio 49-42-36-12-0011 | Kar Luen Inc · 25,105 SF · built 1962 (remod. 1987) · SEPARATE parcel from the 2455 office condo · restaurant/jeweler value-add
B4: PROPERTY FACTS — ⚠️ REPORTED (BCPA blocked in build env; LoopNet/Sunbiz sourced)
B5: Record owner | D5: Kar Luen Inc (FL corp est. 1994; registered at 2465 E Sunrise)
B6: Parcel scope | D6: 2465 / 2473 / 2485 E Sunrise — one folio (-0011); DISTINCT from the 2455 office condo (its own tab)
B7: Building | D7: 25,105 SF, 2-story retail/commercial
B8: Land | D8: 0.71 ac ≈ 30,928 SF
B9: Year built | D9: 1962 (remodeled 1987)
B10: Zoning | D10: Community Business (CB) / B-1 corridor
B11: Anchor tenant | D11: Daoud's Fine Jewelry — 100+ yr family jeweler at 2473 (~6,000 SF)
B12: Reported value | D12: ≈ $8.5M (UNVERIFIED — no recent arm's-length sale)
B13: Last recorded sale | D13: Oct 2000 — $128,000 (stale/partial; not a value indicator)
B15: RENT ROLL (2465–2485 E Sunrise, incl. 2473) — 🔶 tenants REPORTED (Yelp/LoopNet); suite SF & rents estimated
B16: Tenant / component | E16: Category | G16: SF | H16: $/SF NNN | I16: Annual rent | L16: Note
B17: 2473 · Daoud's Fine Jewelry | E17: Retail – jeweler (anchor) | G17: 6000 | H17: 34 | I17: =G17*H17 | L17: 100+ yr family business
B18: 2465 · Sunness Supper Club | E18: Restaurant | G18: 4000 | H18: 36 | I18: =G18*H18 | L18: corner restaurant
B19: 2475 · BurgerFi | E19: Fast-casual restaurant | G19: 3000 | H19: 40 | I19: =G19*H19 | L19: national franchise
B20: 2485 · In-line shops | E20: Various local retail/service | G20: 6005 | H20: 30 | I20: =G20*H20 | L20: balance of occupied
B21: 2481 · SFL Maven | E21: Retail / resale | G21: 1100 | H21: 32 | I21: =G21*H21 | L21: small-shop
B22: VACANT / available | E22: Lease-up upside | G22: 5000 | H22: — | I22: — | L22: value-add
B23: TOTAL / WTD AVG | G23: =SUM(G17:G22) | H23: =IFERROR(SUM(I17:I21)/SUM(G17:G21),0) | I23: =SUM(I17:I21) | L23: Daoud's = anchor; ~20% vacant
B25: ASSUMPTIONS — 🔵 blue = hardcoded inputs
B26: Property & revenue
B27: Rentable SF | C27: 25105 | D27: ⚠️ LoopNet (25,105 SF)
B28: Land (SF) | C28: ='Assumptions'!C84 | D28: 🟢 Assumptions
B29: In-place occupancy | C29: ='Assumptions'!C87 | D29: 🟢 Assumptions
B30: Stabilized occupancy | C30: ='Assumptions'!C88 | D30: 🟢 Assumptions
B31: Market rent ($/SF NNN) | C31: ='Assumptions'!C86 | D31: 🟢 Assumptions
B32: Rent growth | C32: 0.03 | D32: 🔶
B33: Credit & collection loss | C33: 0.03 | D33: 🔶
B34: Effective millage | C34: 0.0191 | D34: ✅ 2025 area millage
B35: Operating expenses
B36: Insurance ($/yr) | C36: ='Assumptions'!C89 | D36: 🟢 Assumptions
B37: CAM ($/yr, recoverable) | C37: ='Assumptions'!C90 | D37: 🟢 Assumptions
B38: Repairs & maintenance ($/yr) | C38: ='Assumptions'!C91 | D38: 🟢 Assumptions
B39: Management fee (% EGR) | C39: ='Assumptions'!C92 | D39: 🟢 Assumptions
B40: Expense growth | C40: 0.03 | D40: 🔶
B41: Capital
B42: Tenant improvements ($/SF) | C42: 30 | D42: 🔶 on leased-up SF
B43: Leasing commissions ($/SF) | C43: 20 | D43: 🔶 on leased-up SF
B44: Replacement reserves ($/SF/yr) | C44: 0.15 | D44: 🔶
B45: Rollover leasing reserve ($/SF/yr) | C45: 0.75 | D45: 🔶
B46: Acquisition & financing
B47: Purchase price / basis | C47: ='Assumptions'!C83 | D47: 🟢 Assumptions
B48: Closing & acq costs (% price) | C48: 0.025 | D48: 🔶
B49: Senior loan LTV | C49: ='Assumptions'!C95 | D49: 🟢 Assumptions
B50: Senior loan rate | C50: ='Assumptions'!C96 | D50: 🟢 Assumptions
B51: Senior loan amortization (yrs) | C51: 30 | D51: 🔶
B52: Valuation & hold
B53: Going-in cap | C53: ='Assumptions'!C93 | D53: 🟢 Assumptions
B54: Exit / reversion cap | C54: ='Assumptions'!C94 | D54: 🟢 Assumptions
B55: Cost of sale at exit | C55: 0.02 | D55: 🔶
B56: Hold period (yrs) | C56: 5 | D56: 🔶
B57: Discount rate (NPV) | C57: 0.09 | D57: 🔶
B58: Land value ($/SF) | C58: ='Assumptions'!C85 | D58: 🟢 Assumptions
B60: DERIVED VALUES & DEBT SIZING
B61: Senior loan amount | C61: =C47*C49 | D61: price × LTV
B62: Monthly rate | C62: =C50/12
B63: Annual debt service | C63: =C61*(C62/(1-(1+C62)^(-C51*12)))*12
B64: Equity at acquisition | C64: =C47*(1+C48)-C61
B65: Absorption SF (lease-up) | C65: =C27*(C30-C29)
B66: Initial leasing capital | C66: =C65*(C42+C43)
B67: Total cost basis | C67: =C47*(1+C48)+C66
B68: Total equity required | C68: =C67-C61
B69: Income value (Yr-1 NOI ÷ going-in cap) | C69: =D90/C53 | D69: computed below
B70: Land value (land SF × $/SF) | C70: =C28*C58 | D70: land SF × land $/SF (both blue inputs above)
B72: OPERATING CASH FLOW — 10-year annual
B73: Year | C73: 0 / Acq | D73: 1 | E73: 2 | F73: 3 | G73: 4 | H73: 5 | I73: 6 | J73: 7 | K73: 8 | L73: 9 | M73: 10
B74: Year ending | C74: At close | D74: Dec-2027 | E74: Dec-2028 | F74: Dec-2029 | G74: Dec-2030 | H74: Dec-2031 | I74: Dec-2032 | J74: Dec-2033 | K74: Dec-2034 | L74: Dec-2035 | M74: Dec-2036
B75: Occupancy | D75: =(C29+C30)/2 | E75: =C30 | F75: =C30 | G75: =C30 | H75: =C30 | I75: =C30 | J75: =C30 | K75: =C30 | L75: =C30 | M75: =C30
B76: Leased SF | D76: =C27*D75 | E76: =C27*E75 | F76: =C27*F75 | G76: =C27*G75 | H76: =C27*H75 | I76: =C27*I75 | J76: =C27*J75 | K76: =C27*K75 | L76: =C27*L75 | M76: =C27*M75
B77: REVENUE
B78: Base rental income | D78: =D76*C31*(1+C32)^(1-1) | E78: =E76*C31*(1+C32)^(2-1) | F78: =F76*C31*(1+C32)^(3-1) | G78: =G76*C31*(1+C32)^(4-1) | H78: =H76*C31*(1+C32)^(5-1) | I78: =I76*C31*(1+C32)^(6-1) | J78: =J76*C31*(1+C32)^(7-1) | K78: =K76*C31*(1+C32)^(8-1) | L78: =L76*C31*(1+C32)^(9-1) | M78: =M76*C31*(1+C32)^(10-1)
B79: Recoverable opex (gross) | D79: =(C47*C34+C36+C37)*(1+C40)^(1-1) | E79: =(C47*C34+C36+C37)*(1+C40)^(2-1) | F79: =(C47*C34+C36+C37)*(1+C40)^(3-1) | G79: =(C47*C34+C36+C37)*(1+C40)^(4-1) | H79: =(C47*C34+C36+C37)*(1+C40)^(5-1) | I79: =(C47*C34+C36+C37)*(1+C40)^(6-1) | J79: =(C47*C34+C36+C37)*(1+C40)^(7-1) | K79: =(C47*C34+C36+C37)*(1+C40)^(8-1) | L79: =(C47*C34+C36+C37)*(1+C40)^(9-1) | M79: =(C47*C34+C36+C37)*(1+C40)^(10-1)
B80: Expense reimbursements (NNN) | D80: =D79*D75 | E80: =E79*E75 | F80: =F79*F75 | G80: =G79*G75 | H80: =H79*H75 | I80: =I79*I75 | J80: =J79*J75 | K80: =K79*K75 | ... M80: =M79*M75
B81: Less: credit & collection loss | D81: =-D78*C33 | E81: =-E78*C33 | F81: =-F78*C33 | G81: =-G78*C33 | H81: =-H78*C33 | I81: =-I78*C33 | J81: =-J78*C33 | K81: =-K78*C33 | L81: =-L78*C33 | M81: =-M78*C33
B82: Effective Gross Revenue | D82: =D78+D80+D81 | E82: =E78+E80+E81 | F82: =F78+F80+F81 | G82: =G78+G80+G81 | H82: =H78+H80+H81 | I82: =I78+I80+I81 | J82: =J78+J80+J81 | K82: =K78+K80+K81 | ... M82: =M78+M80+M81
B83: OPERATING EXPENSES
B84: Real-estate taxes (reassessed) | D84: =C47*C34*(1+C40)^(1-1) | E84: =C47*C34*(1+C40)^(2-1) | F84: =C47*C34*(1+C40)^(3-1) | G84: =C47*C34*(1+C40)^(4-1) | H84: =C47*C34*(1+C40)^(5-1) | I84: =C47*C34*(1+C40)^(6-1) | J84: =C47*C34*(1+C40)^(7-1) | K84: =C47*C34*(1+C40)^(8-1) | L84: =C47*C34*(1+C40)^(9-1) | M84: =C47*C34*(1+C40)^(10-1)
B85: Insurance | D85: =C36*(1+C40)^(1-1) | E85: =C36*(1+C40)^(2-1) | F85: =C36*(1+C40)^(3-1) | G85: =C36*(1+C40)^(4-1) | H85: =C36*(1+C40)^(5-1) | I85: =C36*(1+C40)^(6-1) | J85: =C36*(1+C40)^(7-1) | K85: =C36*(1+C40)^(8-1) | L85: =C36*(1+C40)^(9-1) | M85: =C36*(1+C40)^(10-1)
B86: CAM | D86: =C37*(1+C40)^(1-1) | E86: =C37*(1+C40)^(2-1) | F86: =C37*(1+C40)^(3-1) | G86: =C37*(1+C40)^(4-1) | H86: =C37*(1+C40)^(5-1) | I86: =C37*(1+C40)^(6-1) | J86: =C37*(1+C40)^(7-1) | K86: =C37*(1+C40)^(8-1) | L86: =C37*(1+C40)^(9-1) | M86: =C37*(1+C40)^(10-1)
B87: Repairs & maintenance | D87: =C38*(1+C40)^(1-1) | E87: =C38*(1+C40)^(2-1) | F87: =C38*(1+C40)^(3-1) | G87: =C38*(1+C40)^(4-1) | H87: =C38*(1+C40)^(5-1) | I87: =C38*(1+C40)^(6-1) | J87: =C38*(1+C40)^(7-1) | K87: =C38*(1+C40)^(8-1) | L87: =C38*(1+C40)^(9-1) | M87: =C38*(1+C40)^(10-1)
B88: Management fee | D88: =D82*C39 | E88: =E82*C39 | F88: =F82*C39 | G88: =G82*C39 | H88: =H82*C39 | I88: =I82*C39 | J88: =J82*C39 | K88: =K82*C39 | L88: =L82*C39 | M88: =M82*C39
B89: Total operating expenses | D89: =SUM(D84:D88) | E89: =SUM(E84:E88) | F89: =SUM(F84:F88) | G89: =SUM(G84:G88) | H89: =SUM(H84:H88) | I89: =SUM(I84:I88) | J89: =SUM(J84:J88) | K89: =SUM(K84:K88) | ... M89: =SUM(M84:M88)
B90: NET OPERATING INCOME | D90: =D82-D89 | E90: =E82-E89 | F90: =F82-F89 | G90: =G82-G89 | H90: =H82-H89 | I90: =I82-I89 | J90: =J82-J89 | K90: =K82-K89 | ... M90: =M82-M89
B91: CAPITAL
B92: Replacement reserves | D92: =C27*C44*(1+C40)^(1-1) | E92: =C27*C44*(1+C40)^(2-1) | F92: =C27*C44*(1+C40)^(3-1) | G92: =C27*C44*(1+C40)^(4-1) | H92: =C27*C44*(1+C40)^(5-1) | I92: =C27*C44*(1+C40)^(6-1) | J92: =C27*C44*(1+C40)^(7-1) | K92: =C27*C44*(1+C40)^(8-1) | L92: =C27*C44*(1+C40)^(9-1) | M92: =C27*C44*(1+C40)^(10-1)
B93: Leasing costs | D93: =C65*(C42+C43)+C27*C45 | E93: =C27*C45*(1+C40)^(2-1) | F93: =C27*C45*(1+C40)^(3-1) | G93: =C27*C45*(1+C40)^(4-1) | H93: =C27*C45*(1+C40)^(5-1) | I93: =C27*C45*(1+C40)^(6-1) | J93: =C27*C45*(1+C40)^(7-1) | K93: =C27*C45*(1+C40)^(8-1) | L93: =C27*C45*(1+C40)^(9-1) | M93: =C27*C45*(1+C40)^(10-1)
B94: Total capital | D94: =D92+D93 | E94: =E92+E93 | F94: =F92+F93 | G94: =G92+G93 | H94: =H92+H93 | I94: =I92+I93 | J94: =J92+J93 | K94: =K92+K93 | ... M94: =M92+M93
B95: Unlevered cash flow (before reversion) | C95: =-C47*(1+C48) | D95: =D90-D94 | E95: =E90-E94 | F95: =F90-F94 | G95: =G90-G94 | H95: =H90-H94 | I95: =I90-I94 | J95: =J90-J94 | K95: =K90-K94 | ... M95: =M90-M94
B97: REVERSION, DEBT SERVICE & LEVERED CASH FLOW
B98: Net sale proceeds (exit year) | D98: =IF(1=C56,(D90*(1+C32)/C54)*(1-C55),0) | E98: =IF(2=C56,(E90*(1+C32)/C54)*(1-C55),0) | F98: =IF(3=C56,(F90*(1+C32)/C54)*(1-C55),0) | G98: =IF(4=C56,(G90*(1+C32)/C54)*(1-C55),0) | H98: =IF(5=C56,(H90*(1+C32)/C54)*(1-C55),0) | I98: =IF(6=C56,(I90*(1+C32)/C54)*(1-C55),0) | J98: =IF(7=C56,(J90*(1+C32)/C54)*(1-C55),0) | K98: =IF(8=C56,(K90*(1+C32)/C54)*(1-C55),0) | L98: =IF(9=C56,(L90*(1+C32)/C54)*(1-C55),0) | M98: =IF(10=C56,(M90*(1+C32)/C54)*(1-C55),0)
B99: UNLEVERED PROJECT CASH FLOW | C99: =C95 | D99: =IF(1<=C56,D95,0)+D98 | E99: =IF(2<=C56,E95,0)+E98 | F99: =IF(3<=C56,F95,0)+F98 | G99: =IF(4<=C56,G95,0)+G98 | H99: =IF(5<=C56,H95,0)+H98 | I99: =IF(6<=C56,I95,0)+I98 | J99: =IF(7<=C56,J95,0)+J98 | K99: =IF(8<=C56,K95,0)+K98 | L99: =IF(9<=C56,L95,0)+L98 | M99: =IF(10<=C56,M95,0)+M98
B100: Debt service | D100: =IF(1<=C56,-C63,0) | E100: =IF(2<=C56,-C63,0) | F100: =IF(3<=C56,-C63,0) | G100: =IF(4<=C56,-C63,0) | H100: =IF(5<=C56,-C63,0) | I100: =IF(6<=C56,-C63,0) | J100: =IF(7<=C56,-C63,0) | K100: =IF(8<=C56,-C63,0) | L100: =IF(9<=C56,-C63,0) | M100: =IF(10<=C56,-C63,0)
B101: Loan balance (year-end) | D101: =C61*(1+C62)^(12*1)-(C63/12)*((1+C62)^(12*1)-1)/C62 | E101: =C61*(1+C62)^(12*2)-(C63/12)*((1+C62)^(12*2)-1)/C62 | F101: =C61*(1+C62)^(12*3)-(C63/12)*((1+C62)^(12*3)-1)/C62 | G101: =C61*(1+C62)^(12*4)-(C63/12)*((1+C62)^(12*4)-1)/C62 | H101: =C61*(1+C62)^(12*5)-(C63/12)*((1+C62)^(12*5)-1)/C62 | I101: =C61*(1+C62)^(12*6)-(C63/12)*((1+C62)^(12*6)-1)/C62 | J101: =C61*(1+C62)^(12*7)-(C63/12)*((1+C62)^(12*7)-1)/C62 | K101: =C61*(1+C62)^(12*8)-(C63/12)*((1+C62)^(12*8)-1)/C62 | L101: =C61*(1+C62)^(12*9)-(C63/12)*((1+C62)^(12*9)-1)/C62 | M101: =C61*(1+C62)^(12*10)-(C63/12)*((1+C62)^(12*10)-1)/C62
B102: DSCR (NOI ÷ DS) | D102: =D90/C63 | E102: =E90/C63 | F102: =F90/C63 | G102: =G90/C63 | H102: =H90/C63 | I102: =I90/C63 | J102: =J90/C63 | K102: =K90/C63 | L102: =L90/C63 | M102: =M90/C63
B103: Debt yield (NOI ÷ loan) | D103: =D90/C61 | E103: =E90/C61 | F103: =F90/C61 | G103: =G90/C61 | H103: =H90/C61 | I103: =I90/C61 | J103: =J90/C61 | K103: =K90/C61 | L103: =L90/C61 | M103: =M90/C61
B104: LEVERED CASH FLOW (equity) | C104: =-C64 | D104: =IF(1<=C56,D95-C63,0)+IF(1=C56,D98-D101,0) | E104: =IF(2<=C56,E95-C63,0)+IF(2=C56,E98-E101,0) | F104: =IF(3<=C56,F95-C63,0)+IF(3=C56,F98-F101,0) | G104: =IF(4<=C56,G95-C63,0)+IF(4=C56,G98-G101,0) | H104: =IF(5<=C56,H95-C63,0)+IF(5=C56,H98-H101,0) | I104: =IF(6<=C56,I95-C63,0)+IF(6=C56,I98-I101,0) | J104: =IF(7<=C56,J95-C63,0)+IF(7=C56,J98-J101,0) | K104: =IF(8<=C56,K95-C63,0)+IF(8=C56,K98-K101,0) | L104: =IF(9<=C56,L95-C63,0)+IF(9=C56,L98-L101,0) | M104: =IF(10<=C56,M95-C63,0)+IF(10=C56,M98-M101,0)
B106: RETURNS — unlevered & levered
B107: Unlevered IRR | C107: =IFERROR(IRR(C99:M99),"n/m")
...

Sheet Office Condo
B1: GALLERIA CORPORATE CENTRE · OFFICE CONDOMINIUM
B2: 2455 E Sunrise Blvd | 13-story Class B office condo · ~168,807 SF · built 1973 (renov. 2007) · fractured ownership — every owner modeled individually + full buy-out
B4: PROPERTY FACTS — ⚠️ REPORTED (LoopNet / Daily Business Review / Sunbiz; BCPA blocked in build env)
B5: Building | D5: ~168,807 SF, 13-story Class B office condominium (+ ground-floor retail)
B6: Year built / reno | D6: 1973 (renovated 2007)
B7: Condo regime | D7: Created 2007; converted to condos 2011 by Bush Development Group
B8: Association | D8: Galleria Corporate Centre Condominium Association, Inc. (Sunbiz N07000001902)
B9: Lease economics | D9: Office units leased ≈ $26/SF Modified Gross
B10: Sale comp (historical) | D10: Unit sales ≈ $300/SF (pre-2020; office values since softened)
B11: Amenities | D11: Covered/valet parking, concierge, on-site café, two conference facilities
B12: Ownership | D12: Fractured condo: Main St Fund (Grove Gate) held 57.4% and is NOW RESELLING units individually; the balance is International Sunrise + a growing number of small owners (Jorgensen, Hublot, Merrimac, individual suites)
B13: Buy-out note | D13: Assembling the building = buying out EVERY unit owner (modeled individually below; the un-itemizable balance is grouped)
B14: ⚠️ BCPA limitation | D14: bcpa.net and the Broward Clerk are egress-blocked in this build; the complete per-unit folio roster (every unit, owner, price, date) needs a direct BCPA pull to finish
B16: ASSUMPTIONS — 🔵 blue = hardcoded inputs (Modified-Gross office)
B17: Rentable SF (both owners) | C17: 168807 | D17: ⚠️ ~168,807 SF
B18: In-place occupancy | C18: ='Assumptions'!C101 | D18: 🟢 Assumptions
B19: Stabilized occupancy | C19: ='Assumptions'!C102 | D19: 🟢 Assumptions
B20: Market rent ($/SF Modified Gross) | C20: ='Assumptions'!C100 | D20: 🟢 Assumptions
B21: Rent growth | C21: 0.03 | D21: 🔶
B22: Credit & vacancy loss | C22: 0.03 | D22: 🔶
B23: Effective millage | C23: 0.0191 | D23: ✅ area millage
B24: Office opex ex-taxes ($/SF, landlord) | C24: ='Assumptions'!C103 | D24: 🟢 Assumptions
B25: Management fee (% EGR) | C25: ='Assumptions'!C104 | D25: 🟢 Assumptions
B26: Expense growth | C26: 0.03 | D26: 🔶
B27: Replacement reserves ($/SF/yr) | C27: 0.2 | D27: 🔶
B28: Acquisition basis (income value) | C28: ='Assumptions'!C99 | D28: 🟢 Assumptions
B29: Closing & acq costs (% price) | C29: 0.02 | D29: 🔶
B30: Senior loan LTV | C30: ='Assumptions'!C107 | D30: 🟢 Assumptions
B31: Senior loan rate | C31: ='Assumptions'!C108 | D31: 🟢 Assumptions
B32: Amortization (yrs) | C32: 30 | D32: 🔶
B33: Going-in cap | C33: ='Assumptions'!C105 | D33: 🟢 Assumptions
B34: Exit cap | C34: ='Assumptions'!C106 | D34: 🟢 Assumptions
B35: Cost of sale | C35: 0.02 | D35: 🔶
B36: Hold period (yrs) | C36: 5 | D36: 🔶
B37: Discount rate (NPV) | C37: 0.1 | D37: 🔶
B38: Sale comp ($/SF) | C38: 300 | D38: ⚠️ historical ~$300/SF
B40: DERIVED VALUES & DEBT SIZING
B41: Senior loan amount | C41: =C28*C30 | D41: price × LTV
B42: Monthly rate | C42: =C31/12
B43: Annual debt service | C43: =C41*(C42/(1-(1+C42)^(-C32*12)))*12
B44: Equity at acquisition | C44: =C28*(1+C29)-C41
B45: Total cost basis | C45: =C28*(1+C29)
B46: Total equity required | C46: =C45-C41
B48: OPERATING CASH FLOW — 10-year annual (Modified Gross)
B49: Year | C49: 0 / Acq | D49: 1 | E49: 2 | F49: 3 | G49: 4 | H49: 5 | I49: 6 | J49: 7 | K49: 8 | L49: 9 | M49: 10
B50: Year ending | C50: At close | D50: Dec-2027 | E50: Dec-2028 | F50: Dec-2029 | G50: Dec-2030 | H50: Dec-2031 | I50: Dec-2032 | J50: Dec-2033 | K50: Dec-2034 | L50: Dec-2035 | M50: Dec-2036
B51: Occupancy | D51: =(C18+C19)/2 | E51: =C19 | F51: =C19 | G51: =C19 | H51: =C19 | I51: =C19 | J51: =C19 | K51: =C19 | L51: =C19 | M51: =C19
B52: Leased SF | D52: =C17*D51 | E52: =C17*E51 | F52: =C17*F51 | G52: =C17*G51 | H52: =C17*H51 | I52: =C17*I51 | J52: =C17*J51 | K52: =C17*K51 | L52: =C17*L51 | M52: =C17*M51
B53: Gross rental income (MG) | D53: =D52*C20*(1+C21)^(1-1) | E53: =E52*C20*(1+C21)^(2-1) | F53: =F52*C20*(1+C21)^(3-1) | G53: =G52*C20*(1+C21)^(4-1) | H53: =H52*C20*(1+C21)^(5-1) | I53: =I52*C20*(1+C21)^(6-1) | J53: =J52*C20*(1+C21)^(7-1) | K53: =K52*C20*(1+C21)^(8-1) | L53: =L52*C20*(1+C21)^(9-1) | M53: =M52*C20*(1+C21)^(10-1)
B54: Less: credit & vacancy loss | D54: =-D53*C22 | E54: =-E53*C22 | F54: =-F53*C22 | G54: =-G53*C22 | H54: =-H53*C22 | I54: =-I53*C22 | J54: =-J53*C22 | K54: =-K53*C22 | L54: =-L53*C22 | M54: =-M53*C22
B55: Effective Gross Revenue | D55: =D53+D54 | E55: =E53+E54 | F55: =F53+F54 | G55: =G53+G54 | H55: =H53+H54 | I55: =I53+I54 | J55: =J53+J54 | K55: =K53+K54 | ... M55: =M53+M54
B56: OPERATING EXPENSES (landlord — Modified Gross)
B57: Real-estate taxes | D57: =C28*C23*(1+C26)^(1-1) | E57: =C28*C23*(1+C26)^(2-1) | F57: =C28*C23*(1+C26)^(3-1) | G57: =C28*C23*(1+C26)^(4-1) | H57: =C28*C23*(1+C26)^(5-1) | I57: =C28*C23*(1+C26)^(6-1) | J57: =C28*C23*(1+C26)^(7-1) | K57: =C28*C23*(1+C26)^(8-1) | L57: =C28*C23*(1+C26)^(9-1) | M57: =C28*C23*(1+C26)^(10-1)
B58: Office opex (utilities, R&M, ins, CAM) | D58: =C17*C24*(1+C26)^(1-1) | E58: =C17*C24*(1+C26)^(2-1) | F58: =C17*C24*(1+C26)^(3-1) | G58: =C17*C24*(1+C26)^(4-1) | H58: =C17*C24*(1+C26)^(5-1) | I58: =C17*C24*(1+C26)^(6-1) | J58: =C17*C24*(1+C26)^(7-1) | K58: =C17*C24*(1+C26)^(8-1) | L58: =C17*C24*(1+C26)^(9-1) | M58: =C17*C24*(1+C26)^(10-1)
B59: Management fee | D59: =D55*C25 | E59: =E55*C25 | F59: =F55*C25 | G59: =G55*C25 | H59: =H55*C25 | I59: =I55*C25 | J59: =J55*C25 | K59: =K55*C25 | L59: =L55*C25 | M59: =M55*C25
B60: Total operating expenses | D60: =SUM(D57:D59) | E60: =SUM(E57:E59) | F60: =SUM(F57:F59) | G60: =SUM(G57:G59) | H60: =SUM(H57:H59) | I60: =SUM(I57:I59) | J60: =SUM(J57:J59) | K60: =SUM(K57:K59) | ... M60: =SUM(M57:M59)
B61: NET OPERATING INCOME | D61: =D55-D60 | E61: =E55-E60 | F61: =F55-F60 | G61: =G55-G60 | H61: =H55-H60 | I61: =I55-I60 | J61: =J55-J60 | K61: =K55-K60 | ... M61: =M55-M60
B62: Replacement reserves | D62: =C17*C27*(1+C26)^(1-1) | E62: =C17*C27*(1+C26)^(2-1) | F62: =C17*C27*(1+C26)^(3-1) | G62: =C17*C27*(1+C26)^(4-1) | H62: =C17*C27*(1+C26)^(5-1) | I62: =C17*C27*(1+C26)^(6-1) | J62: =C17*C27*(1+C26)^(7-1) | K62: =C17*C27*(1+C26)^(8-1) | L62: =C17*C27*(1+C26)^(9-1) | M62: =C17*C27*(1+C26)^(10-1)
B63: Unlevered cash flow (before reversion) | C63: =-C28*(1+C29) | D63: =D61-D62 | E63: =E61-E62 | F63: =F61-F62 | G63: =G61-G62 | H63: =H61-H62 | I63: =I61-I62 | J63: =J61-J62 | K63: =K61-K62 | ... M63: =M61-M62
B65: REVERSION, DEBT SERVICE & LEVERED CASH FLOW
B66: Net sale proceeds (exit year) | D66: =IF(1=C36,(D61*(1+C21)/C34)*(1-C35),0) | E66: =IF(2=C36,(E61*(1+C21)/C34)*(1-C35),0) | F66: =IF(3=C36,(F61*(1+C21)/C34)*(1-C35),0) | G66: =IF(4=C36,(G61*(1+C21)/C34)*(1-C35),0) | H66: =IF(5=C36,(H61*(1+C21)/C34)*(1-C35),0) | I66: =IF(6=C36,(I61*(1+C21)/C34)*(1-C35),0) | J66: =IF(7=C36,(J61*(1+C21)/C34)*(1-C35),0) | K66: =IF(8=C36,(K61*(1+C21)/C34)*(1-C35),0) | L66: =IF(9=C36,(L61*(1+C21)/C34)*(1-C35),0) | M66: =IF(10=C36,(M61*(1+C21)/C34)*(1-C35),0)
B67: UNLEVERED PROJECT CASH FLOW | C67: =C63 | D67: =IF(1<=C36,D63,0)+D66 | E67: =IF(2<=C36,E63,0)+E66 | F67: =IF(3<=C36,F63,0)+F66 | G67: =IF(4<=C36,G63,0)+G66 | H67: =IF(5<=C36,H63,0)+H66 | I67: =IF(6<=C36,I63,0)+I66 | J67: =IF(7<=C36,J63,0)+J66 | K67: =IF(8<=C36,K63,0)+K66 | L67: =IF(9<=C36,L63,0)+L66 | M67: =IF(10<=C36,M63,0)+M66
B68: Loan balance (year-end) | D68: =C41*(1+C42)^(12*1)-(C43/12)*((1+C42)^(12*1)-1)/C42 | E68: =C41*(1+C42)^(12*2)-(C43/12)*((1+C42)^(12*2)-1)/C42 | F68: =C41*(1+C42)^(12*3)-(C43/12)*((1+C42)^(12*3)-1)/C42 | G68: =C41*(1+C42)^(12*4)-(C43/12)*((1+C42)^(12*4)-1)/C42 | H68: =C41*(1+C42)^(12*5)-(C43/12)*((1+C42)^(12*5)-1)/C42 | I68: =C41*(1+C42)^(12*6)-(C43/12)*((1+C42)^(12*6)-1)/C42 | J68: =C41*(1+C42)^(12*7)-(C43/12)*((1+C42)^(12*7)-1)/C42 | K68: =C41*(1+C42)^(12*8)-(C43/12)*((1+C42)^(12*8)-1)/C42 | L68: =C41*(1+C42)^(12*9)-(C43/12)*((1+C42)^(12*9)-1)/C42 | M68: =C41*(1+C42)^(12*10)-(C43/12)*((1+C42)^(12*10)-1)/C42
B69: DSCR (NOI ÷ DS) | D69: =D61/C43 | E69: =E61/C43 | F69: =F61/C43 | G69: =G61/C43 | H69: =H61/C43 | I69: =I61/C43 | J69: =J61/C43 | K69: =K61/C43 | L69: =L61/C43 | M69: =M61/C43
B70: LEVERED CASH FLOW (equity) | C70: =-C44 | D70: =IF(1<=C36,D63-C43,0)+IF(1=C36,D66-D68,0) | E70: =IF(2<=C36,E63-C43,0)+IF(2=C36,E66-E68,0) | F70: =IF(3<=C36,F63-C43,0)+IF(3=C36,F66-F68,0) | G70: =IF(4<=C36,G63-C43,0)+IF(4=C36,G66-G68,0) | H70: =IF(5<=C36,H63-C43,0)+IF(5=C36,H66-H68,0) | I70: =IF(6<=C36,I63-C43,0)+IF(6=C36,I66-I68,0) | J70: =IF(7<=C36,J63-C43,0)+IF(7=C36,J66-J68,0) | K70: =IF(8<=C36,K63-C43,0)+IF(8=C36,K66-K68,0) | L70: =IF(9<=C36,L63-C43,0)+IF(9=C36,L66-L68,0) | M70: =IF(10<=C36,M63-C43,0)+IF(10=C36,M66-M68,0)
B72: RETURNS — unlevered & levered
B73: Unlevered IRR | C73: =IRR(C67:M67)
B74: Unlevered equity multiple | C74: =SUM(D67:M67)/-C67
B75: Unlevered NPV @ discount rate | C75: =C67+NPV(C37,D67:M67)
B76: Levered IRR | C76: =IRR(C70:M70)
B77: Levered equity multiple | C77: =SUM(D70:M70)/C44
B78: Year-1 NOI (pro-forma) | C78: =D61
B79: As-is in-place NOI (at occ0, no lease-up) | C79: =(C17*C18*C20)-(C17*C18*C20)*C22-(C28*C23+C17*C24)-((C17*C18*C20)-(C17*C18*C20)*C22)*C25
B80: Going-in cap (as-is NOI ÷ price) | C80: =C79/C28
B81: Stabilized NOI (Yr 2) | C81: =E61
B82: Stabilized value (÷ exit cap) | C82: =C81/C34
B83: In-place NOI per SF | C83: =D61/C17
B84: Income value (Yr-1 NOI ÷ going-in cap) | C84: =D61/C33
B85: Sale-comp value (SF × $/SF) | C85: =C17*C38
B87: OWNERS & FULL BUY-OUT — every identifiable owner modeled individually (⚠️ BCPA/Clerk egress-blocked; balance grouped)
B88: Condo buyout premium (fractured ownership / holdout) | C88: 0.12 | D88: 🔵 uplift over income value to get owners to sell
B89: Owner / unit | D89: SF | E89: % bldg | F89: Orig basis | G89: Bought | H89: Income value | I89: Buy-out value | J89: Note
B90: Main Street Fund LLC (Grove Gate) | D90: 96930 | E90: =D90/C17 | F90: 10000000 | G90: 09/2019 | H90: =C83*D90/C33 | I90: =H90*(1+C88) | J90: 57.4% + 2 parking lots · ✅ press · NOW RESELLING units individually
B91: International Sunrise Partners LLC | D91: 40000 | E91: =D91/C17 | F91: — | G91: 2011 | H91: =C83*D91/C33 | I91: =H91*(1+C88) | J91: Bush Development condo-conversion sponsor · retained balance · SF est.
B92: P. Jorgensen Management LLC — Ste 805 | D92: 1722 | E92: =D92/C17 | F92: 410000 | G92: 11/2019 | H92: =C83*D92/C33 | I92: =H92*(1+C88) | J92: Denmark-based US HQ · ✅ press (Berger Commercial)
B93: Hublot of America, Inc. — Ste 402 | D93: 2000 | E93: =D93/C17 | F93: — | G93: — | H93: =C83*D93/C33 | I93: =H93*(1+C88) | J93: Swiss watchmaker boutique · SF est. · ⚠️ reported
B94: Merrimac Ventures (Motwani) — unit(s) | D94: 3000 | E94: =D94/C17 | F94: — | G94: — | H94: =C83*D94/C33 | I94: =H94*(1+C88) | J94: reported owner · SF est. · ⚠️ reported
B95: Unit 401 owner — Ste 401 | D95: 682 | E95: =D95/C17 | F95: 260000 | G95: 06/2024 | H95: =C83*D95/C33 | I95: =H95*(1+C88) | J95: sold via MLS 6/2024 · ⚠️ reported
B96: Other unit owners (dozens of small units) | D96: 24473 | E96: =D96/C17 | F96: — | G96: — | H96: =C83*D96/C33 | I96: =H96*(1+C88) | J96: ⚠️ balance — needs a BCPA folio pull to itemize each
B97: TOTAL BUILDING — FULL BUY-OUT | D97: =SUM(D90:D96) | E97: =SUM(E90:E96) | F97: — | G97: — | H97: =SUM(H90:H96) | I97: =SUM(I90:I96) | J97: cost to control the whole building
B98: cross-check — income value (no premium) vs. $300/SF comp | H98: =H97 | I98: =C85
B100: PROFIT & LOSS STATEMENT — Year 1 vs. Stabilized (Yr 2)
B101: $ / year | F101: Year 1 | H101: Stabilized | J101: Per SF (stab.)
B102: Gross rental income (MG) | F102: =D53 | H102: =E53 | J102: =H102/C17
B103: Less: credit & vacancy loss | F103: =D54 | H103: =E54 | J103: =H103/C17
B104: Effective Gross Income | F104: =D55 | H104: =E55 | J104: =H104/C17
B105: Real-estate taxes | F105: =-D57 | H105: =-E57 | J105: =H105/C17
B106: Office opex (landlord) | F106: =-D58 | H106: =-E58 | J106: =H106/C17
B107: Management fee | F107: =-D59 | H107: =-E59 | J107: =H107/C17
B108: Net Operating Income | F108: =D61 | H108: =E61 | J108: =H108/C17
...

Sheet Land
B1: 1040 BAYVIEW · COVERED-LAND / REDEVELOPMENT SITE
B2: 1040 Bayview Dr | Folio 49-42-36-12-0040 | Sunrise & Bayview Partners LLC (Procacci) · 2.39 ac · existing 84,495 SF office (1967) · entitled 259 units
B4: PROPERTY FACTS — ⚠️ REPORTED (LoopNet / Florida YIMBY / BBX / Procacci; BCPA blocked in build env)
B5: Record owner | D5: Sunrise and Bayview Partners, LLC (Procacci Development affiliate; BBX exited 2022)
B6: Land | D6: 2.39 ac ≈ 104,108 SF — same plat block (49-42-36-12) as the assemblage
B7: Existing improvement | D7: 84,495 SF office building (built 1967) — a redevelopment site, not raw land
B8: Zoning | D8: B-1 (Boulevard Business) / CB core commercial; active rezoning UDP-Z25002
B9: Entitlement | D9: “The Residences at Bayview” — 259 units + 8,081 SF commercial, 8-story (81 ft)
B10: BCPA market value | D10: ≈ $6,685,580 (reported)
B11: Status | D11: NOT listed — owner is entitling, not selling; a future assemblage/JV target
B12: Covered-land thesis | D12: Interim office income covers carry; value is the entitled land + Live Local density optionality
B14: ASSUMPTIONS — 🔵 blue = hardcoded inputs
B15: Land (SF) | C15: 104108 | D15: ⚠️ 2.39 ac
B16: Existing office SF | C16: 84495 | D16: ⚠️ 1967 bldg
B17: Entitled units | C17: 259 | D17: ⚠️ approved 259
B18: BCPA market value | C18: 6685580 | D18: ⚠️ reported
B19: Interim office occupancy | C19: ='Assumptions'!C112 | D19: 🟢 Assumptions
B20: Interim office rent ($/SF MG) | C20: ='Assumptions'!C113 | D20: 🟢 Assumptions
B21: Interim office opex ($/SF) | C21: ='Assumptions'!C114 | D21: 🟢 Assumptions
B22: Management fee (% EGR) | C22: ='Assumptions'!C115 | D22: 🟢 Assumptions
B23: Effective millage | C23: 0.0191 | D23: ✅ area
B24: Acquisition basis (entitled land) | C24: ='Assumptions'!C111 | D24: 🟢 Assumptions
B25: Closing & acq costs (% price) | C25: 0.02 | D25: 🔶
B26: Land value growth | C26: 0.04 | D26: 🔶
B27: Hold period (yrs) | C27: 5 | D27: 🔶 to redevelopment
B28: Land loan LTV (IO) | C28: ='Assumptions'!C116 | D28: 🟢 Assumptions
B29: Land loan rate (IO) | C29: ='Assumptions'!C117 | D29: 🟢 Assumptions
B30: Cost of sale at exit | C30: 0.02 | D30: 🔶
B31: Discount rate (NPV) | C31: 0.1 | D31: 🔶
B32: Expense growth | C32: 0.03 | D32: 🔶
B34: LAND VALUATION — four approaches (Low / Base / High)
B35: Approach | D35: Low | E35: Base | F35: High | G35: Basis / note
B36: ① Per SF of land | D36: =C15*'Assumptions'!C33 | E36: =C15*'Assumptions'!C34 | F36: =C15*'Assumptions'!C35 | G36: land SF × $/SF (low/base/high on Assumptions tab)
B37: ② Per entitled unit | D37: =C17*'Assumptions'!C36 | E37: =C17*'Assumptions'!C37 | F37: =C17*'Assumptions'!C38 | G37: units × $/unit (low/base/high on Assumptions tab)
B38: ③ BCPA market value (floor) | D38: =C18 | E38: =C18 | F38: =C18 | G38: assessed just value — conservative floor
B39: ④ Interim income value | D39: =C48 | E39: =C48 | F39: =C48 | G39: existing office NOI ÷ 8% cap (income the land throws off)
B40: Concluded acquisition basis | E40: =C24 | G40: 🔶 entitled-land basis used in the hold model & assemblage
B42: INTERIM INCOME — existing office (the “cover” on the land)
B43: Interim gross rent | C43: =C16*C19*C20
B44: Interim office opex | C44: =-C16*C21
B45: Interim taxes (on basis) | C45: =-C24*C23
B46: Interim management fee | C46: =-C43*C22
B47: Interim NOI (covers carry) | C47: =C43+C44+C45+C46
B48: Interim income value @ 8% cap | C48: =C47/0.08
B50: Land loan (IO) | C50: =C24*C28 | D50: price × LTV
B51: Annual interest (IO) | C51: =C50*C29
B52: Equity at acquisition | C52: =C24*(1+C25)-C50
B53: Interim net carry (NOI − interest) | C53: =C47-C51 | D53: covered-land carry
B55: COVERED-LAND HOLD — interim income + land appreciation (10-yr; unlevered & levered)
B56: Year | C56: 0 / Acq | D56: 1 | E56: 2 | F56: 3 | G56: 4 | H56: 5 | I56: 6 | J56: 7 | K56: 8 | L56: 9 | M56: 10
B57: Land value (appreciating) | D57: =C24*(1+C26)^1 | E57: =C24*(1+C26)^2 | F57: =C24*(1+C26)^3 | G57: =C24*(1+C26)^4 | H57: =C24*(1+C26)^5 | I57: =C24*(1+C26)^6 | J57: =C24*(1+C26)^7 | K57: =C24*(1+C26)^8 | L57: =C24*(1+C26)^9 | M57: =C24*(1+C26)^10
B58: Interim NOI | D58: =C47*(1+C32)^(1-1) | E58: =C47*(1+C32)^(2-1) | F58: =C47*(1+C32)^(3-1) | G58: =C47*(1+C32)^(4-1) | H58: =C47*(1+C32)^(5-1) | I58: =C47*(1+C32)^(6-1) | J58: =C47*(1+C32)^(7-1) | K58: =C47*(1+C32)^(8-1) | L58: =C47*(1+C32)^(9-1) | M58: =C47*(1+C32)^(10-1)
B59: Net land sale (exit year) | D59: =IF(1=C27,D57*(1-C30),0) | E59: =IF(2=C27,E57*(1-C30),0) | F59: =IF(3=C27,F57*(1-C30),0) | G59: =IF(4=C27,G57*(1-C30),0) | H59: =IF(5=C27,H57*(1-C30),0) | I59: =IF(6=C27,I57*(1-C30),0) | J59: =IF(7=C27,J57*(1-C30),0) | K59: =IF(8=C27,K57*(1-C30),0) | L59: =IF(9=C27,L57*(1-C30),0) | M59: =IF(10=C27,M57*(1-C30),0)
B60: UNLEVERED PROJECT CASH FLOW | C60: =-C24*(1+C25) | D60: =IF(1<=C27,D58,0)+D59 | E60: =IF(2<=C27,E58,0)+E59 | F60: =IF(3<=C27,F58,0)+F59 | G60: =IF(4<=C27,G58,0)+G59 | H60: =IF(5<=C27,H58,0)+H59 | I60: =IF(6<=C27,I58,0)+I59 | J60: =IF(7<=C27,J58,0)+J59 | K60: =IF(8<=C27,K58,0)+K59 | L60: =IF(9<=C27,L58,0)+L59 | M60: =IF(10<=C27,M58,0)+M59
B61: Loan balance (IO — constant) | D61: =IF(1<=C27,C50,0) | E61: =IF(2<=C27,C50,0) | F61: =IF(3<=C27,C50,0) | G61: =IF(4<=C27,C50,0) | H61: =IF(5<=C27,C50,0) | I61: =IF(6<=C27,C50,0) | J61: =IF(7<=C27,C50,0) | K61: =IF(8<=C27,C50,0) | L61: =IF(9<=C27,C50,0) | M61: =IF(10<=C27,C50,0)
B62: LEVERED CASH FLOW (equity) | C62: =-C52 | D62: =IF(1<=C27,D58-C51,0)+IF(1=C27,D59-C50,0) | E62: =IF(2<=C27,E58-C51,0)+IF(2=C27,E59-C50,0) | F62: =IF(3<=C27,F58-C51,0)+IF(3=C27,F59-C50,0) | G62: =IF(4<=C27,G58-C51,0)+IF(4=C27,G59-C50,0) | H62: =IF(5<=C27,H58-C51,0)+IF(5=C27,H59-C50,0) | I62: =IF(6<=C27,I58-C51,0)+IF(6=C27,I59-C50,0) | J62: =IF(7<=C27,J58-C51,0)+IF(7=C27,J59-C50,0) | K62: =IF(8<=C27,K58-C51,0)+IF(8=C27,K59-C50,0) | L62: =IF(9<=C27,L58-C51,0)+IF(9=C27,L59-C50,0) | M62: =IF(10<=C27,M58-C51,0)+IF(10=C27,M59-C50,0)
B64: COVERED-LAND RETURNS — unlevered & levered
B65: Unlevered IRR | C65: =IRR(C60:M60)
B66: Unlevered equity multiple | C66: =SUM(D60:M60)/-C60
B67: Unlevered NPV @ discount rate | C67: =C60+NPV(C31,D60:M60)
B68: Levered IRR | C68: =IRR(C62:M62)
B69: Levered equity multiple | C69: =SUM(D62:M62)/C52
B70: Interim yield on basis (NOI ÷ price) | C70: =C47/C24
B72: REDEVELOPMENT RESIDUAL — ⚠️ AE flood zone; residual runs NEGATIVE — DO NOT force positive
B73: Gross development value | C73: =C17*'Assumptions'!C39 | D73: units × achievable value/unit (Assumptions tab)
B74: Buildable GBA (SF) | C74: =C17*'Assumptions'!C41 | D74: units × GBA/unit (Assumptions tab)
B75: Hard cost | C75: =-C74*'Assumptions'!C40 | D75: $/GBA SF (AE-zone coastal, Assumptions tab)
B76: Soft cost | C76: =-C74*'Assumptions'!C40*'Assumptions'!C42 | D76: % of hard (Assumptions tab)
B77: Developer profit | C77: =-C73*'Assumptions'!C43 | D77: % of GDV (Assumptions tab)
B78: RESIDUAL LAND VALUE | C78: =C73+C75+C76+C77
B79: Conclusion | C79: HOLD | D79: Residual < entitled-land basis → redevelopment does not pencil today; hold as covered land for Live Local optionality

Sheet Notes & Sources
B1: NOTES, SOURCES & METHODOLOGY
B2: DAWN RE Enterprises Corp. · E Sunrise Blvd Assemblage · Fort Lauderdale, FL · prepared 2026-07-21 · CONFIDENTIAL
B4: PURPOSE & HOW TO USE THIS MODEL
B5: Institutional acquisition underwriting for a five-asset covered-land-play assemblage on the E Sunrise Blvd hard corner at the Galleria.
B6: Two valuations of the same block are presented: (1) an INCOME basis — what the combined cash flows support — and (2) a HIGHEST-AND-
B7: BEST-USE / covered-land basis — land value plus an assemblage premium to control every parcel. Only blue cells are inputs; change any
B8: blue cell and the entire workbook recalculates (full recalc on open). The ASSUMPTIONS tab is the single control surface — global drivers
B9: plus a block per asset (price · rents · occupancy · operating expenses · caps · debt). Standard modeling params (rent/expense growth,
B10: TI/LC, reserves, closing detail) stay blue on each asset tab. Order: Exec · Assumptions · Income · Scenarios · Assemblage · Highest & Best Use · assets · Notes.
B11: Each component is priced independently (asset tabs) and combined (Assemblage / Income / HBU). The HBU tab prices the land as regular fragmented parcels vs. an assembled superblock (plottage premium), and carries the office condo full buy-out.
B13: VALUATION METHODOLOGY
B14: As-is vs. stabilized | D14: Direct cap on AS-IS in-place NOI (current occupancy) gives the going-in value; stabilized NOI ÷ exit cap gives post-lease-up value. The spread is value creation.
B15: Income-based price | D15: Concluded on as-is direct cap; stabilized direct cap and a DCF (PV of unlevered cash flows at the target unlevered yield) are shown as cross-checks.
B16: Portfolio returns | D16: Computed by CONSOLIDATING each asset's actual cash flows into one stream and running a single IRR — never by averaging asset IRRs (mathematically invalid).
B17: Sources & Uses | D17: Uses = price + doc-stamp/transfer tax + title + legal/DD + loan origination; Sources = sized senior debt + equity (plug). Equity is the S&U plug, not a shortcut.
B18: Return attribution | D18: Unlevered profit is decomposed into operating cash flow, NOI growth / lease-up, cap-rate movement, cost of sale, and closing — and ties exactly to the consolidated cash flow.
B19: Scenario analysis | D19: Downside / Base / Upside bundle NOI achievement, exit cap, and financing rate; each is a full consolidated cash flow with its own IRR / multiple / DSCR / cash-on-cash.
B20: Break-even | D20: The break-even exit cap is the softest exit that still returns 1.0x of equity; the cushion vs. the underwritten exit cap is a downside guardrail.
B21: Covered-land (HBU) price | D21: Summed control cost (each parcel at the greater of income or land value; Publix via sale-leaseback at its fee price) plus a 15/20/25% assemblage premium.
B22: Publix sale-leaseback | D22: Acquire the Publix fee; Publix leases back and pays NNN rent for the entitlement term (rent covers carry), then vacates. The leaseback income CLIFFS at term-end and the parcel EXITS AT LAND VALUE (covered-land), not an income cap. A solver on the Publix tab back-solves the leaseback rent for a target DSCR or cap. Rent, SF, price, term, and leverage are on the Assumptions tab.
B23: Reversion | D23: Each asset sells in the hold year at its forward NOI ÷ exit cap, net of cost of sale; the consolidated reversion sums the asset-level reversions.
B24: Redevelopment | D24: The Live Local residual runs negative in the AE flood zone at current coastal hard costs; the model does NOT force it positive — the conclusion is HOLD.
B26: SENIOR DEBT — SIZING CONVENTION
B27: Debt is sized to the LESSER OF three lender constraints, sized on as-is in-place NOI:
B28: Constraint 1 — LTV | D28: Loan ≤ max LTV × purchase price (default 60%).
B29: Constraint 2 — DSCR | D29: Loan ≤ NOI ÷ (min DSCR × mortgage constant); default min DSCR 1.30x.
B30: Constraint 3 — Debt yield | D30: Loan ≤ NOI ÷ min debt yield (default 8.5%).
B31: The sized loan is the minimum of the three; the binding constraint is flagged on the Income Valuation tab.
B33: DATA SOURCES & CONFIDENCE FLAGS
B34: Flag | C34: Meaning
B35: ✅ VERIFIED | C35: public record — BCPA property appraiser / FL Sunbiz / recorded deed
B36: ⚠️ REPORTED | C36: counterparty, broker listing (LoopNet/Crexi), or press — unconfirmed at the county
B37: 🔶 MODELED | C37: assumption from mid-2026 market research; moves with the blue inputs
B39: Asset | D39: Verified | E39: Sources
B40: Shahidi Retail (Galleria Plaza) | D40: ✅ BCPA/Sunbiz | E40: Folio 49-42-36-12-0070; tenants via LoopNet/Southeast Centers, Yelp, official locators; rents from corridor comps
B41: Publix + Starbucks | D41: ✅ BCPA/deed | E41: Folio -0060; $25M Trustee's Deed 03/2025 (The Real Deal); rents/caps from net-lease research (Boulder Group, Matthews)
B42: Sunrise Plaza (Kar Luen) | D42: ⚠️ reported | E42: Folio -0011; LoopNet/Sunbiz/Cortera; tenants via Yelp; value & sale unconfirmed — VERIFY AT BCPA
B43: Galleria Corporate Centre | D43: ⚠️ reported | E43: 2455 E Sunrise; owners via Daily Business Review 10/2019 (Main Street Fund 57.4%); per-unit folios not enumerated
B44: 1040 Bayview (land) | D44: ⚠️ reported | E44: Folio -0040; Florida YIMBY/Traded/BBX/Procacci; entitlement 259 units; BCPA market value reported not confirmed
B45: BCPA (bcpa.net) was blocked from the build environment; ⚠️ items were sourced from web mirrors of the tax roll and must be confirmed at the county before close.
B47: KEY MARKET ASSUMPTIONS (mid-2026, MODELED)
B48: Retail rents | D48: in-line $32–55/SF NNN (Sunrise corridor $45–60); restaurant/end-cap $40–50/SF
B49: Publix / Starbucks | D49: grocery ~$13/SF NNN, cap 6.0–6.75%; Starbucks pad ~$60/SF, cap 4.75–5.5%
B50: Office | D50: small Class B/C ~$20–30/SF gross (~$15–24 NNN); cap 7.5–9.0%
B51: Retail caps | D51: stabilized strip 6.25–6.75%; value-add 7.25–8.0%; exit = going-in +25 bps
B52: Land | D52: Fort Lauderdale infill ~$248/SF (subject comps $228–255); Galleria bulk ~$53/SF
B53: Senior debt | D53: stabilized 5.75–7.0%, 60–75% LTV, DSCR 1.25–1.40x, debt yield 7–10%
B54: Covered-land cap | D54: in-place income cap ~3–5% — income covers carry, not a yield play
B56: COLOR & FONT LEGEND
B57: Blue on yellow | D57: hardcoded input — the only cells to change
B58: Black on white | D58: formula / calculation
B59: Green | D59: public-record verified fact or cross-sheet link
B60: Gold on navy / dark | D60: section header, total, KPI box, banner
B61: Orange / dark red | D61: warning, flag, or excluded-from note
B63: LIMITATIONS & DISCLAIMERS
B64: • Space-level rent rolls are estimated; no tenant-by-tenant lease abstracts (expirations, options, recovery type) were available. Replace with real leases in diligence.
B65: • Publix and the office-condo units are not listed for sale; they are modeled as acquisition cases. Publix is a fee owner, so its 'rent' is a mark-to-market, not contract income.
B66: • Property-tax reassessment is modeled to each asset's own price (FL rule); an assemblage purchase would reallocate basis and taxes across parcels.
B67: • Returns exclude any LP/GP promote/waterfall, transfer taxes, and portfolio-level G&A. This is a screening model, not a closing model.
B68: • All figures are estimates for internal evaluation only and are not an appraisal, an offer, or investment advice. Confirm all ⚠️ REPORTED data at the county before relying on it.
