Workbook

Sheet Executive Summary
A1: 451 WHITE HORSE PIKE, ATCO NJ — ACQUISITION RECOMMENDATION
A2: Everything an approver needs is on this sheet. Detail follows on the tabs behind it.
A4: RECOMMENDATION: Offer $1,100,000 all cash, 30-day diligence, 15-day close. At this price we buy the building at what it is worth with an ordinary tenant paying ordinary rent — so the 36% cannabis rent premium, the renewal option, the 3-lane drive-thru and 2.5 acres of idle land all come free. Expected unlevered return 12%. Every modelled outcome, including total tenant failure, returns a profit.
A8: THE NUMBERS THAT MATTER
A9: Metric | B9: At our offer | C9: At the asking price | F9: What it means
A10: Purchase price | B10: =Assumptions!$B$15 -> 1100000 | C10: =Assumptions!$B$14 -> 1600000 | F10: Below the ask and below our own value indication
A11: Weighted value indication | B11: =Valuation!$C$9 -> 1252494.9 | C11: =Valuation!$C$9 -> 1252494.9 | F11: Where the four independent valuation methods converge
A12: Discount to value indication | B12: =Assumptions!$B$15/Valuation!$C$9-1 -> -0.12175289 | C12: =Assumptions!$B$14/Valuation!$C$9-1 -> 0.27745034 | F12: Our margin of safety on entry, versus the seller's premium
A13: Price per square foot | B13: =Assumptions!$B$15/Assumptions!$B$7 -> 250 | C13: =Assumptions!$B$14/Assumptions!$B$7 -> 363.63636 | F13: Well below the cost of building it new
A14: Going-in cap rate | B14: =Assumptions!$B$22/Assumptions!$B$15 -> 0.12 | C14: =Assumptions!$B$22/Assumptions!$B$14 -> 0.0825 | F14: Cannabis dispensaries trade at 7.4%-9.35%; we enter at 12%
A15: Expected unlevered IRR | B15: =IRR(Returns!B9:I9) -> 0.11995498 | C15: =IRR(Returns!$L$12:$S$12) -> 0.043288476 | F15: Probability-weighted across all six reversion outcomes
A16: Best case IRR (tenant renews) | B16: =Returns!D22 -> 0.1579787 | C16: =Returns!E22 -> 0.080673127 | F16: The single most likely outcome at 40% probability
A17: Worst case IRR (total vacancy) | B17: =Returns!D27 -> 0.061974317 | C17: =Returns!E27 -> -0.014333776 | F17: Tenant fails, building goes dark, we liquidate land and shell
A18: Debt service coverage (55% LTV) | B18: =Financing!F12 -> 2.0008587 | C18: =Financing!F14 -> 1.3755904 | F18: Most lenders decline below 1.25x. Our price is what makes this financeable
A19: Cash-on-cash (55% LTV) | B19: =Financing!H12 -> 0.13339056 | C19: =Financing!H14 -> 0.050057224 | F19: Annual cash return on equity after debt service
A20: Levered IRR (55% LTV) | B20: =Financing!F18 -> 0.14848452 | C20: =Financing!F20 -> -0.033201226 | F20: At the ask, leverage turns the return negative - debt costs more than the property yields
A22: WHY IT WORKS — four reasons
A23: Reason | B23: Figure | F23: Detail
A24: Offer less market-rent value of the building | B24: =Assumptions!$B$15-Assumptions!$B$31*Assumptions!$B$7/0.0875 -> -6285.7143 | F24: Effectively zero. We buy at plain conventional-use value, so the cannabis premium, the option and the land are free.
A25: Capital returned before expiry | B25: =Assumptions!$B$22*6.5/Assumptions!$B$15 -> 0.78 | F25: $858,000 of contracted rent lands before the lease matures, with no reliance on renewal, refinancing or resale.
A26: Basis covered by dirt and shell | B26: =750000/Assumptions!$B$15 -> 0.68181818 | F26: Land plus vacant building supports ~$750,000. Only ~$350,000 of our basis is genuinely at risk.
A27: The worst case still pays | B27: =Returns!D27 -> 0.061974317 | F27: At the asking price that same scenario loses money. That gap is the entire argument for our number.
A29: THE ASSET
A30: Property | B30: 451 White Horse Pike (US Route 30), Atco NJ | F30: Waterford Township, Camden County
A31: Building | B31: 4,400 SF former bank branch on 3.13 acres | F31: Built 1960, renovated 2023. Vault, 3-lane drive-thru, ample parking
A32: Tenant | B32: Holistic Solutions - cannabis dispensary | F32: Single location, founded 2018, two personal guarantees, no corporate credit
A33: Lease | B33: Absolute NNN to 31 Jan 2033 (6.5 years) | F33: $132,000/yr flat, no escalations. One 5-year option at $154,000
A34: Location | B34: 15,370 vehicles per day | F34: Corridor between Philadelphia and the Jersey Shore
A36: IF THE TENANT LEAVES — the question that decides the deal
A37: Re-let scenario | B37: Annual rent | C37: Yield on our offer | F37: Comment
A38: Another cannabis licensee @ $30/SF | B38: =Assumptions!$B$22 -> 132000 | C38: =Assumptions!$B$22/Assumptions!$B$15 -> 0.12 | F38: Holds the rent outright, but Waterford permits only two licences
A39: Bank / credit union or medical @ $24/SF | B39: =24*Assumptions!$B$7 -> 105600 | C39: =24*Assumptions!$B$7/Assumptions!$B$15 -> 0.096 | F39: Turnkey - the vault and drive-thru are already in place
A40: Conventional market rent @ $22/SF | B40: =Assumptions!$B$31*Assumptions!$B$7 -> 96800 | C40: =Assumptions!$B$31*Assumptions!$B$7/Assumptions!$B$15 -> 0.088 | F40: Our underwriting case. This is what we priced the deal on
A41: Deep downside @ $18/SF | B41: =18*Assumptions!$B$7 -> 79200 | C41: =18*Assumptions!$B$7/Assumptions!$B$15 -> 0.072 | F41: Bottom of the conventional range - still clears our cost of capital
A43: UPSIDE WE ARE NOT PAYING FOR
A44: Idle developable land | B44: ='Land Upside'!B9 -> 2.4789899 | F44: Building coverage is only 3.2% of the site
A45: Added NOI from a pad plus EV charging | B45: ='Land Upside'!C15 -> 100000 | F45: Outparcel ground lease plus a third-party EV fast-charging licence
A46: Value created, net of build-out | B46: ='Land Upside'!C16 -> 931081.08 | F46: A second deal hiding inside the first - excluded from every return above
A47: Yield on cost if executed | B47: =(Assumptions!$B$22+'Land Upside'!C15)/Assumptions!$B$15 -> 0.21090909 | F47: Versus 12.0% today
A49: NEGOTIATION DISCIPLINE
A50: Open at | B50: =Assumptions!$B$15 -> 1100000 | F50: All cash, 30-day diligence, 15-day close
A51: Practical ceiling | B51: =Assumptions!$B$16 -> 1250000 | F51: Still delivers a 9.3% expected return. Hold here
A52: Walk away above | B52: 1300000 | F52: Above this the margin of safety is gone - there will be another one
A53: Asking price | B53: =Assumptions!$B$14 -> 1600000 | F53: Expected return of only 4.3%. Decline
A56: Basis: deal terms from the Matthews offering memorandum; assessment and zoning from public tax-assessor records. Comparables are predominantly ASKING RATES AND MARKETED CAP RATES, not verified closed transactions — re-run against CoStar, Crexi and Camden County deed records before hard money. Operating costs, TI, downtime and land figures are analyst estimates; reversion probabilities are judgmental. Returns are unlevered and pre-tax. Not an appraisal.

Sheet Assumptions
A1: ASSUMPTIONS — every input to the model lives here
A2: Blue = input you can change. Every other sheet recalculates from these cells.
A4: PROPERTY
A5: Item | B5: Value | C5: Unit | D5: Source / note
A6: Address | B6: 451 White Horse Pike, Atco NJ 08004 | D6: Waterford Twp, Camden County
A7: Gross leasable area | B7: 4400 | C7: SF | D7: Per Offering Memorandum. Assessor records show 4,206 SF — confirm by measurement
A8: Land area | B8: 3.13 | C8: acres | D8: Per Offering Memorandum
A9: Year built / renovated | B9: 1960 / 2023 | D9: Former bank branch, converted to dispensary
A10: Traffic count | B10: 15370 | C10: VPD | D10: US Route 30, per Offering Memorandum
A12: PRICING
A13: Item | B13: Value | C13: Unit | D13: Source / note
A14: Asking price | B14: 1600000 | C14: $ | D14: Matthews offering memorandum
A15: OUR OFFER | B15: 1100000 | C15: $ | D15: Recommended offer price — the key lever in this model
A16: Practical ceiling | B16: 1250000 | C16: $ | D16: Walk-away discipline: above this the margin of safety is gone
A18: LEASE IN PLACE
A19: Item | B19: Value | C19: Unit | D19: Source / note
A20: Tenant | B20: Holistic Solutions | D20: NJ medical + adult-use dispensary, single location, founded 2018
A21: Guarantee | B21: 2 personal guarantees | D21: No corporate credit, no rated entity
A22: Annual rent (in place) | B22: 132000 | C22: $/yr | D22: Flat for the full 10-year base term — no escalations
A23: Rent commencement | B23: 01-Feb-2023 | D23: Per Offering Memorandum
A24: Lease expiry | B24: 31-Jan-2033 | D24: Per Offering Memorandum
A25: Term remaining | B25: 6.5 | C25: years | D25: As of August 2026
A26: Option rent (1 x 5 yr) | B26: 154000 | C26: $/yr | D26: Tenant-elective. Modelled as optionality, never as income
A28: MARKET RENT (conventional, non-cannabis tenant)
A29: Item | B29: Value | C29: Unit | D29: Source / note
A30: Market rent — low | B30: 20 | C30: $/SF NNN | D30: Conventional retail / service on the Route 30 corridor
A31: Market rent — base | B31: 22 | C31: $/SF NNN | D31: Midpoint. Derived from South Jersey corridor comps — see Lease Comps tab
A32: Market rent — high | B32: 24 | C32: $/SF NNN | D32: Bank, credit union or medical backfill
A34: OPERATING COSTS (tenant pays under absolute NNN; landlord carries only if vacant)
A35: Item | B35: Value | C35: Unit | D35: Source / note
A36: Property taxes | B36: 39402 | C36: $/yr | D36: ESTIMATE: $760,200 assessed x implied ~$5.18/$100 rate. Confirm actual bill in diligence
A37: Insurance | B37: 12000 | C37: $/yr | D37: ESTIMATE — cannabis-use premium loading
A38: Maintenance / CAM | B38: 10000 | C38: $/yr | D38: ESTIMATE — roof, HVAC, lot
A39: Assessed value | B39: 760200 | C39: $ | D39: Camden County tax assessor
A40: Equalization ratio | B40: 0.5981 | C40: % | D40: Camden County Board of Taxation, 2025
A42: LAND UPSIDE (excluded from all base-case returns)
A43: Item | B43: Value | C43: Unit | D43: Source / note
A44: Outparcel ground rent — base | B44: 80000 | C44: $/yr | D44: Benchmarked to the listing agent's own build-to-suit comps: 7 Brew $155,000/yr and Wendy's $157,659/yr. A ground lease (tenant builds) typically runs 40-55% of a BTS rent
A45: EV charging licence — base | B45: 20000 | C45: $/yr | D45: 6-8 DC fast stalls, corridor benchmarks discounted, 10-25% owner revenue share
A46: Land build-out cost | B46: 150000 | C46: $ | D46: ESTIMATE — subdivision, entitlement, site work
A47: Land income cap rate | B47: 0.0925 | C47: % | D47: Capitalization rate applied to incremental land NOI
A49: HOW TO USE THIS WORKBOOK
A50: Blue figures are inputs — change them and the whole workbook recalculates.
A51: Black figures are formulas. Green figures are pulled from another sheet.
A52: The yellow cell is the master lever: our offer price.
A53: Start at Executive Summary. Reversion Scenarios holds the judgmental probabilities.

Sheet Reversion Scenarios
A1: REVERSION SCENARIOS — what the property is worth at lease expiry, Jan 2033
A2: The single uncertainty in the deal. Everything before 2033 is a fixed $132,000 coupon.
A4: Scenario | B4: Probability | C4: Stabilized NOI | D4: Exit cap | E4: Stabilized value | F4: Re-let cost | G4: Net value | H4: Basis of the estimate
A5: Tenant renews at the option rent | B5: 0.4 | C5: =Assumptions!$B$26 -> 154000 | D5: 0.0925 | E5: =IF(D5=0,0,C5/D5) -> 1664864.9 | F5: 25000 | G5: =E5-F5 -> 1639864.9 | H5: Most likely single outcome: sunk build-out, a site-specific licence, and a township that caps retail cannabis at two licences
A6: New NJ cannabis licensee @ $30/SF | B6: 0.1 | C6: 132000 | D6: 0.095 | E6: =IF(D6=0,0,C6/D6) -> 1389473.7 | F6: 325000 | G6: =E6-F6 -> 1064473.7 | H6: Holds full rent but the demand pool is one seat; requires CRC approval at this premises
A7: Bank / credit union / retail @ $22/SF | B7: 0.2 | C7: 96800 | D7: 0.0875 | E7: =IF(D7=0,0,C7/D7) -> 1106285.7 | F7: 275000 | G7: =E7-F7 -> 831285.71 | H7: Turnkey backfill — vault and 3-lane drive-thru already in place, lowest TI of any conventional use
A8: Medical / urgent care / vet @ $24/SF | B8: 0.2 | C8: 105600 | D8: 0.0825 | E8: =IF(D8=0,0,C8/D8) -> 1280000 | F8: 500000 | G8: =E8-F8 -> 780000 | H8: Deepest demand pool but heaviest fit-out at $60-100/SF
A9: QSR pad rebuild @ $42/SF on 2,200 SF | B9: 0.05 | C9: 92400 | D9: 0.07 | E9: =IF(D9=0,0,C9/D9) -> 1320000 | F9: 330000 | G9: =E9-F9 -> 990000 | H9: Reduced footprint or pad rebuild; best rent per foot, heaviest capex
A10: Extended vacancy - land + shell only | B10: 0.05 | C10: 0 | D10: 0 | E10: 750000 | F10: 123000 | G10: =E10-F10 -> 627000 | H10: Liquidation case: sell land and vacant building, less 24 months of carry
A11: PROBABILITY-WEIGHTED REVERSION | B11: =SUM(B5:B10) -> 1 | G11: =SUMPRODUCT($B$5:$B$10,$G$5:$G$10) -> 1165500.5 | H11: Sum of each outcome weighted by its probability
A13: Probabilities are judgmental and are the main soft input in this model. They are shown in blue so you can change them — the weighted value and every IRR in the workbook follow. Check that the probability column sums to 100%.

Sheet Returns
A1: RETURNS — unlevered cash flow, IRR and the negotiation ladder
A2: 6.5-year hold from Aug 2026 to lease expiry Jan 2033, sold at the probability-weighted reversion.
A4: UNLEVERED CASH FLOW AT OUR OFFER PRICE | L4: HELPER — cash flow rows behind the IRR columns (safe to ignore)
A5: Year | B5: 0 (close) | C5: 1 | D5: 2 | E5: 3 | F5: 4 | G5: 5 | H5: 6 | I5: 7 (exit) | J5: Total | L5: Scenario IRR cash flows
A6: Purchase price | B6: =-Assumptions!$B$15 -> -1100000 | C6: 0 | D6: 0 | E6: 0 | F6: 0 | G6: 0 | H6: 0 | I6: 0 | J6: =SUM(B6:I6) -> -1100000 | L6: =-Assumptions!$B$15 -> -1100000 | M6: =Assumptions!$B$22 -> 132000 | N6: =Assumptions!$B$22 -> 132000 | O6: =Assumptions!$B$22 -> 132000 | P6: =Assumptions!$B$22 -> 132000 | Q6: =Assumptions!$B$22 -> 132000 | R6: =Assumptions!$B$22 -> 132000 | S6: =Assumptions!$B$22*0.5+'Reversion Scenarios'!G5 -> 1705864.9 | U6: =-Assumptions!$B$14 -> -1600000 | V6: =Assumptions!$B$22 -> 132000 | W6: =Assumptions!$B$22 -> 132000 | X6: =Assumptions!$B$22 -> 132000 | Y6: =Assumptions!$B$22 -> 132000 | Z6: =Assumptions!$B$22 -> 132000 | AA6: =Assumptions!$B$22 -> 132000 | AB6: =Assumptions!$B$22*0.5+'Reversion Scenarios'!G5 -> 1705864.9
A7: Net rent received | B7: 0 | C7: =Assumptions!$B$22 -> 132000 | D7: =Assumptions!$B$22 -> 132000 | E7: =Assumptions!$B$22 -> 132000 | F7: =Assumptions!$B$22 -> 132000 | G7: =Assumptions!$B$22 -> 132000 | H7: =Assumptions!$B$22 -> 132000 | I7: =Assumptions!$B$22*0.5 -> 66000 | J7: =SUM(B7:I7) -> 858000 | L7: =-Assumptions!$B$15 -> -1100000 | M7: =Assumptions!$B$22 -> 132000 | N7: =Assumptions!$B$22 -> 132000 | O7: =Assumptions!$B$22 -> 132000 | P7: =Assumptions!$B$22 -> 132000 | Q7: =Assumptions!$B$22 -> 132000 | R7: =Assumptions!$B$22 -> 132000 | S7: =Assumptions!$B$22*0.5+'Reversion Scenarios'!G6 -> 1130473.7 | U7: =-Assumptions!$B$14 -> -1600000 | V7: =Assumptions!$B$22 -> 132000 | W7: =Assumptions!$B$22 -> 132000 | X7: =Assumptions!$B$22 -> 132000 | Y7: =Assumptions!$B$22 -> 132000 | Z7: =Assumptions!$B$22 -> 132000 | AA7: =Assumptions!$B$22 -> 132000 | AB7: =Assumptions!$B$22*0.5+'Reversion Scenarios'!G6 -> 1130473.7
A8: Sale proceeds at expiry | B8: 0 | C8: 0 | D8: 0 | E8: 0 | F8: 0 | G8: 0 | H8: 0 | I8: ='Reversion Scenarios'!$G$11 -> 1165500.5 | J8: =SUM(B8:I8) -> 1165500.5 | L8: =-Assumptions!$B$15 -> -1100000 | M8: =Assumptions!$B$22 -> 132000 | N8: =Assumptions!$B$22 -> 132000 | O8: =Assumptions!$B$22 -> 132000 | P8: =Assumptions!$B$22 -> 132000 | Q8: =Assumptions!$B$22 -> 132000 | R8: =Assumptions!$B$22 -> 132000 | S8: =Assumptions!$B$22*0.5+'Reversion Scenarios'!G7 -> 897285.71 | U8: =-Assumptions!$B$14 -> -1600000 | V8: =Assumptions!$B$22 -> 132000 | W8: =Assumptions!$B$22 -> 132000 | X8: =Assumptions!$B$22 -> 132000 | Y8: =Assumptions!$B$22 -> 132000 | Z8: =Assumptions!$B$22 -> 132000 | AA8: =Assumptions!$B$22 -> 132000 | AB8: =Assumptions!$B$22*0.5+'Reversion Scenarios'!G7 -> 897285.71
A9: NET CASH FLOW | B9: =SUM(B6:B8) -> -1100000 | C9: =SUM(C6:C8) -> 132000 | D9: =SUM(D6:D8) -> 132000 | E9: =SUM(E6:E8) -> 132000 | F9: =SUM(F6:F8) -> 132000 | G9: =SUM(G6:G8) -> 132000 | H9: =SUM(H6:H8) -> 132000 | I9: =SUM(I6:I8) -> 1231500.5 | J9: =SUM(J6:J8) -> 923500.46 | L9: =-Assumptions!$B$15 -> -1100000 | M9: =Assumptions!$B$22 -> 132000 | N9: =Assumptions!$B$22 -> 132000 | O9: =Assumptions!$B$22 -> 132000 | P9: =Assumptions!$B$22 -> 132000 | Q9: =Assumptions!$B$22 -> 132000 | R9: =Assumptions!$B$22 -> 132000 | S9: =Assumptions!$B$22*0.5+'Reversion Scenarios'!G8 -> 846000 | U9: =-Assumptions!$B$14 -> -1600000 | V9: =Assumptions!$B$22 -> 132000 | W9: =Assumptions!$B$22 -> 132000 | X9: =Assumptions!$B$22 -> 132000 | Y9: =Assumptions!$B$22 -> 132000 | Z9: =Assumptions!$B$22 -> 132000 | AA9: =Assumptions!$B$22 -> 132000 | AB9: =Assumptions!$B$22*0.5+'Reversion Scenarios'!G8 -> 846000
L10: =-Assumptions!$B$15 -> -1100000 | M10: =Assumptions!$B$22 -> 132000 | N10: =Assumptions!$B$22 -> 132000 | O10: =Assumptions!$B$22 -> 132000 | P10: =Assumptions!$B$22 -> 132000 | Q10: =Assumptions!$B$22 -> 132000 | R10: =Assumptions!$B$22 -> 132000 | S10: =Assumptions!$B$22*0.5+'Reversion Scenarios'!G9 -> 1056000 | U10: =-Assumptions!$B$14 -> -1600000 | V10: =Assumptions!$B$22 -> 132000 | W10: =Assumptions!$B$22 -> 132000 | X10: =Assumptions!$B$22 -> 132000 | Y10: =Assumptions!$B$22 -> 132000 | Z10: =Assumptions!$B$22 -> 132000 | AA10: =Assumptions!$B$22 -> 132000 | AB10: =Assumptions!$B$22*0.5+'Reversion Scenarios'!G9 -> 1056000
A11: HEADLINE RETURNS | L11: =-Assumptions!$B$15 -> -1100000 | M11: =Assumptions!$B$22 -> 132000 | N11: =Assumptions!$B$22 -> 132000 | O11: =Assumptions!$B$22 -> 132000 | P11: =Assumptions!$B$22 -> 132000 | Q11: =Assumptions!$B$22 -> 132000 | R11: =Assumptions!$B$22 -> 132000 | S11: =Assumptions!$B$22*0.5+'Reversion Scenarios'!G10 -> 693000 | U11: =-Assumptions!$B$14 -> -1600000 | V11: =Assumptions!$B$22 -> 132000 | W11: =Assumptions!$B$22 -> 132000 | X11: =Assumptions!$B$22 -> 132000 | Y11: =Assumptions!$B$22 -> 132000 | Z11: =Assumptions!$B$22 -> 132000 | AA11: =Assumptions!$B$22 -> 132000 | AB11: =Assumptions!$B$22*0.5+'Reversion Scenarios'!G10 -> 693000
A12: Going-in cap rate | B12: =Assumptions!$B$22/Assumptions!$B$15 -> 0.12 | C12: In-place rent divided by our purchase price | L12: =-Assumptions!$B$14 -> -1600000 | M12: =Assumptions!$B$22 -> 132000 | N12: =Assumptions!$B$22 -> 132000 | O12: =Assumptions!$B$22 -> 132000 | P12: =Assumptions!$B$22 -> 132000 | Q12: =Assumptions!$B$22 -> 132000 | R12: =Assumptions!$B$22 -> 132000 | S12: =Assumptions!$B$22*0.5+'Reversion Scenarios'!$G$11 -> 1231500.5
A13: Price per square foot | B13: =Assumptions!$B$15/Assumptions!$B$7 -> 250 | C13: Well below replacement cost | L13: Ladder cash flows
A14: Unlevered IRR (expected) | B14: =IRR(B9:I9) -> 0.11995498 | C14: Probability-weighted across all six reversion outcomes | L14: =-A31 -> -1100000 | M14: =Assumptions!$B$22 -> 132000 | N14: =Assumptions!$B$22 -> 132000 | O14: =Assumptions!$B$22 -> 132000 | P14: =Assumptions!$B$22 -> 132000 | Q14: =Assumptions!$B$22 -> 132000 | R14: =Assumptions!$B$22 -> 132000 | S14: =Assumptions!$B$22*0.5+'Reversion Scenarios'!$G$11 -> 1231500.5 | U14: =-A31 -> -1100000 | V14: =Assumptions!$B$22 -> 132000 | W14: =Assumptions!$B$22 -> 132000 | X14: =Assumptions!$B$22 -> 132000 | Y14: =Assumptions!$B$22 -> 132000 | Z14: =Assumptions!$B$22 -> 132000 | AA14: =Assumptions!$B$22 -> 132000 | AB14: =Assumptions!$B$22*0.5+'Reversion Scenarios'!G5 -> 1705864.9 | AD14: =-A31 -> -1100000 | AE14: =Assumptions!$B$22 -> 132000 | AF14: =Assumptions!$B$22 -> 132000 | AG14: =Assumptions!$B$22 -> 132000 | AH14: =Assumptions!$B$22 -> 132000 | AI14: =Assumptions!$B$22 -> 132000 | AJ14: =Assumptions!$B$22 -> 132000 | AK14: =Assumptions!$B$22*0.5+'Reversion Scenarios'!G10 -> 693000
A15: Equity multiple | B15: =SUM(C9:I9)/Assumptions!$B$15 -> 1.8395459 | C15: Total cash returned divided by cash invested | L15: =-A32 -> -1150000 | M15: =Assumptions!$B$22 -> 132000 | N15: =Assumptions!$B$22 -> 132000 | O15: =Assumptions!$B$22 -> 132000 | P15: =Assumptions!$B$22 -> 132000 | Q15: =Assumptions!$B$22 -> 132000 | R15: =Assumptions!$B$22 -> 132000 | S15: =Assumptions!$B$22*0.5+'Reversion Scenarios'!$G$11 -> 1231500.5 | U15: =-A32 -> -1150000 | V15: =Assumptions!$B$22 -> 132000 | W15: =Assumptions!$B$22 -> 132000 | X15: =Assumptions!$B$22 -> 132000 | Y15: =Assumptions!$B$22 -> 132000 | Z15: =Assumptions!$B$22 -> 132000 | AA15: =Assumptions!$B$22 -> 132000 | AB15: =Assumptions!$B$22*0.5+'Reversion Scenarios'!G5 -> 1705864.9 | AD15: =-A32 -> -1150000 | AE15: =Assumptions!$B$22 -> 132000 | AF15: =Assumptions!$B$22 -> 132000 | AG15: =Assumptions!$B$22 -> 132000 | AH15: =Assumptions!$B$22 -> 132000 | AI15: =Assumptions!$B$22 -> 132000 | AJ15: =Assumptions!$B$22 -> 132000 | AK15: =Assumptions!$B$22*0.5+'Reversion Scenarios'!G10 -> 693000
A16: Contracted rent to expiry | B16: =Assumptions!$B$22*6.5 -> 858000 | C16: Rent collected before the lease even matures | L16: =-A33 -> -1200000 | M16: =Assumptions!$B$22 -> 132000 | N16: =Assumptions!$B$22 -> 132000 | O16: =Assumptions!$B$22 -> 132000 | P16: =Assumptions!$B$22 -> 132000 | Q16: =Assumptions!$B$22 -> 132000 | R16: =Assumptions!$B$22 -> 132000 | S16: =Assumptions!$B$22*0.5+'Reversion Scenarios'!$G$11 -> 1231500.5 | U16: =-A33 -> -1200000 | V16: =Assumptions!$B$22 -> 132000 | W16: =Assumptions!$B$22 -> 132000 | X16: =Assumptions!$B$22 -> 132000 | Y16: =Assumptions!$B$22 -> 132000 | Z16: =Assumptions!$B$22 -> 132000 | AA16: =Assumptions!$B$22 -> 132000 | AB16: =Assumptions!$B$22*0.5+'Reversion Scenarios'!G5 -> 1705864.9 | AD16: =-A33 -> -1200000 | AE16: =Assumptions!$B$22 -> 132000 | AF16: =Assumptions!$B$22 -> 132000 | AG16: =Assumptions!$B$22 -> 132000 | AH16: =Assumptions!$B$22 -> 132000 | AI16: =Assumptions!$B$22 -> 132000 | AJ16: =Assumptions!$B$22 -> 132000 | AK16: =Assumptions!$B$22*0.5+'Reversion Scenarios'!G10 -> 693000
A17: ... as % of purchase price | B17: =Assumptions!$B$22*6.5/Assumptions!$B$15 -> 0.78 | C17: Capital returned with no reliance on renewal or resale | L17: =-A34 -> -1250000 | M17: =Assumptions!$B$22 -> 132000 | N17: =Assumptions!$B$22 -> 132000 | O17: =Assumptions!$B$22 -> 132000 | P17: =Assumptions!$B$22 -> 132000 | Q17: =Assumptions!$B$22 -> 132000 | R17: =Assumptions!$B$22 -> 132000 | S17: =Assumptions!$B$22*0.5+'Reversion Scenarios'!$G$11 -> 1231500.5 | U17: =-A34 -> -1250000 | V17: =Assumptions!$B$22 -> 132000 | W17: =Assumptions!$B$22 -> 132000 | X17: =Assumptions!$B$22 -> 132000 | Y17: =Assumptions!$B$22 -> 132000 | Z17: =Assumptions!$B$22 -> 132000 | AA17: =Assumptions!$B$22 -> 132000 | AB17: =Assumptions!$B$22*0.5+'Reversion Scenarios'!G5 -> 1705864.9 | AD17: =-A34 -> -1250000 | AE17: =Assumptions!$B$22 -> 132000 | AF17: =Assumptions!$B$22 -> 132000 | AG17: =Assumptions!$B$22 -> 132000 | AH17: =Assumptions!$B$22 -> 132000 | AI17: =Assumptions!$B$22 -> 132000 | AJ17: =Assumptions!$B$22 -> 132000 | AK17: =Assumptions!$B$22*0.5+'Reversion Scenarios'!G10 -> 693000
A18: Years of rent to full payback | B18: =Assumptions!$B$15/Assumptions!$B$22 -> 8.3333333 | C18: Simple payback on the in-place coupon | L18: =-A35 -> -1300000 | M18: =Assumptions!$B$22 -> 132000 | N18: =Assumptions!$B$22 -> 132000 | O18: =Assumptions!$B$22 -> 132000 | P18: =Assumptions!$B$22 -> 132000 | Q18: =Assumptions!$B$22 -> 132000 | R18: =Assumptions!$B$22 -> 132000 | S18: =Assumptions!$B$22*0.5+'Reversion Scenarios'!$G$11 -> 1231500.5 | U18: =-A35 -> -1300000 | V18: =Assumptions!$B$22 -> 132000 | W18: =Assumptions!$B$22 -> 132000 | X18: =Assumptions!$B$22 -> 132000 | Y18: =Assumptions!$B$22 -> 132000 | Z18: =Assumptions!$B$22 -> 132000 | AA18: =Assumptions!$B$22 -> 132000 | AB18: =Assumptions!$B$22*0.5+'Reversion Scenarios'!G5 -> 1705864.9 | AD18: =-A35 -> -1300000 | AE18: =Assumptions!$B$22 -> 132000 | AF18: =Assumptions!$B$22 -> 132000 | AG18: =Assumptions!$B$22 -> 132000 | AH18: =Assumptions!$B$22 -> 132000 | AI18: =Assumptions!$B$22 -> 132000 | AJ18: =Assumptions!$B$22 -> 132000 | AK18: =Assumptions!$B$22*0.5+'Reversion Scenarios'!G10 -> 693000
L19: =-A36 -> -1400000 | M19: =Assumptions!$B$22 -> 132000 | N19: =Assumptions!$B$22 -> 132000 | O19: =Assumptions!$B$22 -> 132000 | P19: =Assumptions!$B$22 -> 132000 | Q19: =Assumptions!$B$22 -> 132000 | R19: =Assumptions!$B$22 -> 132000 | S19: =Assumptions!$B$22*0.5+'Reversion Scenarios'!$G$11 -> 1231500.5 | U19: =-A36 -> -1400000 | V19: =Assumptions!$B$22 -> 132000 | W19: =Assumptions!$B$22 -> 132000 | X19: =Assumptions!$B$22 -> 132000 | Y19: =Assumptions!$B$22 -> 132000 | Z19: =Assumptions!$B$22 -> 132000 | AA19: =Assumptions!$B$22 -> 132000 | AB19: =Assumptions!$B$22*0.5+'Reversion Scenarios'!G5 -> 1705864.9 | AD19: =-A36 -> -1400000 | AE19: =Assumptions!$B$22 -> 132000 | AF19: =Assumptions!$B$22 -> 132000 | AG19: =Assumptions!$B$22 -> 132000 | AH19: =Assumptions!$B$22 -> 132000 | AI19: =Assumptions!$B$22 -> 132000 | AJ19: =Assumptions!$B$22 -> 132000 | AK19: =Assumptions!$B$22*0.5+'Reversion Scenarios'!G10 -> 693000
A20: IRR BY REVERSION OUTCOME — every scenario at our offer price | L20: =-A37 -> -1600000 | M20: =Assumptions!$B$22 -> 132000 | N20: =Assumptions!$B$22 -> 132000 | O20: =Assumptions!$B$22 -> 132000 | P20: =Assumptions!$B$22 -> 132000 | Q20: =Assumptions!$B$22 -> 132000 | R20: =Assumptions!$B$22 -> 132000 | S20: =Assumptions!$B$22*0.5+'Reversion Scenarios'!$G$11 -> 1231500.5 | U20: =-A37 -> -1600000 | V20: =Assumptions!$B$22 -> 132000 | W20: =Assumptions!$B$22 -> 132000 | X20: =Assumptions!$B$22 -> 132000 | Y20: =Assumptions!$B$22 -> 132000 | Z20: =Assumptions!$B$22 -> 132000 | AA20: =Assumptions!$B$22 -> 132000 | AB20: =Assumptions!$B$22*0.5+'Reversion Scenarios'!G5 -> 1705864.9 | AD20: =-A37 -> -1600000 | AE20: =Assumptions!$B$22 -> 132000 | AF20: =Assumptions!$B$22 -> 132000 | AG20: =Assumptions!$B$22 -> 132000 | AH20: =Assumptions!$B$22 -> 132000 | AI20: =Assumptions!$B$22 -> 132000 | AJ20: =Assumptions!$B$22 -> 132000 | AK20: =Assumptions!$B$22*0.5+'Reversion Scenarios'!G10 -> 693000
A21: Outcome | B21: Probability | C21: Net value | D21: IRR at our offer | E21: IRR at the ask
A22: ='Reversion Scenarios'!A5 -> Tenant renews at the option rent | B22: ='Reversion Scenarios'!B5 -> 0.4 | C22: ='Reversion Scenarios'!G5 -> 1639864.9 | D22: =IRR(L6:S6) -> 0.1579787 | E22: =IRR(U6:AB6) -> 0.080673127
A23: ='Reversion Scenarios'!A6 -> New NJ cannabis licensee @ $30/SF | B23: ='Reversion Scenarios'!B6 -> 0.1 | C23: ='Reversion Scenarios'!G6 -> 1064473.7 | D23: =IRR(L7:S7) -> 0.11058277 | E23: =IRR(U7:AB7) -> 0.034031052
A24: ='Reversion Scenarios'!A7 -> Bank / credit union / retail @ $22/SF | B24: ='Reversion Scenarios'!B7 -> 0.2 | C24: ='Reversion Scenarios'!G7 -> 831285.71 | D24: =IRR(L8:S8) -> 0.08657826 | E24: =IRR(U8:AB8) -> 0.010227658
A25: ='Reversion Scenarios'!A8 -> Medical / urgent care / vet @ $24/SF | B25: ='Reversion Scenarios'!B8 -> 0.2 | C25: ='Reversion Scenarios'!G8 -> 780000 | D25: =IRR(L9:S9) -> 0.080764747 | E25: =IRR(U9:AB9) -> 0.0044404445
A26: ='Reversion Scenarios'!A9 -> QSR pad rebuild @ $42/SF on 2,200 SF | B26: ='Reversion Scenarios'!B9 -> 0.05 | C26: ='Reversion Scenarios'!G9 -> 990000 | D26: =IRR(L10:S10) -> 0.10330551 | E26: =IRR(U10:AB10) -> 0.026829522
A27: ='Reversion Scenarios'!A10 -> Extended vacancy - land + shell only | B27: ='Reversion Scenarios'!B10 -> 0.05 | C27: ='Reversion Scenarios'!G10 -> 627000 | D27: =IRR(L11:S11) -> 0.061974317 | E27: =IRR(U11:AB11) -> -0.014333776
A28: Every outcome clears at our offer price. Compare the two IRR columns: at the asking price the same scenarios return under 3.5%, and the liquidation case loses money.
A29: NEGOTIATION LADDER — what each dollar of price costs us
A30: Purchase price | B30: $ / SF | C30: Going-in cap | D30: Expected IRR | E30: If tenant renews | F30: Worst case | G30: Position
A31: 1100000 | B31: =A31/Assumptions!$B$7 -> 250 | C31: =Assumptions!$B$22/A31 -> 0.12 | D31: =IRR(L14:S14) -> 0.11995498 | E31: =IRR(U14:AB14) -> 0.1579787 | F31: =IRR(AD14:AK14) -> 0.061974317 | G31: OUR OFFER
A32: 1150000 | B32: =A32/Assumptions!$B$7 -> 261.36364 | C32: =Assumptions!$B$22/A32 -> 0.11478261 | D32: =IRR(L15:S15) -> 0.11029818 | E32: =IRR(U15:AB15) -> 0.14826619 | F32: =IRR(AD15:AK15) -> 0.052320123 | G32: Comfortable
A33: 1200000 | B33: =A33/Assumptions!$B$7 -> 272.72727 | C33: =Assumptions!$B$22/A33 -> 0.11 | D33: =IRR(L16:S16) -> 0.10120494 | E33: =IRR(U16:AB16) -> 0.13911393 | F33: =IRR(AD16:AK16) -> 0.043240529 | G33: Comfortable
A34: 1250000 | B34: =A34/Assumptions!$B$7 -> 284.09091 | C34: =Assumptions!$B$22/A34 -> 0.1056 | D34: =IRR(L17:S17) -> 0.092618379 | E34: =IRR(U17:AB17) -> 0.1304658 | F34: =IRR(AD17:AK17) -> 0.034676833 | G34: Practical ceiling
A35: 1300000 | B35: =A35/Assumptions!$B$7 -> 295.45455 | C35: =Assumptions!$B$22/A35 -> 0.10153846 | D35: =IRR(L18:S18) -> 0.084489526 | E35: =IRR(U18:AB18) -> 0.12227345 | F35: =IRR(AD18:AK18) -> 0.026578566 | G35: Fair value - no margin left
A36: 1400000 | B36: =A36/Assumptions!$B$7 -> 318.18182 | C36: =Assumptions!$B$22/A36 -> 0.094285714 | D36: =IRR(L19:S19) -> 0.069440652 | E36: =IRR(U19:AB19) -> 0.10709369 | F36: =IRR(AD19:AK19) -> 0.011609275 | G36: Too rich
A37: 1600000 | B37: =A37/Assumptions!$B$7 -> 363.63636 | C37: =Assumptions!$B$22/A37 -> 0.0825 | D37: =IRR(L20:S20) -> 0.043288476 | E37: =IRR(U20:AB20) -> 0.080673127 | F37: =IRR(AD20:AK20) -> -0.014333776 | G37: Asking price - decline
A39: Worst case = extended vacancy, sold as land and shell. Even that outcome pays a positive return at our offer price.

Sheet Valuation
A1: VALUATION — four independent methods
A2: Run separately, all four land above our offer and well below the asking price.
A4: Method | B4: How it is derived | C4: Indicated value | D4: vs. asking price | E4: vs. our offer | F4: Weight
A5: In-place income at a market cap rate | B5: In-place rent capitalized at 9.75% — the correct rate for flat rent on a personally guaranteed lease with 6.5 years left | C5: =Assumptions!$B$22/0.0975 -> 1353846.2 | D5: =C5/Assumptions!$B$14-1 -> -0.15384615 | E5: =C5/Assumptions!$B$15-1 -> 0.23076923 | F5: 0.4
A6: Tax assessor equalized value | B6: Assessed value divided by the Camden County equalization ratio | C6: =Assumptions!$B$39/Assumptions!$B$40 -> 1271024.9 | D6: =C6/Assumptions!$B$14-1 -> -0.20560943 | E6: =C6/Assumptions!$B$15-1 -> 0.15547719 | F6: 0.2
A7: County retail price per SF | B7: Camden County retail listing average of ~$273/SF applied to our building | C7: =273*Assumptions!$B$7 -> 1201200 | D7: =C7/Assumptions!$B$14-1 -> -0.24925 | E7: =C7/Assumptions!$B$15-1 -> 0.092 | F7: 0.15
A8: Market-rent capitalization | B8: Conventional market rent capitalized at 8.75% — the value with no cannabis premium at all | C8: =Assumptions!$B$31*Assumptions!$B$7/0.0875 -> 1106285.7 | D8: =C8/Assumptions!$B$14-1 -> -0.30857143 | E8: =C8/Assumptions!$B$15-1 -> 0.0057142857 | F8: 0.25
A9: WEIGHTED VALUE INDICATION | B9: Each method weighted as shown | C9: =SUMPRODUCT(C5:C8,F5:F8)/SUM(F5:F8) -> 1252494.9 | D9: =C9/Assumptions!$B$14-1 -> -0.2171907 | E9: =C9/Assumptions!$B$15-1 -> 0.1386317 | F9: =SUM(F5:F8) -> 1
A11: THE MARGIN OF SAFETY
A12: Our offer | B12: =Assumptions!$B$15 -> 1100000 | C12: What we are proposing to pay
A13: Weighted value indication | B13: =Valuation!$C$9 -> 1252494.9 | C13: Where the four methods converge
A14: Discount to value | B14: =Assumptions!$B$15/Valuation!$C$9-1 -> -0.12175289 | C14: Margin of safety on entry
A15: Absolute floor (market-rent value) | B15: =Assumptions!$B$31*Assumptions!$B$7/0.0875 -> 1106285.7 | C15: What the building is worth stripped of every cannabis dollar
A16: Our offer vs. that floor | B16: =Assumptions!$B$15/(Assumptions!$B$31*Assumptions!$B$7/0.0875)-1 -> -0.0056818182 | C16: We are buying at conventional-use value — the cannabis premium is free
A17: Break-even rent to hold our basis | B17: =Assumptions!$B$15*0.085/Assumptions!$B$7 -> 21.25 | C17: $/SF the building must re-let at to preserve our price at an 8.5% cap
A18: Market rent (base) for comparison | B18: =Assumptions!$B$31 -> 22 | C18: Our break-even sits below the market midpoint — that is the cushion

Sheet Re-Rent Analysis
A1: RE-RENT ANALYSIS — what the building lets for, and what that yields us
A2: The question the buyer asked. Yield on cost is calculated against our offer price.
A4: Tenant type | B4: Rent/SF low | C4: Rent/SF high | D4: Annual rent low | E4: Annual rent high | F4: Yield low | G4: Yield high | H4: Comment
A5: Cannabis - new NJ licensee | B5: 28 | C5: 34 | D5: =B5*4400 -> 123200 | E5: =C5*4400 -> 149600 | F5: =D5/Assumptions!$B$15 -> 0.112 | G5: =E5/Assumptions!$B$15 -> 0.136 | H5: Holds the rent outright, but the demand pool is one seat
A6: Medical / urgent care / dental / vet | B6: 22 | C6: 26 | D6: =B6*4400 -> 96800 | E6: =C6*4400 -> 114400 | F6: =D6/Assumptions!$B$15 -> 0.088 | G6: =E6/Assumptions!$B$15 -> 0.104 | H6: Deepest demand pool; drive-thru converts to covered drop-off
A7: Bank / credit union | B7: 22 | C7: 26 | D7: =B7*4400 -> 96800 | E7: =C7*4400 -> 114400 | F7: =D7/Assumptions!$B$15 -> 0.088 | G7: =E7/Assumptions!$B$15 -> 0.104 | H7: Turnkey - vault and drive-thru already in place, lowest TI
A8: QSR / coffee drive-thru | B8: 38 | C8: 48 | D8: =B8*2200 -> 83600 | E8: =C8*2200 -> 105600 | F8: =D8/Assumptions!$B$15 -> 0.076 | G8: =E8/Assumptions!$B$15 -> 0.096 | H8: Reduced 2,200 SF footprint or pad rebuild; heaviest capex
A9: Conventional retail / service | B9: 18 | C9: 22 | D9: =B9*4400 -> 79200 | E9: =C9*4400 -> 96800 | F9: =D9/Assumptions!$B$15 -> 0.072 | G9: =E9/Assumptions!$B$15 -> 0.088 | H9: The floor - liquor, convenience, pharmacy, auto parts
A10: Daycare / early education | B10: 18 | C10: 22 | D10: =B10*4400 -> 79200 | E10: =C10*4400 -> 96800 | F10: =D10/Assumptions!$B$15 -> 0.072 | G10: =E10/Assumptions!$B$15 -> 0.088 | H10: Site plan and licensing lag; 3 acres supports playground
A11: IN PLACE TODAY (cannabis) | B11: =Assumptions!$B$22/Assumptions!$B$7 -> 30 | C11: =Assumptions!$B$22/Assumptions!$B$7 -> 30 | D11: =Assumptions!$B$22 -> 132000 | E11: =Assumptions!$B$22 -> 132000 | F11: =Assumptions!$B$22/Assumptions!$B$15 -> 0.12 | G11: =Assumptions!$B$22/Assumptions!$B$15 -> 0.12 | H11: 36% above conventional market rent - a premium we are not paying for
A13: THE DOWNSIDE TEST
A14: Conventional market rent (base) | B14: =Assumptions!$B$31*Assumptions!$B$7 -> 96800 | C14: What an ordinary tenant pays for this box
A15: Yield on our offer | B15: =Assumptions!$B$31*Assumptions!$B$7/Assumptions!$B$15 -> 0.088 | C15: Still a strong yield with no cannabis rent at all
A16: Deep downside rent @ $18/SF | B16: =18*Assumptions!$B$7 -> 79200 | C16: Bottom of the conventional range
A17: Yield on our offer | B17: =18*Assumptions!$B$7/Assumptions!$B$15 -> 0.072 | C17: Even the worst re-let clears our cost of capital
A18: Roll-down from in-place rent | B18: =Assumptions!$B$31*Assumptions!$B$7/Assumptions!$B$22-1 -> -0.26666667 | C18: The rent reduction we have already underwritten
A19: Annual carry if fully vacant | B19: =(Assumptions!$B$36+Assumptions!$B$37+Assumptions!$B$38) -> 61402 | C19: Taxes, insurance and maintenance the landlord picks up

Sheet Re-Leasing Options
A1: RE-LEASING OPTIONS — who takes it, what they pay, how long it takes, and how long they stay
A2: The goal is one re-tenanting into a long covenant, then a passive hold - not an asset that churns.
A4: THE OBJECTIVE: ONE RE-TENANTING, NOT PERPETUAL CHURN
A5: This asset should not become a management job. The plan is a SINGLE re-tenanting event, into a tenant that signs a 10-15 year NNN lease with escalations, and then it goes passive again for a decade or more. That objective changes the ranking. The right tenants are the ones with sunk fit-out cost and a location-bound customer base - banks, credit unions and medical groups - because they stay. The wrong answer is a string of short conventional retail deals at $18-22/SF that roll every five years and put us back in the market again and again. It also argues against demising the box into two spaces for a QSR: that trades one covenant for two, and doubles the management. Keep it single-tenant.
A9: THE OPTIONS — ranked by durability first, then speed and cost
A10: # | B10: Tenant type | C10: Rent / SF | D10: Annual rent | E10: Time to rent | F10: Landlord cost | G10: Typical lease term | H10: Rollover risk | I10: Why this works here
A11: 1 | B11: Urgent care / dental / vet | C11: 24 | D11: =C11*4400 -> 105600 | E11: 17 | F11: =C11*0+60*4400 -> 264000 | G11: 10-15 yrs + options | H11: Very low | I11: The best answer for a passive owner. Huge sunk fit-out and a location-bound patient base mean they do not move. They sign 10-15 year NNN leases WITH escalations - fixing the one real flaw in the lease we are buying. Deepest tenant pool in South Jersey; the drive-thru converts to a covered patient drop-off.
A12: 2 | B12: Bank / credit union | C12: 24 | D12: =C12*4400 -> 105600 | E12: 10 | F12: =C12*0+5*4400 -> 22000 | G12: 10-15 yrs + options | H12: Very low | I12: The building already IS one - vault, 3-lane drive-thru and teller infrastructure transfer as-is, so fit-out is cosmetic and occupancy is fastest. Branches are capital-intensive and banks stay put. Cheapest and quickest route to a long covenant.
A13: 3 | B13: Cannabis - new NJ licensee | C13: 30 | D13: =C13*4400 -> 132000 | E13: 24 | F13: =C13*0+15*4400 -> 66000 | G13: 10 yrs | H13: Low | I13: Holds the full rent with almost no fit-out, and the licence is tied to this premises so the tenant is sticky. But Waterford permits only two retail licences and the incumbent holds one, and CRC approval adds a long regulatory lag.
A14: 4 | B14: QSR / coffee drive-thru | C14: 42 | D14: =C14*2200 -> 92400 | E14: 24 | F14: =C14*0+130*2200 -> 286000 | G14: 15-20 yrs | H14: Very low | I14: Longest lease terms of any use and very sticky - but it needs a demise to ~2,200 SF or a pad rebuild, which trades one covenant for two and doubles the management. Pursue it on the excess LAND as a ground lease instead, and keep the box single-tenant.
A15: 5 | B15: Daycare / early education | C15: 20 | D15: =C15*4400 -> 88000 | E15: 22 | F15: =C15*0+70*4400 -> 308000 | G15: 10-15 yrs | H15: Low | I15: Sticky once open - licensing and parent relationships are location-bound - but site plan approval and state licensing make this the slowest option to start.
A16: 6 | B16: Conventional retail / service | C16: 20 | D16: =C16*4400 -> 88000 | E16: 10 | F16: =C16*0+30*4400 -> 132000 | G16: 5-10 yrs | H16: HIGH | I16: Liquor, convenience, pharmacy, auto parts, fitness. Always available, and it pays - but these roll every five years and put us straight back in the market. Use it as a fallback, not a plan, precisely because it is the churn outcome we are trying to avoid.
B17: IN PLACE TODAY (cannabis) | C17: =Assumptions!$B$22/Assumptions!$B$7 -> 30 | D17: =Assumptions!$B$22 -> 132000 | E17: - | F17: - | G17: 10 yrs, flat | H17: n/a | I17: No action required while the lease runs to January 2033
A19: HOW LONG IT TAKES — indicative timeline from vacancy to rent commencing
B20: Stage | C20: Bank / CU | D20: Medical | E20: Retail | F20: Cannabis | G20: QSR | I20: What happens
B21: Marketing and tenant sourcing | C21: 4 | D21: 6 | E21: 4 | F21: 6 | G21: 9 | I21: List, tour, negotiate LOI. A corner drive-thru property tours well and shortens this.
B22: Lease negotiation and signature | C22: 2 | D22: 2 | E22: 2 | F22: 3 | G22: 3 | I22: Longer where a licence or franchise approval is involved.
B23: Permits, approvals and licensing | C23: 1 | D23: 3 | E23: 1 | F23: 12 | G23: 4 | I23: The cannabis line is CRC plus township approval - this is the long pole in that option.
B24: Construction and fit-out | C24: 3 | D24: 6 | E24: 3 | F24: 3 | G24: 8 | I24: Bank and retail are cosmetic. Medical and QSR are full build-outs.
B25: TOTAL MONTHS TO RENT COMMENCING | C25: =SUM(C21:C24) -> 10 | D25: =SUM(D21:D24) -> 17 | E25: =SUM(E21:E24) -> 10 | F25: =SUM(F21:F24) -> 24 | G25: =SUM(G21:G24) -> 24 | I25: Overlapping stages can compress this; assume the longer end in a slow market
B26: Rent lost during downtime | C26: =C25/12*Assumptions!$B$31*Assumptions!$B$7 -> 80666.667 | D26: =D25/12*Assumptions!$B$31*Assumptions!$B$7 -> 137133.33 | E26: =E25/12*Assumptions!$B$31*Assumptions!$B$7 -> 80666.667 | F26: =F25/12*Assumptions!$B$31*Assumptions!$B$7 -> 193600 | G26: =G25/12*Assumptions!$B$31*Assumptions!$B$7 -> 193600 | I26: Market rent forgone while the building sits empty
B27: Carry cost during downtime | C27: =C25/12*(Assumptions!$B$36+Assumptions!$B$37+Assumptions!$B$38) -> 51168.333 | D27: =D25/12*(Assumptions!$B$36+Assumptions!$B$37+Assumptions!$B$38) -> 86986.167 | E27: =E25/12*(Assumptions!$B$36+Assumptions!$B$37+Assumptions!$B$38) -> 51168.333 | F27: =F25/12*(Assumptions!$B$36+Assumptions!$B$37+Assumptions!$B$38) -> 122804 | G27: =G25/12*(Assumptions!$B$36+Assumptions!$B$37+Assumptions!$B$38) -> 122804 | I27: Taxes, insurance and maintenance the landlord picks up when vacant
A29: WHY THE CORNER MATTERS — this is not an ordinary in-line box
B30: Two frontages, two access points | C30: 451 White Horse Pike sits at the corner of US Route 30 and Cooper Folly Road. Corner sites carry a genuine rent premium over mid-block space because they offer signage on two streets, ingress and egress from a secondary road (so customers avoid turning across highway traffic), and far easier circulation for a drive-thru.
B31: It is what makes the drive-thru work | C31: A 3-lane drive-thru needs stacking depth and a clean in-and-out loop. On a mid-block parcel that is hard; on a corner it is straightforward. This is the single feature that puts banks, QSR, coffee and pharmacy tenants in play at all.
B32: It widens the tenant pool | C32: Uses that require or strongly prefer a corner - QSR, coffee, pharmacy, convenience, car wash, bank - are precisely the covenant-strength tenants who sign long NNN leases with escalations. A mid-block box does not get those calls.
B33: It supports subdividing a pad | C33: A corner parcel of 3.13 acres can usually yield a second access point and a separate pad with its own frontage, without compromising the existing building's parking or circulation. That is what makes the land upside physically realistic rather than theoretical.
B34: It shortens marketing time | C34: Corner drive-thru properties on a state highway tour well and lease faster. That is reflected in the shorter marketing periods in the table above versus what a mid-block box on this corridor would carry.
B36: Marketing periods, fit-out durations and landlord costs are analyst estimates based on typical South Jersey second-generation retail transactions. They are shown in blue so you can flex them.

Sheet Land Upside
A1: LAND UPSIDE — 2.5 idle acres, excluded from every return in this model
A2: Building coverage is 3.2%. This is free option value; we never bid it up.
A4: SITE CAPACITY
A5: Total site area | B5: =Assumptions!$B$8 -> 3.13 | C5: Per Offering Memorandum
A6: Building footprint | B6: =Assumptions!$B$7/43560 -> 0.1010101 | C6: 4,400 SF converted to acres
A7: Building coverage | B7: =Assumptions!$B$7/(Assumptions!$B$8*43560) -> 0.032271598 | C7: Extraordinarily low for a highway commercial site
A8: Land used by parking / drive-thru | B8: 0.55 | C8: ESTIMATE - confirm with a site plan and parking count
A9: DEVELOPABLE EXCESS LAND | B9: =Assumptions!$B$8-Assumptions!$B$7/43560-B8 -> 2.4789899 | C9: The opportunity - subject to confirming the lease does not demise the whole parcel
A11: INCOME OPPORTUNITIES
A12: Opportunity | B12: Low | C12: Base | D12: High | E12: Land used | F12: How it is derived
A13: Outparcel ground lease | B13: 60000 | C13: =Assumptions!$B$44 -> 80000 | D13: 110000 | E13: 0.75-1.0 AC | F13: Benchmarked to the listing agent's own comps: 7 Brew pays $155,000/yr and Wendy's $157,659/yr on build-to-suit pads. A ground lease, where the tenant builds, runs ~40-55% of that. QSR, coffee, car wash or medical pad.
A14: EV fast-charging licence | B14: 12000 | C14: =Assumptions!$B$45 -> 20000 | D14: 34000 | E14: 0.30-0.40 AC | F14: 6-8 DC fast stalls. Corridor benchmarks of $2,200-3,500/stall/mo discounted to $1,000-1,800 for a 15,370 VPD secondary route, at a 10-25% owner revenue share. Operator funds 100% of capex.
A15: COMBINED INCREMENTAL NOI | B15: =SUM(B13:B14) -> 72000 | C15: =SUM(C13:C14) -> 100000 | D15: =SUM(D13:D14) -> 144000 | E15: ~1.3 AC | F15: On land carried at zero in the base case
A16: Value created (net of build-out cost) | B16: =B15/Assumptions!$B$47-Assumptions!$B$46 -> 628378.38 | C16: =C15/Assumptions!$B$47-Assumptions!$B$46 -> 931081.08 | D16: =D15/Assumptions!$B$47-Assumptions!$B$46 -> 1406756.8 | F16: Incremental NOI capitalized, less subdivision, entitlement and site work
A18: EFFECT ON THE DEAL IF EXECUTED (base case)
A19: Stabilized NOI with land income | B19: =Assumptions!$B$22+C15 -> 232000 | C19: In-place rent plus pad and EV licence
A20: Yield on cost | B20: =(Assumptions!$B$22+C15)/Assumptions!$B$15 -> 0.21090909 | C20: Against our offer price
A21: Yield on cost today, for comparison | B21: =Assumptions!$B$22/Assumptions!$B$15 -> 0.12 | C21: Before any land monetization
A22: Value created per dollar invested | B22: =C16/Assumptions!$B$15 -> 0.84643735 | C22: Value added as a share of our basis
A23: DOWNSIDE RE-TEST: dark building @ $18/SF + land income | B23: =(18*Assumptions!$B$7+C15)/Assumptions!$B$15 -> 0.16290909 | C23: The land does not just add upside - it removes the downside
A25: GATING ITEMS — confirm before assigning any of this a dollar
A26: Demised premises clause | B26: THE gating item. The offering markets 3.13 AC as the leased premises. If the lease demises the entire lot to the tenant, we cannot develop any of it during the term without their consent. Read this clause first.
A27: Pinelands Commission review | B27: Atco sits in the Regional Growth Area - the most permissive of the six CMP designations - but subdivision and site plan still go through Pinelands review.
A28: Sewer capacity | B28: The CMP requires nonresidential parcels under one acre to be served by centralized wastewater. A septic-only site materially limits what a pad can be.
A29: Parking and circulation | B29: Any pad must leave the existing tenant with compliant parking and preserve drive-thru stacking. Run a count against the PHB standard.
A30: Tesla specifically | B30: Tesla historically pays site hosts little or no ground rent, and its newer Supercharger for Business program is host-owned, meaning we would fund the hardware. The rent is with third-party operators who fund 100% of capex.

Sheet Financing
A1: FINANCING — can he borrow against it, and what does leverage do?
A2: Cannabis collateral is not bankable or CMBS-eligible. Assume private or credit-union debt.
A4: DEBT ASSUMPTIONS | L4: =-B18 -> -495000 | M4: =C18 -> 66028.326 | N4: =C18 -> 66028.326 | O4: =C18 -> 66028.326 | P4: =C18 -> 66028.326 | Q4: =C18 -> 66028.326 | R4: =C18 -> 66028.326 | S4: =C18*0.5+E18 -> 643328.11
A5: Loan to value | B5: 0.55 | C5: Private lenders cap cannabis-collateral LTV well below conventional | L5: =-B19 -> -562500 | M5: =C19 -> 57032.188 | N5: =C19 -> 57032.188 | O5: =C19 -> 57032.188 | P5: =C19 -> 57032.188 | Q5: =C19 -> 57032.188 | R5: =C19 -> 57032.188 | S5: =C19*0.5+E19 -> 563122.79
A6: Interest rate | B6: 0.1 | C6: Private / credit-union pricing for cannabis-tenanted real estate | L6: =-B20 -> -720000 | M6: =C20 -> 36041.201 | N6: =C20 -> 36041.201 | O6: =C20 -> 36041.201 | P6: =C20 -> 36041.201 | Q6: =C20 -> 36041.201 | R6: =C20 -> 36041.201 | S6: =C20*0.5+E20 -> 375977.05
A7: Amortization (years) | B7: 25 | C7: Typical for this lender class
A8: Hold period (years) | B8: 6.5 | C8: To lease expiry, January 2033
A10: LOAN SIZING AND COVERAGE AT THREE PRICE POINTS
A11: Purchase price | B11: Loan amount | C11: Equity | D11: Annual debt service | E11: NOI | F11: DSCR | G11: Cash flow after debt | H11: Cash-on-cash | I11: Verdict
A12: Our offer | B12: =Assumptions!$B$15*$B$5 -> 605000 | C12: =Assumptions!$B$15-B12 -> 495000 | D12: =-PMT($B$6/12,$B$7*12,B12)*12 -> 65971.674 | E12: =Assumptions!$B$22 -> 132000 | F12: =E12/D12 -> 2.0008587 | G12: =E12-D12 -> 66028.326 | H12: =G12/C12 -> 0.13339056 | I12: =IF(F12>=1.5,"Comfortably financeable",IF(F12>=1.25,"Financeable, tight","Lender would decline")) -> Comfortably financeable
A13: Practical ceiling | B13: =Assumptions!$B$16*$B$5 -> 687500 | C13: =Assumptions!$B$16-B13 -> 562500 | D13: =-PMT($B$6/12,$B$7*12,B13)*12 -> 74967.812 | E13: =Assumptions!$B$22 -> 132000 | F13: =E13/D13 -> 1.7607557 | G13: =E13-D13 -> 57032.188 | H13: =G13/C13 -> 0.10139056 | I13: =IF(F13>=1.5,"Comfortably financeable",IF(F13>=1.25,"Financeable, tight","Lender would decline")) -> Comfortably financeable
A14: Asking price | B14: =Assumptions!$B$14*$B$5 -> 880000 | C14: =Assumptions!$B$14-B14 -> 720000 | D14: =-PMT($B$6/12,$B$7*12,B14)*12 -> 95958.799 | E14: =Assumptions!$B$22 -> 132000 | F14: =E14/D14 -> 1.3755904 | G14: =E14-D14 -> 36041.201 | H14: =G14/C14 -> 0.050057224 | I14: =IF(F14>=1.5,"Comfortably financeable",IF(F14>=1.25,"Financeable, tight","Lender would decline")) -> Financeable, tight
A16: LEVERED RETURN — hold to expiry, sold at the weighted reversion
A17: Purchase price | B17: Equity in | C17: Annual cash flow | D17: Loan balance at exit | E17: Net sale proceeds | F17: Levered IRR | G17: Unlevered IRR | H17: Leverage adds
A18: Our offer | B18: =C12 -> 495000 | C18: =G12 -> 66028.326 | D18: =B12*(1+$B$6/12)^($B$8*12)-(-PMT($B$6/12,$B$7*12,B12))*((1+$B$6/12)^($B$8*12)-1)/($B$6/12) -> 555186.51 | E18: ='Reversion Scenarios'!$G$11-D18 -> 610313.95 | F18: =IRR(L4:S4) -> 0.14848452 | G18: =Returns!$D$31 -> 0.11995498 | H18: =F18-G18 -> 0.028529536
A19: Practical ceiling | B19: =C13 -> 562500 | C19: =G13 -> 57032.188 | D19: =B13*(1+$B$6/12)^($B$8*12)-(-PMT($B$6/12,$B$7*12,B13))*((1+$B$6/12)^($B$8*12)-1)/($B$6/12) -> 630893.76 | E19: ='Reversion Scenarios'!$G$11-D19 -> 534606.7 | F19: =IRR(L5:S5) -> 0.090507662 | G19: =Returns!$D$34 -> 0.092618379 | H19: =F19-G19 -> -0.0021107171
A20: Asking price | B20: =C14 -> 720000 | C20: =G14 -> 36041.201 | D20: =B14*(1+$B$6/12)^($B$8*12)-(-PMT($B$6/12,$B$7*12,B14))*((1+$B$6/12)^($B$8*12)-1)/($B$6/12) -> 807544.01 | E20: ='Reversion Scenarios'!$G$11-D20 -> 357956.44 | F20: =IRR(L6:S6) -> -0.033201226 | G20: =Returns!$D$37 -> 0.043288476 | H20: =F20-G20 -> -0.076489702
A22: Read the DSCR column. At our offer the loan covers itself twice over and the deal throws off a double-digit cash-on-cash return. At the asking price coverage falls to a level most lenders decline, cash-on-cash drops to about 5%, and leverage turns the return NEGATIVE - because the debt costs more than the 8.25% the property yields. Our price is what makes this financeable at all.

Sheet Stress Tests
A1: STRESS TESTS — tenant health, sensitivity, and the exit
A2: How wrong can the assumptions be before the deal stops working?
A4: 1. TENANT HEALTH — can they carry the rent for 6.5 years? | J4: =-Assumptions!$B$15 -> -1100000 | K4: =Assumptions!$B$22 -> 132000 | L4: =Assumptions!$B$22 -> 132000 | M4: =Assumptions!$B$22 -> 132000 | N4: =Assumptions!$B$22 -> 132000 | O4: =Assumptions!$B$22 -> 132000 | P4: =Assumptions!$B$22 -> 132000 | Q4: =Assumptions!$B$22*0.5+$B$19 -> 1073379 | S4: =-Assumptions!$B$16 -> -1250000 | T4: =Assumptions!$B$22 -> 132000 | U4: =Assumptions!$B$22 -> 132000 | V4: =Assumptions!$B$22 -> 132000 | W4: =Assumptions!$B$22 -> 132000 | X4: =Assumptions!$B$22 -> 132000 | Y4: =Assumptions!$B$22 -> 132000 | Z4: =Assumptions!$B$22*0.5+$B$19 -> 1073379 | AB4: =-Assumptions!$B$14 -> -1600000 | AC4: =Assumptions!$B$22 -> 132000 | AD4: =Assumptions!$B$22 -> 132000 | AE4: =Assumptions!$B$22 -> 132000 | AF4: =Assumptions!$B$22 -> 132000 | AG4: =Assumptions!$B$22 -> 132000 | AH4: =Assumptions!$B$22 -> 132000 | AI4: =Assumptions!$B$22*0.5+$B$19 -> 1073379
A5: Component | B5: Annual | C5: Per SF | G5: Note | J5: =-Assumptions!$B$15 -> -1100000 | K5: =Assumptions!$B$22 -> 132000 | L5: =Assumptions!$B$22 -> 132000 | M5: =Assumptions!$B$22 -> 132000 | N5: =Assumptions!$B$22 -> 132000 | O5: =Assumptions!$B$22 -> 132000 | P5: =Assumptions!$B$22 -> 132000 | Q5: =Assumptions!$B$22*0.5+$B$20 -> 1112909.4 | S5: =-Assumptions!$B$16 -> -1250000 | T5: =Assumptions!$B$22 -> 132000 | U5: =Assumptions!$B$22 -> 132000 | V5: =Assumptions!$B$22 -> 132000 | W5: =Assumptions!$B$22 -> 132000 | X5: =Assumptions!$B$22 -> 132000 | Y5: =Assumptions!$B$22 -> 132000 | Z5: =Assumptions!$B$22*0.5+$B$20 -> 1112909.4 | AB5: =-Assumptions!$B$14 -> -1600000 | AC5: =Assumptions!$B$22 -> 132000 | AD5: =Assumptions!$B$22 -> 132000 | AE5: =Assumptions!$B$22 -> 132000 | AF5: =Assumptions!$B$22 -> 132000 | AG5: =Assumptions!$B$22 -> 132000 | AH5: =Assumptions!$B$22 -> 132000 | AI5: =Assumptions!$B$22*0.5+$B$20 -> 1112909.4
A6: Base rent | B6: =Assumptions!$B$22 -> 132000 | C6: =B6/Assumptions!$B$7 -> 30 | G6: Contractual | J6: =-Assumptions!$B$15 -> -1100000 | K6: =Assumptions!$B$22 -> 132000 | L6: =Assumptions!$B$22 -> 132000 | M6: =Assumptions!$B$22 -> 132000 | N6: =Assumptions!$B$22 -> 132000 | O6: =Assumptions!$B$22 -> 132000 | P6: =Assumptions!$B$22 -> 132000 | Q6: =Assumptions!$B$22*0.5+$B$21 -> 1231500.5 | S6: =-Assumptions!$B$16 -> -1250000 | T6: =Assumptions!$B$22 -> 132000 | U6: =Assumptions!$B$22 -> 132000 | V6: =Assumptions!$B$22 -> 132000 | W6: =Assumptions!$B$22 -> 132000 | X6: =Assumptions!$B$22 -> 132000 | Y6: =Assumptions!$B$22 -> 132000 | Z6: =Assumptions!$B$22*0.5+$B$21 -> 1231500.5 | AB6: =-Assumptions!$B$14 -> -1600000 | AC6: =Assumptions!$B$22 -> 132000 | AD6: =Assumptions!$B$22 -> 132000 | AE6: =Assumptions!$B$22 -> 132000 | AF6: =Assumptions!$B$22 -> 132000 | AG6: =Assumptions!$B$22 -> 132000 | AH6: =Assumptions!$B$22 -> 132000 | AI6: =Assumptions!$B$22*0.5+$B$21 -> 1231500.5
A7: Property taxes | B7: =Assumptions!$B$36 -> 39402 | C7: =B7/Assumptions!$B$7 -> 8.955 | G7: Estimate - confirm the actual bill | J7: =-Assumptions!$B$15 -> -1100000 | K7: =Assumptions!$B$22 -> 132000 | L7: =Assumptions!$B$22 -> 132000 | M7: =Assumptions!$B$22 -> 132000 | N7: =Assumptions!$B$22 -> 132000 | O7: =Assumptions!$B$22 -> 132000 | P7: =Assumptions!$B$22 -> 132000 | Q7: =Assumptions!$B$22*0.5+$B$22 -> 1310561.2 | S7: =-Assumptions!$B$16 -> -1250000 | T7: =Assumptions!$B$22 -> 132000 | U7: =Assumptions!$B$22 -> 132000 | V7: =Assumptions!$B$22 -> 132000 | W7: =Assumptions!$B$22 -> 132000 | X7: =Assumptions!$B$22 -> 132000 | Y7: =Assumptions!$B$22 -> 132000 | Z7: =Assumptions!$B$22*0.5+$B$22 -> 1310561.2 | AB7: =-Assumptions!$B$14 -> -1600000 | AC7: =Assumptions!$B$22 -> 132000 | AD7: =Assumptions!$B$22 -> 132000 | AE7: =Assumptions!$B$22 -> 132000 | AF7: =Assumptions!$B$22 -> 132000 | AG7: =Assumptions!$B$22 -> 132000 | AH7: =Assumptions!$B$22 -> 132000 | AI7: =Assumptions!$B$22*0.5+$B$22 -> 1310561.2
A8: Insurance | B8: =Assumptions!$B$37 -> 12000 | C8: =B8/Assumptions!$B$7 -> 2.7272727 | G8: Cannabis-use premium loading | J8: =-Assumptions!$B$15 -> -1100000 | K8: =Assumptions!$B$22 -> 132000 | L8: =Assumptions!$B$22 -> 132000 | M8: =Assumptions!$B$22 -> 132000 | N8: =Assumptions!$B$22 -> 132000 | O8: =Assumptions!$B$22 -> 132000 | P8: =Assumptions!$B$22 -> 132000 | Q8: =Assumptions!$B$22*0.5+$B$23 -> 1389621.9 | S8: =-Assumptions!$B$16 -> -1250000 | T8: =Assumptions!$B$22 -> 132000 | U8: =Assumptions!$B$22 -> 132000 | V8: =Assumptions!$B$22 -> 132000 | W8: =Assumptions!$B$22 -> 132000 | X8: =Assumptions!$B$22 -> 132000 | Y8: =Assumptions!$B$22 -> 132000 | Z8: =Assumptions!$B$22*0.5+$B$23 -> 1389621.9 | AB8: =-Assumptions!$B$14 -> -1600000 | AC8: =Assumptions!$B$22 -> 132000 | AD8: =Assumptions!$B$22 -> 132000 | AE8: =Assumptions!$B$22 -> 132000 | AF8: =Assumptions!$B$22 -> 132000 | AG8: =Assumptions!$B$22 -> 132000 | AH8: =Assumptions!$B$22 -> 132000 | AI8: =Assumptions!$B$22*0.5+$B$23 -> 1389621.9
A9: Maintenance / CAM | B9: =Assumptions!$B$38 -> 10000 | C9: =B9/Assumptions!$B$7 -> 2.2727273 | G9: Roof, HVAC, lot | J9: =-Assumptions!$B$15 -> -1100000 | K9: =Assumptions!$B$22 -> 132000 | L9: =Assumptions!$B$22 -> 132000 | M9: =Assumptions!$B$22 -> 132000 | N9: =Assumptions!$B$22 -> 132000 | O9: =Assumptions!$B$22 -> 132000 | P9: =Assumptions!$B$22 -> 132000 | Q9: =Assumptions!$B$22*0.5+$B$24 -> 1508213 | S9: =-Assumptions!$B$16 -> -1250000 | T9: =Assumptions!$B$22 -> 132000 | U9: =Assumptions!$B$22 -> 132000 | V9: =Assumptions!$B$22 -> 132000 | W9: =Assumptions!$B$22 -> 132000 | X9: =Assumptions!$B$22 -> 132000 | Y9: =Assumptions!$B$22 -> 132000 | Z9: =Assumptions!$B$22*0.5+$B$24 -> 1508213 | AB9: =-Assumptions!$B$14 -> -1600000 | AC9: =Assumptions!$B$22 -> 132000 | AD9: =Assumptions!$B$22 -> 132000 | AE9: =Assumptions!$B$22 -> 132000 | AF9: =Assumptions!$B$22 -> 132000 | AG9: =Assumptions!$B$22 -> 132000 | AH9: =Assumptions!$B$22 -> 132000 | AI9: =Assumptions!$B$22*0.5+$B$24 -> 1508213
A10: GROSS OCCUPANCY COST | B10: =SUM(B6:B9) -> 193402 | C10: =B10/Assumptions!$B$7 -> 43.955 | G10: What the store must carry, not just the rent | J10: =-Assumptions!$B$15 -> -1100000 | K10: =Assumptions!$B$22 -> 132000 | L10: =Assumptions!$B$22 -> 132000 | M10: =Assumptions!$B$22 -> 132000 | N10: =Assumptions!$B$22 -> 132000 | O10: =Assumptions!$B$22 -> 132000 | P10: =Assumptions!$B$22 -> 132000 | Q10: =Assumptions!$B$22*0.5+$B$25 -> 1626804.1 | S10: =-Assumptions!$B$16 -> -1250000 | T10: =Assumptions!$B$22 -> 132000 | U10: =Assumptions!$B$22 -> 132000 | V10: =Assumptions!$B$22 -> 132000 | W10: =Assumptions!$B$22 -> 132000 | X10: =Assumptions!$B$22 -> 132000 | Y10: =Assumptions!$B$22 -> 132000 | Z10: =Assumptions!$B$22*0.5+$B$25 -> 1626804.1 | AB10: =-Assumptions!$B$14 -> -1600000 | AC10: =Assumptions!$B$22 -> 132000 | AD10: =Assumptions!$B$22 -> 132000 | AE10: =Assumptions!$B$22 -> 132000 | AF10: =Assumptions!$B$22 -> 132000 | AG10: =Assumptions!$B$22 -> 132000 | AH10: =Assumptions!$B$22 -> 132000 | AI10: =Assumptions!$B$22*0.5+$B$25 -> 1626804.1
A12: Store sales scenario | B12: $1.5M | C12: $2.0M | D12: $2.5M | E12: $3.0M | F12: $3.9M | G12: Assessment
A13: Occupancy cost as % of sales | B13: =$B$10/1500000 -> 0.12893467 | C13: =$B$10/2000000 -> 0.096701 | D13: =$B$10/2500000 -> 0.0773608 | E13: =$B$10/3000000 -> 0.064467333 | F13: =$B$10/3900000 -> 0.049590256 | G13: Cannabis retail is generally healthy below ~7% and stressed above ~9%
A14: Verdict | B14: =IF(B13>0.09,"Distressed",IF(B13>0.07,"Tight",IF(B13>0.055,"Workable","Healthy"))) -> Distressed | C14: =IF(C13>0.09,"Distressed",IF(C13>0.07,"Tight",IF(C13>0.055,"Workable","Healthy"))) -> Distressed | D14: =IF(D13>0.09,"Distressed",IF(D13>0.07,"Tight",IF(D13>0.055,"Workable","Healthy"))) -> Tight | E14: =IF(E13>0.09,"Distressed",IF(E13>0.07,"Tight",IF(E13>0.055,"Workable","Healthy"))) -> Workable | F14: =IF(F13>0.09,"Distressed",IF(F13>0.07,"Tight",IF(F13>0.055,"Workable","Healthy"))) -> Healthy | G14: NJ certified 2025 sales of $1.164bn across ~300 stores average $3.88M per store, but that average is carried by multi-state operators
A15: Sales needed to keep occupancy under 9% | B15: =$B$10/0.09 -> 2148911.1 | C15: THE key diligence item: get the tenant's actual sales. This single number drives the renewal probability that the whole model turns on.
A17: 2. SENSITIVITY — how wrong can the renewal assumption be?
A18: Probability the tenant renews | B18: Weighted reversion | C18: IRR at our offer | D18: IRR at the ceiling | E18: IRR at the ask | G18: Read
A19: 0.2 | B19: =A19*'Reversion Scenarios'!$G$5+(1-A19)*(SUMPRODUCT('Reversion Scenarios'!$B$6:$B$10,'Reversion Scenarios'!$G$6:$G$10)/SUM('Reversion Scenarios'!$B$6:$B$10)) -> 1007379 | C19: =IRR(J4:Q4) -> 0.10503369 | D19: =IRR(S4:Z4) -> 0.077737388 | E19: =IRR(AB4:AI4) -> 0.028540821 | G19: Deeply pessimistic
A20: 0.25 | B20: =A20*'Reversion Scenarios'!$G$5+(1-A20)*(SUMPRODUCT('Reversion Scenarios'!$B$6:$B$10,'Reversion Scenarios'!$G$6:$G$10)/SUM('Reversion Scenarios'!$B$6:$B$10)) -> 1046909.4 | C20: =IRR(J5:Q5) -> 0.10889611 | D20: =IRR(S5:Z5) -> 0.081591145 | E20: =IRR(AB5:AI5) -> 0.032363025 | G20: Deeply pessimistic
A21: 0.4 | B21: =A21*'Reversion Scenarios'!$G$5+(1-A21)*(SUMPRODUCT('Reversion Scenarios'!$B$6:$B$10,'Reversion Scenarios'!$G$6:$G$10)/SUM('Reversion Scenarios'!$B$6:$B$10)) -> 1165500.5 | C21: =IRR(J6:Q6) -> 0.11995498 | D21: =IRR(S6:Z6) -> 0.092618379 | E21: =IRR(AB6:AI6) -> 0.043288476 | G21: Base case
A22: 0.5 | B22: =A22*'Reversion Scenarios'!$G$5+(1-A22)*(SUMPRODUCT('Reversion Scenarios'!$B$6:$B$10,'Reversion Scenarios'!$G$6:$G$10)/SUM('Reversion Scenarios'!$B$6:$B$10)) -> 1244561.2 | C22: =IRR(J7:Q7) -> 0.12692943 | D22: =IRR(S7:Z7) -> 0.099567967 | E22: =IRR(AB7:AI7) -> 0.050165653
A23: 0.6 | B23: =A23*'Reversion Scenarios'!$G$5+(1-A23)*(SUMPRODUCT('Reversion Scenarios'!$B$6:$B$10,'Reversion Scenarios'!$G$6:$G$10)/SUM('Reversion Scenarios'!$B$6:$B$10)) -> 1323621.9 | C23: =IRR(J8:Q8) -> 0.13361917 | D23: =IRR(S8:Z8) -> 0.10623053 | E23: =IRR(AB8:AI8) -> 0.056753164
A24: 0.75 | B24: =A24*'Reversion Scenarios'!$G$5+(1-A24)*(SUMPRODUCT('Reversion Scenarios'!$B$6:$B$10,'Reversion Scenarios'!$G$6:$G$10)/SUM('Reversion Scenarios'!$B$6:$B$10)) -> 1442213 | C24: =IRR(J9:Q9) -> 0.1431729 | D24: =IRR(S9:Z9) -> 0.11574006 | E24: =IRR(AB9:AI9) -> 0.066146576 | G24: Optimistic
A25: 0.9 | B25: =A25*'Reversion Scenarios'!$G$5+(1-A25)*(SUMPRODUCT('Reversion Scenarios'!$B$6:$B$10,'Reversion Scenarios'!$G$6:$G$10)/SUM('Reversion Scenarios'!$B$6:$B$10)) -> 1560804.1 | C25: =IRR(J10:Q10) -> 0.15221088 | D25: =IRR(S10:Z10) -> 0.12473077 | E25: =IRR(AB10:AI10) -> 0.075018343 | G25: Optimistic
A26: Even at a 20% renewal probability - far more pessimistic than we think reasonable - our offer still returns over 10%. The conclusion does not depend on the 40% assumption. At the asking price, even a 90% renewal probability only reaches 7.5%.
A29: 3. SENSITIVITY — what if market rent is wrong?
A30: Market rent / SF | B30: NOI | C30: Yield on our offer | D30: Value at 8.75% cap | E30: vs our basis | G30: Read
A31: 16 | B31: =A31*Assumptions!$B$7 -> 70400 | C31: =B31/Assumptions!$B$15 -> 0.064 | D31: =B31/0.0875 -> 804571.43 | E31: =D31/Assumptions!$B$15-1 -> -0.26857143 | G31: Below anything on the corridor
A32: 18 | B32: =A32*Assumptions!$B$7 -> 79200 | C32: =B32/Assumptions!$B$15 -> 0.072 | D32: =B32/0.0875 -> 905142.86 | E32: =D32/Assumptions!$B$15-1 -> -0.17714286
A33: 20 | B33: =A33*Assumptions!$B$7 -> 88000 | C33: =B33/Assumptions!$B$15 -> 0.08 | D33: =B33/0.0875 -> 1005714.3 | E33: =D33/Assumptions!$B$15-1 -> -0.085714286
A34: 22 | B34: =A34*Assumptions!$B$7 -> 96800 | C34: =B34/Assumptions!$B$15 -> 0.088 | D34: =B34/0.0875 -> 1106285.7 | E34: =D34/Assumptions!$B$15-1 -> 0.0057142857 | G34: Base case - our underwriting
A35: 24 | B35: =A35*Assumptions!$B$7 -> 105600 | C35: =B35/Assumptions!$B$15 -> 0.096 | D35: =B35/0.0875 -> 1206857.1 | E35: =D35/Assumptions!$B$15-1 -> 0.097142857
A36: 26 | B36: =A36*Assumptions!$B$7 -> 114400 | C36: =B36/Assumptions!$B$15 -> 0.104 | D36: =B36/0.0875 -> 1307428.6 | E36: =D36/Assumptions!$B$15-1 -> 0.18857143
A37: Market rent would have to fall to about $18/SF - below every conventional comp on the corridor except in-line strip space - before our basis stopped being covered by the building alone.
A40: 4. THE EXIT — who buys it from us in 2033
A41: Exit scenario | B41: NOI at exit | C41: Exit cap | D41: Value | G41: Buyer pool
A42: Renewed cannabis lease, 5 years term | B42: 154000 | C42: 0.0925 | D42: =IF(C42="-",750000,B42/C42) -> 1664864.9 | G42: Cannabis net-lease buyers only - all-cash, limited pool, wide caps
A43: Re-let to bank / credit union, 10-15 yr NNN with bumps | B43: 105600 | C43: 0.08 | D43: =IF(C43="-",750000,B43/C43) -> 1320000 | G43: NON-cannabis covenant: bankable and CMBS-eligible, national net-lease buyer pool
A44: Re-let to medical / urgent care, 10-15 yr NNN with bumps | B44: 105600 | C44: 0.0775 | D44: =IF(C44="-",750000,B44/C44) -> 1362580.6 | G44: Medical net lease trades tighter still; deepest institutional demand
A45: Vacant - land and shell | B45: - | C45: - | D45: =IF(C45="-",750000,B45/C45) -> 750000 | G45: Local owner-user or developer
A47: THE COUNTER-INTUITIVE POINT: losing the cannabis tenant is not purely a downside. A conventional covenant - a bank, credit union or medical group on a 10-15 year NNN lease WITH escalations - removes the financing constraint entirely. That widens the buyer pool from cash-only cannabis specialists to the whole institutional net-lease market, and is worth roughly 75-125 bps of exit cap rate. Re-tenanting costs money up front and buys a more valuable, more liquid asset.

Sheet Lease Comps
A1: LEASE COMPS — local like-and-kind rents, South Jersey / Route 30 corridor
A2: Asking rates, NNN. Tier 1 is like-and-kind (freestanding with a drive-thru); Tier 2 is submarket context.
A4: TIER 1 — LIKE AND KIND: freestanding buildings with a drive-thru
A5: Comparable | B5: Type | C5: SF | D5: Rent / SF | E5: Annual | F5: Drive-thru | G5: Corner | H5: Read-through
A6: 451 White Horse Pike, Atco - SUBJECT | B6: Freestanding, drive-thru, cannabis | C6: 4400 | D6: 30 | E6: =IF(ISNUMBER(D6),D6*C6,"-") -> 132000 | F6: 3-lane | G6: Yes | H6: In place. 36% above conventional market - a premium that expires with the tenant
A7: 340 S White Horse Pike, Berlin | B7: Freestanding retail w/ drive-thru | C7: 1750 | D7: 27.43 | E7: =IF(ISNUMBER(D7),D7*C7,"-") -> 48002.5 | F7: Yes | G7: - | H7: The best direct comp we have ($4,000/mo). But it is a small box - and small boxes always earn more per foot, so a 4,400 SF building will not beat this rate
A8: 804 N White Horse Pike, Magnolia | B8: Former Arby's, drive-thru, 38 spaces | C8: 3035 | D8: On req. | E8: - | F8: Yes | G8: - | H8: Rate on request. Closest second-generation drive-thru analogue on the corridor - worth a call to the listing broker to pin the number
A9: 2 S White Horse Pike, Stratford | B9: Freestanding QSR (Freebyrd Chicken) | C9: - | D9: On req. | E9: - | F9: Yes | G9: Yes | H9: Corner freestanding QSR on the same pike - evidence of active drive-thru demand on this corridor
A11: TIER 2 — SUBMARKET CONTEXT: what retail generally clears on this corridor
A12: Comparable | B12: Type | C12: SF | D12: Rent / SF | E12: Annual | F12: Drive-thru | G12: Corner | H12: Read-through
A13: NJ medical office average | B13: Medical | C13: - | D13: 24 | E13: =D13*Assumptions!$B$7 -> 105600 | F13: - | G13: - | H13: Ceiling for a healthcare backfill - and healthcare is the deepest demand pool for this box
A14: Berlin submarket average | B14: Retail, all formats | C14: - | D14: 21 | E14: =D14*Assumptions!$B$7 -> 92400 | F14: - | G14: - | H14: Adjacent submarket, comparable demographics
A15: Sicklerville submarket average | B15: Retail, all formats | C15: - | D15: 20 | E15: =D15*Assumptions!$B$7 -> 88000 | F15: - | G15: - | H15: Adjacent submarket, comparable demographics
A16: Hammonton submarket average | B16: Retail, all formats | C16: - | D16: 20 | E16: =D16*Assumptions!$B$7 -> 88000 | F16: - | G16: - | H16: Route 30 east, comparable
A17: Atco submarket average | B17: Retail, all formats | C17: - | D17: 13 | E17: =D17*Assumptions!$B$7 -> 57200 | F17: - | G17: - | H17: This is in-line strip space, which is why it is low. Our freestanding corner drive-thru format beats it comfortably - do not read this as our market rent
A18: 706 N White Horse Pike, Magnolia | B18: Flex / industrial | C18: 40000 | D18: 11.5 | E18: =D18*Assumptions!$B$7 -> 50600 | F18: - | G18: - | H18: Scale reference only - large boxes on this pike clear in the low teens
A20: CONCLUDED MARKET RENT
A21: CONVENTIONAL MARKET RENT - SUBJECT | B21: Freestanding, drive-thru, corner, large lot | C21: =Assumptions!$B$7 -> 4400 | D21: =Assumptions!$B$31 -> 22 | E21: =Assumptions!$B$31*Assumptions!$B$7 -> 96800 | F21: 3-lane | G21: Yes | H21: The floor our offer is built on. Range $20-$24/SF; base case $22
A23: TIER 3 — COMPARABLES SUPPLIED BY THE LISTING AGENT
A24: Tenant | B24: Location | C24: SF | D24: Rent / SF | E24: Annual | F24: Deal type | G24: Useful? | H24: What it actually shows
A25: 7 Brew | B25: 1390 Blackwood-Clementon Rd, Clementon | C25: 510 | D25: =E25/C25 -> 303.92157 | E25: 155000 | F25: Build-to-suit | G25: No | H25: A 510 SF coffee kiosk at an apparent $303.92/SF. Nobody rents a building at that rate - the rent is for the PAD and drive-thru lanes, not the hut
A26: Wawa | B26: 301 White Horse Pike, Chesilhurst | C26: 5585 | D26: =E26/C26 -> 58.191585 | E26: 325000 | F26: Build-to-suit | G26: No | H26: Purpose-built store with fuel on a large pad; rent repays land AND construction
A27: Wendy's | B27: 69 NJ-73, Voorhees | C27: 3321 | D27: =E27/C27 -> 47.473351 | E27: 157659 | F27: Build-to-suit | G27: No | H27: Purpose-built drive-thru restaurant - same land-plus-building economics
A28: 501 Delsea Dr | B28: Sewell - lease signed 5 Jul | C28: 1373 | D28: =E28/C28 -> 39.329934 | E28: 54000 | F28: 2nd generation | G28: Partly | H28: A genuine letting, but a very small unit - small units always rent high per foot
A29: Walgreens | B29: 625 N Black Horse Pike, Blackwood | C29: 14870 | D29: =E29/C29 -> 31.191863 | E29: 463823 | F29: Credit BTS | G29: No | H29: Purpose-built pharmacy for a national credit tenant on a long-standing rent
A30: Avis Budget | B30: 341 N White Horse Pike, Lawnside - signed 5 Jun 2025 | C30: 3300 | D30: =E30/C30 -> 27.96 | E30: 92268 | F30: 2nd generation | G30: YES | H30: THE ONE GENUINELY USEFUL COMP: second-hand building, same road, closest size to ours, recently signed
A31: ALDI | B31: 142 NJ-73, Voorhees | C31: 19054 | D31: =E31/C31 -> 12.960533 | E31: 246950 | F31: Grocery big box | G31: No | H31: At $12.96/SF it shows the opposite end of the same size effect - big buildings rent low per foot
A33: ADJUSTING THE TWO GENUINE LETTINGS TO OUR BUILDING
A34: Adjustment | B34: Avis, Lawnside | C34: Berlin drive-thru | H34: Reasoning
A35: Starting rent | B35: 27.96 | C35: 27.43 | H35: Avis signed Jun-2025; Berlin is an asking rate
A36: Bigger building than the comp | B36: 0.9 | C36: 0.8 | H36: Ours is 4,400 SF; larger boxes rent lower per foot
A37: Atco is softer than Lawnside | B37: 0.9 | C37: 1 | H37: Lawnside is denser and closer in
A38: 10-15 yr lease vs a 3-yr deal | B38: 0.95 | C38: 1 | H38: Short leases carry a premium rate
A39: INDICATED RENT FOR OUR BUILDING | B39: =B35*B36*B37*B38 -> 21.51522 | C39: =C35*C36*C37*C38 -> 21.944 | H39: Two independent routes converging on ~$22 - the seller's own evidence confirms the market rent we used
A41: HOW WE GOT TO $22 — the adjustment reasoning
A42: Start from the submarket | B42: Berlin, Sicklerville and Hammonton all cluster at $20-21/SF for general retail. That is the base.
A43: Add for freestanding format | B43: A standalone building with its own identity, signage and parking field commands a premium over in-line strip space. Atco's $13/SF average is in-line space and is not our comp.
A44: Add for the drive-thru | B44: The Berlin comp at $27.43/SF is a freestanding drive-thru - the only priced like-and-kind evidence we have. It is a 1,750 SF box, and small boxes always carry a higher rate per foot.
A45: Add for the corner | B45: Two frontages, signage on both, and secondary-road access. A real premium over mid-block, and what makes the drive-thru circulation work at all.
A46: Subtract for size | B46: At 4,400 SF this is roughly 2.5x the Berlin comp. Larger boxes lease at lower rates per foot, which pulls us back down from $27.
A47: Land at $20-$24, base $22 | B47: Below the small-box drive-thru comp, above the general submarket average. Our entire offer is built on the assumption that this box re-lets at $22 - and the deal still works at $18.
A49: Submarket averages are asking-rate averages published by commercial listing platforms, not verified closed leases. Verify against CoStar comparable-lease data in diligence. Note that our offer holds even at the bottom of this range.

Sheet Sale Comps
A1: SALE COMPS — cannabis net lease transactions and benchmarks
A2: Cannabis dispensaries trade 7.4%-9.35%. Our entry at 12.0% is wider than every comp in the set.
A4: Comparable | B4: Price | C4: Cap rate | D4: Note | E4: Status
A5: STNL market average, Q1 2026 | B5: - | C5: 0.068 | D5: All tenants, all sectors | E5: Benchmark
A6: Jungle Boys - Naples, FL | B6: - | C6: 0.074 | D6: Dispensary with 2% annual increases | E6: Listing
A7: Cookies - Kalamazoo, MI | B7: 3100000 | C7: 0.0825 | D7: 10 years remaining, corporate guarantee | E7: Listing
A8: SUBJECT at the $1.6M asking price | B8: 1600000 | C8: 0.0825 | D8: 6.5 years, flat rent, personal guarantees only | E8: Asking
A9: LivWell - Aurora, CO | B9: 1025000 | C9: 0.0887 | D9: Closed April 2026 | E9: CLOSED
A10: Ascend - Pennsylvania | B10: - | C10: 0.0925 | D10: Medical-only market | E10: Listing
A11: Curaleaf - Worth, IL | B11: - | C11: 0.0935 | D11: 10% rent increases every 5 years | E11: Listing
A12: Weaker private credit - 2026 guide | B12: - | C12: 0.0875 | D12: Published range 8.00%-9.50%. The subject's true credit tier | E12: Benchmark
A13: SUBJECT AT OUR OFFER | B13: =Assumptions!$B$15 -> 1100000 | C13: =Assumptions!$B$22/Assumptions!$B$15 -> 0.12 | D13: Wider than every comparable transaction in the set | E13: OUR BID
A15: ADJUSTMENT GRID — why this asset belongs wide of the comp set
A16: Attribute | B16: Comp set | C16: Subject | D16: Adjustment
A17: Guarantee | B17: Corporate / MSO guarantees | C17: Two personal guarantees, single-store operator | D17: +50 to +100 bps
A18: Rent escalations | B18: 2% annual or 10% every 5 years | C18: Flat - 0% for the full base term | D18: +50 to +75 bps
A19: Rent vs. market | B19: Generally at or near market | C19: ~36% above conventional market rent | D19: +50 to +75 bps
A20: Term remaining | B20: 8-15 years typical | C20: 6.5 years | D20: +25 to +50 bps
A21: Market fundamentals | B21: Mixed; several limited-licence states | C21: NJ - 300+ stores, flower -23% YoY | D21: +25 bps
A22: Real estate quality | B22: Varies | C22: Corner, drive-thru, 3.13 AC, below replacement cost | D22: -50 to -75 bps
A23: Licensing moat | B23: Varies | C23: Waterford caps retail cannabis at two licences | D23: -25 bps
A24: Fair cap rate, fully adjusted | B24: 9.25% - 10.25% | C24: Implying a value of $1.29M - $1.43M | D24: =Assumptions!$B$22/Assumptions!$B$15 -> 0.12 | E24: our entry
A26: Cannabis comps are drawn from public brokerage listings and transaction announcements; only the LivWell trade is confirmed closed. Benchmarks are published Q1 2026 net lease research. Re-run against CoStar, Crexi and Camden County deed records before hard money.

Sheet Risks & Diligence
A1: RISKS AND DILIGENCE
A2: The risks are real - they are also why the asset is available at 12% instead of 8.25%.
A4: RISK REGISTER — and how the price answers each one
A5: Risk | B5: How our offer price answers it
A6: Rent is 36% above market | B6: We capitalized the MARKET rent, not the contract rent, to set our price. The premium is upside we did not pay for.
A7: Flat rent, no escalations | B7: Priced in at a 12% entry. We do not need growth - we need the coupon, and the coupon returns 78% of capital before expiry.
A8: Personal guarantees only | B8: Worth ~75 bps of cap rate; we took 375. Verify guarantor net worth in diligence, but the basis does not depend on it.
A9: NJ cannabis price compression | B9: The reason this is a 12% deal and not an 8% one. Our downside case already assumes the tenant fails.
A10: Financing is hard for cannabis collateral | B10: At a 12% cap, private debt at 9-11% is POSITIVE leverage. At the 8.25% ask it would have been negative.
A11: Special-purpose improvements | B11: Cuts both ways - narrows the pool, but makes us the only compliant drive-thru site on the corridor for banks, medical and cannabis alike.
A12: Reassessment on sale | B12: A $1.1M deed sits BELOW the assessor's $1.27M implied value - buying at our number argues for an appeal, not an increase.
A13: GLA discrepancy (4,400 vs 4,206 SF) | B13: Confirm by measurement. At our price the difference is ~$12/SF - material to reporting, not to the decision.
A15: DILIGENCE CHECKLIST — confirm before hard money
A16: Tenant & lease
A17: ☐ Tenant sales reports and P&L - occupancy cost runs ~$193,400 all-in; at $3.0M of store sales that is a workable 6.4%
A18: ☐ DEMISED PREMISES CLAUSE - does the lease include the full 3.13 AC? Gates all land upside
A19: ☐ Complete lease with all amendments; confirm roof, structure and HVAC allocation
A20: ☐ Both personal guarantees - scope, caps, burn-off, joint-and-several
A21: ☐ Guarantor personal financial statements and net worth verification
A22: ☐ Estoppel certificate, SNDA, and full rent payment history since 2023
A24: Regulatory & physical
A25: ☐ CRC licence status, expiry and site-specific conditions
A26: ☐ Waterford Township approval and status of the two-licence cap
A27: ☐ Pinelands Commission jurisdiction; sewer vs. septic capacity
... A31: ☐ Phase I ESA, ALTA survey, title, zoning compliance letter
